Workbook

Sheet INICIO
A1: CONTROL ADMINISTRATIVO – RESTAURANTE / HELADERÍA
A2: Inventario, costos, recetas, planilla, gastos, caja y reportes en un solo libro.
B4: Negocio: | C4: =NEGOCIO -> La Cremería
B6: CÓMO LEER LOS COLORES
B7: Azul claro, letra azul | C7: Celda para LLENAR por usted (datos de entrada).
B8: Gris | C8: Se calcula sola. No la escriba (tiene fórmula).
B9: Letra verde | C9: Viene de otra hoja (enlace).
B10: Amarillo | C10: Resultado o supuesto clave.
B12: ORDEN DE USO
B13: CONFIG | C13: 1 sola vez: nombre, año, % IVA, cargas sociales CCSS/INS, márgenes objetivo y listas desplegables.
B14: INSUMOS | C14: Catálogo de materias primas y empaques: presentación de compra, precio, % aprovechamiento, stock mínimo e inicial. Aquí ve el INVENTARIO ACTUAL, su valor y qué reordenar.
B15: COMPRAS | C15: Registre cada factura de proveedor. Suma al inventario y actualiza el último costo del insumo. Controle pendientes de pago.
B16: RECETAS | C16: Una línea por ingrediente de cada producto (cantidad neta por porción o por lote). Calcula el costo de cada receta.
B17: FICHA_TECNICA | C17: Elija un producto y vea su ficha técnica: ingredientes, costo, margen, precio sugerido y preparación.
B18: PRODUCTOS | C18: Menú con precio de venta (con IVA). Calcula costo variable, contribución, food cost y precio sugerido.
B19: VENTAS | C19: Registre ventas (por ticket o total diario por producto). Descuenta el inventario según las recetas.
B20: MERMAS | C20: Mermas, vencidos, cortesías y ajustes de conteo físico. Afectan inventario y resultados.
B21: PLANILLA | C21: Planilla mensual: salario, horas extra, CCSS obrera/patronal, INS, aguinaldo, vacaciones, cesantía.
B22: GASTOS | C22: Gastos operativos (alquiler, luz, agua, internet, publicidad, contador, etc.).
B23: CAJA_DIARIA | C23: Cierre de caja: fondo, ventas por medio de pago, efectivo esperado vs contado, faltantes/sobrantes.
B24: ESTADO_RESULTADOS | C24: Automático: ventas, costo de ventas, utilidad, planilla, gastos, indicadores e IVA por mes.
... B27: DASHBOARD | C27: Resumen del mes elegido: KPIs, productos más rentables, insumos por reordenar y gráfico anual.
B29: REGLAS DE ORO
B30: • | C30: Precios de venta con IVA en PRODUCTOS; los análisis usan el precio NETO (sin IVA), como en la capacitación.
B31: • | C31: Las recetas usan cantidades NETAS aprovechables (g, ml o unidades). El % de aprovechamiento convierte a cantidad bruta comprada.
B32: • | C32: La planilla fija va una sola vez (en PLANILLA), nunca dentro del costo de las recetas.
B33: • | C33: Use el mismo período en todo y no duplique costos (p. ej., no meta en GASTOS lo que ya está en COMPRAS de insumos).
B34: • | C34: Haga un conteo físico al menos semanal en INSUMOS (columna 'Conteo físico') para detectar faltantes.
B35: • | C35: Los datos que trae el libro son EJEMPLOS ilustrativos: bórrelos o reemplácelos por los suyos. Verifique tasas CCSS/INS/renta vigentes con su contador.

Sheet CONFIG
A1: CONFIGURACIÓN Y PARÁMETROS
A2: Llene las celdas azules. Las demás hojas usan estos valores por su nombre (p. ej. IVA_VENTAS).
F4: LISTAS DESPLEGABLES (puede agregar opciones en las celdas azules vacías)
B5: Parámetro | C5: Valor | D5: Nota / fuente | F5: Categorías de insumo | G5: Unidades base | H5: Categorías de gasto | I5: Medios de pago | J5: Movimientos de inventario | K5: Canales de venta | L5: Forma de pago compras | M5: Estado de pago | N5: Tipo de gasto | O5: Categorías de producto
B6: Nombre del negocio | C6: La Cremería | D6: Aparece en reportes. | F6: Fruta | G6: g | H6: Alquiler | I6: Efectivo | J6: Merma | K6: Local | L6: Contado | M6: Pagado | N6: Fijo | O6: Fresas con crema
B7: Año del estado de resultados | C7: 2026 | D7: Columnas ene–dic de ESTADO_RESULTADOS. | F7: Lácteos | G7: ml | H7: Electricidad | I7: SINPE Móvil | J7: Vencimiento | K7: Para llevar | L7: Crédito | M7: Pendiente | N7: Variable | O7: Especiales
B8: Mes a analizar en el DASHBOARD | C8: 46296 | D8: Escriba el día 1 del mes. | F8: Abarrotes | G8: u | H8: Agua | I8: Tarjeta | J8: Daño | K8: WhatsApp | O8: Extras
B9: IVA en ventas | C9: 0.13 | D9: Tarifa general CR 13%. Se usa como valor por defecto en PRODUCTOS. | F9: Toppings | H9: Internet y teléfono | I9: Plataforma | J9: Consumo interno | K9: Delivery | O9: Postres
B10: IVA promedio en compras de insumos | C10: 0.05 | D10: Supuesto para el flujo de caja (mezcla canasta básica 1% y 13%). | F10: Jarabes y salsas | H10: Gas | I10: Transferencia | J10: Cortesía | O10: Bebidas
B11: CCSS cuota patronal | C11: 0.265 | D11: Valor usado en la capacitación (26.50%). Verifique la tasa vigente. | F11: Empaque | H11: Publicidad y redes | J11: Ajuste (-) faltante
B12: CCSS cuota obrera (rebajo al trabajador) | C12: 0.1067 | D12: Supuesto. Verifique la tasa vigente. | F12: Limpieza | H12: Servicios profesionales | J12: Ajuste (+) sobrante
B13: Póliza riesgos del trabajo (INS) | C13: 0.0185 | D13: Valor de la capacitación (1.85%). Depende de su póliza. | F13: Otros | H13: Mantenimiento y reparaciones
B14: Provisión aguinaldo | C14: 0.0833 | D14: 1/12 del salario. | H14: Limpieza
B15: Provisión vacaciones | C15: 0.0416 | D15: Valor de la capacitación (4.16%). | H15: Patentes, permisos y seguros
B16: Provisión cesantía / despidos | C16: 0.0533 | D16: Valor de la capacitación (5.33%). | H16: Comisiones tarjetas/plataformas
B17: Recargo hora extra (x salario/hora) | C17: 1.5 | D17: Tiempo y medio. | H17: Transporte y combustible
B18: Horas base por mes (salario/hora) | C18: 240 | D18: 30 días x 8 horas. | H18: Otros gastos
B19: Imprevistos en flujo de caja | C19: 0.05 | D19: Valor de la capacitación (5%).
B20: Impuesto sobre la renta estimado | C20: 0.15 | D20: Supuesto de la capacitación. Persona jurídica PYME / física tiene tramos: confirme con su contador.
B21: Margen de contribución objetivo | C21: 0.65 | D21: Para precio sugerido = costo ÷ (1 − margen).
B22: Food cost máximo aceptable | C22: 0.35 | D22: Si un producto lo supera se marca 'REVISAR PRECIO'.
B23: Días de operación por mes | C23: 26 | D23: Para venta diaria necesaria.
B24: Efectivo inicial en banco (flujo) | C24: 1500000 | D24: Saldo al inicio del flujo de caja.
B25: Mes de inicio del flujo de caja | C25: 46327 | D25: Día 1 del primer mes proyectado.
B26: Crecimiento mensual de ventas (flujo) | C26: 0.02 | D26: Supuesto de proyección.
B27: Meses de gastos fijos como reserva mínima | C27: 1 | D27: Si el saldo baja de esto, el flujo alerta.

Sheet DASHBOARD
A1: DASHBOARD DEL MES
A2: Cambie el mes en CONFIG → 'Mes a analizar en el DASHBOARD'.
B4: =NEGOCIO -> La Cremería | C4: =MES_REPORTE -> 46296 | F4: Meta food cost ≤ | G4: =FOODCOST_MAX -> 0.35
B5: Resultados | E5: Indicadores | H5: Control
B6: Ventas netas | C6: =IFERROR(INDEX(ESTADO_RESULTADOS!$C$9:$N$9,MATCH(MES_REPORTE,ESTADO_RESULTADOS!$C$5:$N$5,0)),0) -> 342212.39 | E6: Food cost % | F6: =IFERROR(INDEX(ESTADO_RESULTADOS!$C$37:$N$37,MATCH(MES_REPORTE,ESTADO_RESULTADOS!$C$5:$N$5,0)),0) -> 0.35242938 | H6: Valor del inventario hoy | I6: =SUM(INSUMOS!$U$6:$U$205) -> 388439.3
B7: Costo de ventas | C7: =IFERROR(INDEX(ESTADO_RESULTADOS!$C$10:$N$10,MATCH(MES_REPORTE,ESTADO_RESULTADOS!$C$5:$N$5,0)),0) -> 120605.7 | E7: Labor cost % | F7: =IFERROR(INDEX(ESTADO_RESULTADOS!$C$38:$N$38,MATCH(MES_REPORTE,ESTADO_RESULTADOS!$C$5:$N$5,0)),0) -> 4.9376506 | H7: Insumos por reordenar / agotados | I7: =COUNTIF(INSUMOS!$Y$6:$Y$205,"REORDENAR")+COUNTIF(INSUMOS!$Y$6:$Y$205,"AGOTADO") -> 1
B8: Utilidad bruta | C8: =IFERROR(INDEX(ESTADO_RESULTADOS!$C$11:$N$11,MATCH(MES_REPORTE,ESTADO_RESULTADOS!$C$5:$N$5,0)),0) -> 221606.69 | E8: Prime cost % | F8: =IFERROR(INDEX(ESTADO_RESULTADOS!$C$39:$N$39,MATCH(MES_REPORTE,ESTADO_RESULTADOS!$C$5:$N$5,0)),0) -> 5.2900799 | H8: Diferencias de conteo físico (₡) | I8: =SUM(INSUMOS!$X$6:$X$205) -> 0
B9: Gastos de operación (incl. planilla) | C9: =IFERROR(INDEX(ESTADO_RESULTADOS!$C$31:$N$31,MATCH(MES_REPORTE,ESTADO_RESULTADOS!$C$5:$N$5,0)),0) -> 2372680.2 | E9: Margen operativo % | F9: =IFERROR(INDEX(ESTADO_RESULTADOS!$C$33:$N$33,MATCH(MES_REPORTE,ESTADO_RESULTADOS!$C$5:$N$5,0)),0) -> -6.285785 | H9: Compras pendientes de pago | I9: =SUMIFS(COMPRAS!$M$6:$M$1005,COMPRAS!$P$6:$P$1005,"Pendiente") -> 51246
B10: UTILIDAD OPERATIVA | C10: =IFERROR(INDEX(ESTADO_RESULTADOS!$C$32:$N$32,MATCH(MES_REPORTE,ESTADO_RESULTADOS!$C$5:$N$5,0)),0) -> -2151073.5 | E10: IVA neto por pagar (estimado) | F10: =IFERROR(INDEX(ESTADO_RESULTADOS!$C$43:$N$43,MATCH(MES_REPORTE,ESTADO_RESULTADOS!$C$5:$N$5,0)),0) -> -49695.389 | H10: Productos con precio a revisar | I10: =COUNTIF(PRODUCTOS!$R$6:$R$105,"REVISAR PRECIO") -> 6
B12: Productos en el mes
B13: Producto | C13: Unidades | E13: Venta neta | F13: Contribución | H13: % de la contribución total | I13: Margen %
B14: =IF(PRODUCTOS!$A$6="","",PRODUCTOS!$B$6) -> Fresas con crema Pequeño (8 oz) | C14: =IF(PRODUCTOS!$A$6="","",SUMIFS(VENTAS!$E$6:$E$2005,VENTAS!$C$6:$C$2005,PRODUCTOS!$A$6,VENTAS!$O$6:$O$2005,MES_REPORTE)) -> 27 | E14: =IF(PRODUCTOS!$A$6="","",SUMIFS(VENTAS!$J$6:$J$2005,VENTAS!$C$6:$C$2005,PRODUCTOS!$A$6,VENTAS!$O$6:$O$2005,MES_REPORTE)) -> 46592.92 | F14: =IF(PRODUCTOS!$A$6="","",SUMIFS(VENTAS!$L$6:$L$2005,VENTAS!$C$6:$C$2005,PRODUCTOS!$A$6,VENTAS!$O$6:$O$2005,MES_REPORTE)) -> 28411.938 | H14: =IF(PRODUCTOS!$A$6="","",IFERROR(F14/SUM($F$14:$F$33),0)) -> 0.12820885 | I14: =IF(PRODUCTOS!$A$6="","",IFERROR(F14/E14,0)) -> 0.60979088
B15: =IF(PRODUCTOS!$A$7="","",PRODUCTOS!$B$7) -> Fresas con crema Mediano (12 oz) | C15: =IF(PRODUCTOS!$A$7="","",SUMIFS(VENTAS!$E$6:$E$2005,VENTAS!$C$6:$C$2005,PRODUCTOS!$A$7,VENTAS!$O$6:$O$2005,MES_REPORTE)) -> 40 | E15: =IF(PRODUCTOS!$A$7="","",SUMIFS(VENTAS!$J$6:$J$2005,VENTAS!$C$6:$C$2005,PRODUCTOS!$A$7,VENTAS!$O$6:$O$2005,MES_REPORTE)) -> 104424.78 | F15: =IF(PRODUCTOS!$A$7="","",SUMIFS(VENTAS!$L$6:$L$2005,VENTAS!$C$6:$C$2005,PRODUCTOS!$A$7,VENTAS!$O$6:$O$2005,MES_REPORTE)) -> 64299.357 | H15: =IF(PRODUCTOS!$A$7="","",IFERROR(F15/SUM($F$14:$F$33),0)) -> 0.29015079 | I15: =IF(PRODUCTOS!$A$7="","",IFERROR(F15/E15,0)) -> 0.61574808
B16: =IF(PRODUCTOS!$A$8="","",PRODUCTOS!$B$8) -> Fresas con crema Grande (16 oz) | C16: =IF(PRODUCTOS!$A$8="","",SUMIFS(VENTAS!$E$6:$E$2005,VENTAS!$C$6:$C$2005,PRODUCTOS!$A$8,VENTAS!$O$6:$O$2005,MES_REPORTE)) -> 20 | E16: =IF(PRODUCTOS!$A$8="","",SUMIFS(VENTAS!$J$6:$J$2005,VENTAS!$C$6:$C$2005,PRODUCTOS!$A$8,VENTAS!$O$6:$O$2005,MES_REPORTE)) -> 87610.619 | F16: =IF(PRODUCTOS!$A$8="","",SUMIFS(VENTAS!$L$6:$L$2005,VENTAS!$C$6:$C$2005,PRODUCTOS!$A$8,VENTAS!$O$6:$O$2005,MES_REPORTE)) -> 57112.994 | H16: =IF(PRODUCTOS!$A$8="","",IFERROR(F16/SUM($F$14:$F$33),0)) -> 0.25772234 | I16: =IF(PRODUCTOS!$A$8="","",IFERROR(F16/E16,0)) -> 0.65189579
B17: =IF(PRODUCTOS!$A$9="","",PRODUCTOS!$B$9) -> Fresas con crema Extra grande (24 oz) | C17: =IF(PRODUCTOS!$A$9="","",SUMIFS(VENTAS!$E$6:$E$2005,VENTAS!$C$6:$C$2005,PRODUCTOS!$A$9,VENTAS!$O$6:$O$2005,MES_REPORTE)) -> 7 | E17: =IF(PRODUCTOS!$A$9="","",SUMIFS(VENTAS!$J$6:$J$2005,VENTAS!$C$6:$C$2005,PRODUCTOS!$A$9,VENTAS!$O$6:$O$2005,MES_REPORTE)) -> 43053.097 | F17: =IF(PRODUCTOS!$A$9="","",SUMIFS(VENTAS!$L$6:$L$2005,VENTAS!$C$6:$C$2005,PRODUCTOS!$A$9,VENTAS!$O$6:$O$2005,MES_REPORTE)) -> 26601.182 | H17: =IF(PRODUCTOS!$A$9="","",IFERROR(F17/SUM($F$14:$F$33),0)) -> 0.12003781 | I17: =IF(PRODUCTOS!$A$9="","",IFERROR(F17/E17,0)) -> 0.61786919
B18: =IF(PRODUCTOS!$A$10="","",PRODUCTOS!$B$10) -> Maracumango | C18: =IF(PRODUCTOS!$A$10="","",SUMIFS(VENTAS!$E$6:$E$2005,VENTAS!$C$6:$C$2005,PRODUCTOS!$A$10,VENTAS!$O$6:$O$2005,MES_REPORTE)) -> 13 | E18: =IF(PRODUCTOS!$A$10="","",SUMIFS(VENTAS!$J$6:$J$2005,VENTAS!$C$6:$C$2005,PRODUCTOS!$A$10,VENTAS!$O$6:$O$2005,MES_REPORTE)) -> 48318.584 | F18: =IF(PRODUCTOS!$A$10="","",SUMIFS(VENTAS!$L$6:$L$2005,VENTAS!$C$6:$C$2005,PRODUCTOS!$A$10,VENTAS!$O$6:$O$2005,MES_REPORTE)) -> 36509.646 | H18: =IF(PRODUCTOS!$A$10="","",IFERROR(F18/SUM($F$14:$F$33),0)) -> 0.16474975 | I18: =IF(PRODUCTOS!$A$10="","",IFERROR(F18/E18,0)) -> 0.75560257
B19: =IF(PRODUCTOS!$A$11="","",PRODUCTOS!$B$11) -> Topping extra | C19: =IF(PRODUCTOS!$A$11="","",SUMIFS(VENTAS!$E$6:$E$2005,VENTAS!$C$6:$C$2005,PRODUCTOS!$A$11,VENTAS!$O$6:$O$2005,MES_REPORTE)) -> 8 | E19: =IF(PRODUCTOS!$A$11="","",SUMIFS(VENTAS!$J$6:$J$2005,VENTAS!$C$6:$C$2005,PRODUCTOS!$A$11,VENTAS!$O$6:$O$2005,MES_REPORTE)) -> 1415.9292 | F19: =IF(PRODUCTOS!$A$11="","",SUMIFS(VENTAS!$L$6:$L$2005,VENTAS!$C$6:$C$2005,PRODUCTOS!$A$11,VENTAS!$O$6:$O$2005,MES_REPORTE)) -> 655.69529 | H19: =IF(PRODUCTOS!$A$11="","",IFERROR(F19/SUM($F$14:$F$33),0)) -> 0.0029588244 | I19: =IF(PRODUCTOS!$A$11="","",IFERROR(F19/E19,0)) -> 0.4630848
B20: =IF(PRODUCTOS!$A$12="","",PRODUCTOS!$B$12) -> Topping extra premium | C20: =IF(PRODUCTOS!$A$12="","",SUMIFS(VENTAS!$E$6:$E$2005,VENTAS!$C$6:$C$2005,PRODUCTOS!$A$12,VENTAS!$O$6:$O$2005,MES_REPORTE)) -> 4 | E20: =IF(PRODUCTOS!$A$12="","",SUMIFS(VENTAS!$J$6:$J$2005,VENTAS!$C$6:$C$2005,PRODUCTOS!$A$12,VENTAS!$O$6:$O$2005,MES_REPORTE)) -> 1061.9469 | F20: =IF(PRODUCTOS!$A$12="","",SUMIFS(VENTAS!$L$6:$L$2005,VENTAS!$C$6:$C$2005,PRODUCTOS!$A$12,VENTAS!$O$6:$O$2005,MES_REPORTE)) -> 491.9469 | H20: =IF(PRODUCTOS!$A$12="","",IFERROR(F20/SUM($F$14:$F$33),0)) -> 0.00221991 | I20: =IF(PRODUCTOS!$A$12="","",IFERROR(F20/E20,0)) -> 0.46325
B21: =IF(PRODUCTOS!$A$13="","",PRODUCTOS!$B$13) -> Jarabe premium (Nutella / pistacho) | C21: =IF(PRODUCTOS!$A$13="","",SUMIFS(VENTAS!$E$6:$E$2005,VENTAS!$C$6:$C$2005,PRODUCTOS!$A$13,VENTAS!$O$6:$O$2005,MES_REPORTE)) -> 5 | E21: =IF(PRODUCTOS!$A$13="","",SUMIFS(VENTAS!$J$6:$J$2005,VENTAS!$C$6:$C$2005,PRODUCTOS!$A$13,VENTAS!$O$6:$O$2005,MES_REPORTE)) -> 1769.9115 | F21: =IF(PRODUCTOS!$A$13="","",SUMIFS(VENTAS!$L$6:$L$2005,VENTAS!$C$6:$C$2005,PRODUCTOS!$A$13,VENTAS!$O$6:$O$2005,MES_REPORTE)) -> 576.92905 | H21: =IF(PRODUCTOS!$A$13="","",IFERROR(F21/SUM($F$14:$F$33),0)) -> 0.0026033918 | I21: =IF(PRODUCTOS!$A$13="","",IFERROR(F21/E21,0)) -> 0.32596491
B22: =IF(PRODUCTOS!$A$14="","",PRODUCTOS!$B$14) -> Brownie de la casa (lote de 20) | C22: =IF(PRODUCTOS!$A$14="","",SUMIFS(VENTAS!$E$6:$E$2005,VENTAS!$C$6:$C$2005,PRODUCTOS!$A$14,VENTAS!$O$6:$O$2005,MES_REPORTE)) -> 6 | E22: =IF(PRODUCTOS!$A$14="","",SUMIFS(VENTAS!$J$6:$J$2005,VENTAS!$C$6:$C$2005,PRODUCTOS!$A$14,VENTAS!$O$6:$O$2005,MES_REPORTE)) -> 7964.6018 | F22: =IF(PRODUCTOS!$A$14="","",SUMIFS(VENTAS!$L$6:$L$2005,VENTAS!$C$6:$C$2005,PRODUCTOS!$A$14,VENTAS!$O$6:$O$2005,MES_REPORTE)) -> 6947.0018 | H22: =IF(PRODUCTOS!$A$14="","",IFERROR(F22/SUM($F$14:$F$33),0)) -> 0.03134834 | I22: =IF(PRODUCTOS!$A$14="","",IFERROR(F22/E22,0)) -> 0.87223467
B23: =IF(PRODUCTOS!$A$15="","",PRODUCTOS!$B$15) | C23: =IF(PRODUCTOS!$A$15="","",SUMIFS(VENTAS!$E$6:$E$2005,VENTAS!$C$6:$C$2005,PRODUCTOS!$A$15,VENTAS!$O$6:$O$2005,MES_REPORTE)) | E23: =IF(PRODUCTOS!$A$15="","",SUMIFS(VENTAS!$J$6:$J$2005,VENTAS!$C$6:$C$2005,PRODUCTOS!$A$15,VENTAS!$O$6:$O$2005,MES_REPORTE)) | F23: =IF(PRODUCTOS!$A$15="","",SUMIFS(VENTAS!$L$6:$L$2005,VENTAS!$C$6:$C$2005,PRODUCTOS!$A$15,VENTAS!$O$6:$O$2005,MES_REPORTE)) | H23: =IF(PRODUCTOS!$A$15="","",IFERROR(F23/SUM($F$14:$F$33),0)) | I23: =IF(PRODUCTOS!$A$15="","",IFERROR(F23/E23,0))
B24: =IF(PRODUCTOS!$A$16="","",PRODUCTOS!$B$16) | C24: =IF(PRODUCTOS!$A$16="","",SUMIFS(VENTAS!$E$6:$E$2005,VENTAS!$C$6:$C$2005,PRODUCTOS!$A$16,VENTAS!$O$6:$O$2005,MES_REPORTE)) | E24: =IF(PRODUCTOS!$A$16="","",SUMIFS(VENTAS!$J$6:$J$2005,VENTAS!$C$6:$C$2005,PRODUCTOS!$A$16,VENTAS!$O$6:$O$2005,MES_REPORTE)) | F24: =IF(PRODUCTOS!$A$16="","",SUMIFS(VENTAS!$L$6:$L$2005,VENTAS!$C$6:$C$2005,PRODUCTOS!$A$16,VENTAS!$O$6:$O$2005,MES_REPORTE)) | H24: =IF(PRODUCTOS!$A$16="","",IFERROR(F24/SUM($F$14:$F$33),0)) | I24: =IF(PRODUCTOS!$A$16="","",IFERROR(F24/E24,0))
B25: =IF(PRODUCTOS!$A$17="","",PRODUCTOS!$B$17) | C25: =IF(PRODUCTOS!$A$17="","",SUMIFS(VENTAS!$E$6:$E$2005,VENTAS!$C$6:$C$2005,PRODUCTOS!$A$17,VENTAS!$O$6:$O$2005,MES_REPORTE)) | E25: =IF(PRODUCTOS!$A$17="","",SUMIFS(VENTAS!$J$6:$J$2005,VENTAS!$C$6:$C$2005,PRODUCTOS!$A$17,VENTAS!$O$6:$O$2005,MES_REPORTE)) | F25: =IF(PRODUCTOS!$A$17="","",SUMIFS(VENTAS!$L$6:$L$2005,VENTAS!$C$6:$C$2005,PRODUCTOS!$A$17,VENTAS!$O$6:$O$2005,MES_REPORTE)) | H25: =IF(PRODUCTOS!$A$17="","",IFERROR(F25/SUM($F$14:$F$33),0)) | I25: =IF(PRODUCTOS!$A$17="","",IFERROR(F25/E25,0))
B26: =IF(PRODUCTOS!$A$18="","",PRODUCTOS!$B$18) | C26: =IF(PRODUCTOS!$A$18="","",SUMIFS(VENTAS!$E$6:$E$2005,VENTAS!$C$6:$C$2005,PRODUCTOS!$A$18,VENTAS!$O$6:$O$2005,MES_REPORTE)) | E26: =IF(PRODUCTOS!$A$18="","",SUMIFS(VENTAS!$J$6:$J$2005,VENTAS!$C$6:$C$2005,PRODUCTOS!$A$18,VENTAS!$O$6:$O$2005,MES_REPORTE)) | F26: =IF(PRODUCTOS!$A$18="","",SUMIFS(VENTAS!$L$6:$L$2005,VENTAS!$C$6:$C$2005,PRODUCTOS!$A$18,VENTAS!$O$6:$O$2005,MES_REPORTE)) | H26: =IF(PRODUCTOS!$A$18="","",IFERROR(F26/SUM($F$14:$F$33),0)) | I26: =IF(PRODUCTOS!$A$18="","",IFERROR(F26/E26,0))
B27: =IF(PRODUCTOS!$A$19="","",PRODUCTOS!$B$19) | C27: =IF(PRODUCTOS!$A$19="","",SUMIFS(VENTAS!$E$6:$E$2005,VENTAS!$C$6:$C$2005,PRODUCTOS!$A$19,VENTAS!$O$6:$O$2005,MES_REPORTE)) | E27: =IF(PRODUCTOS!$A$19="","",SUMIFS(VENTAS!$J$6:$J$2005,VENTAS!$C$6:$C$2005,PRODUCTOS!$A$19,VENTAS!$O$6:$O$2005,MES_REPORTE)) | F27: =IF(PRODUCTOS!$A$19="","",SUMIFS(VENTAS!$L$6:$L$2005,VENTAS!$C$6:$C$2005,PRODUCTOS!$A$19,VENTAS!$O$6:$O$2005,MES_REPORTE)) | H27: =IF(PRODUCTOS!$A$19="","",IFERROR(F27/SUM($F$14:$F$33),0)) | I27: =IF(PRODUCTOS!$A$19="","",IFERROR(F27/E27,0))
B28: =IF(PRODUCTOS!$A$20="","",PRODUCTOS!$B$20) | C28: =IF(PRODUCTOS!$A$20="","",SUMIFS(VENTAS!$E$6:$E$2005,VENTAS!$C$6:$C$2005,PRODUCTOS!$A$20,VENTAS!$O$6:$O$2005,MES_REPORTE)) | E28: =IF(PRODUCTOS!$A$20="","",SUMIFS(VENTAS!$J$6:$J$2005,VENTAS!$C$6:$C$2005,PRODUCTOS!$A$20,VENTAS!$O$6:$O$2005,MES_REPORTE)) | F28: =IF(PRODUCTOS!$A$20="","",SUMIFS(VENTAS!$L$6:$L$2005,VENTAS!$C$6:$C$2005,PRODUCTOS!$A$20,VENTAS!$O$6:$O$2005,MES_REPORTE)) | H28: =IF(PRODUCTOS!$A$20="","",IFERROR(F28/SUM($F$14:$F$33),0)) | I28: =IF(PRODUCTOS!$A$20="","",IFERROR(F28/E28,0))
B29: =IF(PRODUCTOS!$A$21="","",PRODUCTOS!$B$21) | C29: =IF(PRODUCTOS!$A$21="","",SUMIFS(VENTAS!$E$6:$E$2005,VENTAS!$C$6:$C$2005,PRODUCTOS!$A$21,VENTAS!$O$6:$O$2005,MES_REPORTE)) | E29: =IF(PRODUCTOS!$A$21="","",SUMIFS(VENTAS!$J$6:$J$2005,VENTAS!$C$6:$C$2005,PRODUCTOS!$A$21,VENTAS!$O$6:$O$2005,MES_REPORTE)) | F29: =IF(PRODUCTOS!$A$21="","",SUMIFS(VENTAS!$L$6:$L$2005,VENTAS!$C$6:$C$2005,PRODUCTOS!$A$21,VENTAS!$O$6:$O$2005,MES_REPORTE)) | H29: =IF(PRODUCTOS!$A$21="","",IFERROR(F29/SUM($F$14:$F$33),0)) | I29: =IF(PRODUCTOS!$A$21="","",IFERROR(F29/E29,0))
B30: =IF(PRODUCTOS!$A$22="","",PRODUCTOS!$B$22) | C30: =IF(PRODUCTOS!$A$22="","",SUMIFS(VENTAS!$E$6:$E$2005,VENTAS!$C$6:$C$2005,PRODUCTOS!$A$22,VENTAS!$O$6:$O$2005,MES_REPORTE)) | E30: =IF(PRODUCTOS!$A$22="","",SUMIFS(VENTAS!$J$6:$J$2005,VENTAS!$C$6:$C$2005,PRODUCTOS!$A$22,VENTAS!$O$6:$O$2005,MES_REPORTE)) | F30: =IF(PRODUCTOS!$A$22="","",SUMIFS(VENTAS!$L$6:$L$2005,VENTAS!$C$6:$C$2005,PRODUCTOS!$A$22,VENTAS!$O$6:$O$2005,MES_REPORTE)) | H30: =IF(PRODUCTOS!$A$22="","",IFERROR(F30/SUM($F$14:$F$33),0)) | I30: =IF(PRODUCTOS!$A$22="","",IFERROR(F30/E30,0))
B31: =IF(PRODUCTOS!$A$23="","",PRODUCTOS!$B$23) | C31: =IF(PRODUCTOS!$A$23="","",SUMIFS(VENTAS!$E$6:$E$2005,VENTAS!$C$6:$C$2005,PRODUCTOS!$A$23,VENTAS!$O$6:$O$2005,MES_REPORTE)) | E31: =IF(PRODUCTOS!$A$23="","",SUMIFS(VENTAS!$J$6:$J$2005,VENTAS!$C$6:$C$2005,PRODUCTOS!$A$23,VENTAS!$O$6:$O$2005,MES_REPORTE)) | F31: =IF(PRODUCTOS!$A$23="","",SUMIFS(VENTAS!$L$6:$L$2005,VENTAS!$C$6:$C$2005,PRODUCTOS!$A$23,VENTAS!$O$6:$O$2005,MES_REPORTE)) | H31: =IF(PRODUCTOS!$A$23="","",IFERROR(F31/SUM($F$14:$F$33),0)) | I31: =IF(PRODUCTOS!$A$23="","",IFERROR(F31/E31,0))
B32: =IF(PRODUCTOS!$A$24="","",PRODUCTOS!$B$24) | C32: =IF(PRODUCTOS!$A$24="","",SUMIFS(VENTAS!$E$6:$E$2005,VENTAS!$C$6:$C$2005,PRODUCTOS!$A$24,VENTAS!$O$6:$O$2005,MES_REPORTE)) | E32: =IF(PRODUCTOS!$A$24="","",SUMIFS(VENTAS!$J$6:$J$2005,VENTAS!$C$6:$C$2005,PRODUCTOS!$A$24,VENTAS!$O$6:$O$2005,MES_REPORTE)) | F32: =IF(PRODUCTOS!$A$24="","",SUMIFS(VENTAS!$L$6:$L$2005,VENTAS!$C$6:$C$2005,PRODUCTOS!$A$24,VENTAS!$O$6:$O$2005,MES_REPORTE)) | H32: =IF(PRODUCTOS!$A$24="","",IFERROR(F32/SUM($F$14:$F$33),0)) | I32: =IF(PRODUCTOS!$A$24="","",IFERROR(F32/E32,0))
B33: =IF(PRODUCTOS!$A$25="","",PRODUCTOS!$B$25) | C33: =IF(PRODUCTOS!$A$25="","",SUMIFS(VENTAS!$E$6:$E$2005,VENTAS!$C$6:$C$2005,PRODUCTOS!$A$25,VENTAS!$O$6:$O$2005,MES_REPORTE)) | E33: =IF(PRODUCTOS!$A$25="","",SUMIFS(VENTAS!$J$6:$J$2005,VENTAS!$C$6:$C$2005,PRODUCTOS!$A$25,VENTAS!$O$6:$O$2005,MES_REPORTE)) | F33: =IF(PRODUCTOS!$A$25="","",SUMIFS(VENTAS!$L$6:$L$2005,VENTAS!$C$6:$C$2005,PRODUCTOS!$A$25,VENTAS!$O$6:$O$2005,MES_REPORTE)) | H33: =IF(PRODUCTOS!$A$25="","",IFERROR(F33/SUM($F$14:$F$33),0)) | I33: =IF(PRODUCTOS!$A$25="","",IFERROR(F33/E33,0))
B35: Insumos por reordenar (desde INSUMOS)
B36: Insumo | C36: Stock actual | E36: Proveedor | F36: Sugerido comprar (presentaciones) | H36: Estado
B37: =IFERROR(INDEX(INSUMOS!$B:$B,SMALL(INSUMOS!$AA$6:$AA$205,1)),"") -> Granola | C37: =IFERROR(INDEX(INSUMOS!$T:$T,SMALL(INSUMOS!$AA$6:$AA$205,1)),"") -> 400 | E37: =IFERROR(INDEX(INSUMOS!$J:$J,SMALL(INSUMOS!$AA$6:$AA$205,1)),"") -> Mayorista | F37: =IFERROR(INDEX(INSUMOS!$Z:$Z,SMALL(INSUMOS!$AA$6:$AA$205,1)),"") -> 1 | H37: =IFERROR(INDEX(INSUMOS!$Y:$Y,SMALL(INSUMOS!$AA$6:$AA$205,1)),"") -> REORDENAR
B38: =IFERROR(INDEX(INSUMOS!$B:$B,SMALL(INSUMOS!$AA$6:$AA$205,2)),"") | C38: =IFERROR(INDEX(INSUMOS!$T:$T,SMALL(INSUMOS!$AA$6:$AA$205,2)),"") | E38: =IFERROR(INDEX(INSUMOS!$J:$J,SMALL(INSUMOS!$AA$6:$AA$205,2)),"") | F38: =IFERROR(INDEX(INSUMOS!$Z:$Z,SMALL(INSUMOS!$AA$6:$AA$205,2)),"") | H38: =IFERROR(INDEX(INSUMOS!$Y:$Y,SMALL(INSUMOS!$AA$6:$AA$205,2)),"")
B39: =IFERROR(INDEX(INSUMOS!$B:$B,SMALL(INSUMOS!$AA$6:$AA$205,3)),"") | C39: =IFERROR(INDEX(INSUMOS!$T:$T,SMALL(INSUMOS!$AA$6:$AA$205,3)),"") | E39: =IFERROR(INDEX(INSUMOS!$J:$J,SMALL(INSUMOS!$AA$6:$AA$205,3)),"") | F39: =IFERROR(INDEX(INSUMOS!$Z:$Z,SMALL(INSUMOS!$AA$6:$AA$205,3)),"") | H39: =IFERROR(INDEX(INSUMOS!$Y:$Y,SMALL(INSUMOS!$AA$6:$AA$205,3)),"")
B40: =IFERROR(INDEX(INSUMOS!$B:$B,SMALL(INSUMOS!$AA$6:$AA$205,4)),"") | C40: =IFERROR(INDEX(INSUMOS!$T:$T,SMALL(INSUMOS!$AA$6:$AA$205,4)),"") | E40: =IFERROR(INDEX(INSUMOS!$J:$J,SMALL(INSUMOS!$AA$6:$AA$205,4)),"") | F40: =IFERROR(INDEX(INSUMOS!$Z:$Z,SMALL(INSUMOS!$AA$6:$AA$205,4)),"") | H40: =IFERROR(INDEX(INSUMOS!$Y:$Y,SMALL(INSUMOS!$AA$6:$AA$205,4)),"")
B41: =IFERROR(INDEX(INSUMOS!$B:$B,SMALL(INSUMOS!$AA$6:$AA$205,5)),"") | C41: =IFERROR(INDEX(INSUMOS!$T:$T,SMALL(INSUMOS!$AA$6:$AA$205,5)),"") | E41: =IFERROR(INDEX(INSUMOS!$J:$J,SMALL(INSUMOS!$AA$6:$AA$205,5)),"") | F41: =IFERROR(INDEX(INSUMOS!$Z:$Z,SMALL(INSUMOS!$AA$6:$AA$205,5)),"") | H41: =IFERROR(INDEX(INSUMOS!$Y:$Y,SMALL(INSUMOS!$AA$6:$AA$205,5)),"")
B42: =IFERROR(INDEX(INSUMOS!$B:$B,SMALL(INSUMOS!$AA$6:$AA$205,6)),"") | C42: =IFERROR(INDEX(INSUMOS!$T:$T,SMALL(INSUMOS!$AA$6:$AA$205,6)),"") | E42: =IFERROR(INDEX(INSUMOS!$J:$J,SMALL(INSUMOS!$AA$6:$AA$205,6)),"") | F42: =IFERROR(INDEX(INSUMOS!$Z:$Z,SMALL(INSUMOS!$AA$6:$AA$205,6)),"") | H42: =IFERROR(INDEX(INSUMOS!$Y:$Y,SMALL(INSUMOS!$AA$6:$AA$205,6)),"")
B43: =IFERROR(INDEX(INSUMOS!$B:$B,SMALL(INSUMOS!$AA$6:$AA$205,7)),"") | C43: =IFERROR(INDEX(INSUMOS!$T:$T,SMALL(INSUMOS!$AA$6:$AA$205,7)),"") | E43: =IFERROR(INDEX(INSUMOS!$J:$J,SMALL(INSUMOS!$AA$6:$AA$205,7)),"") | F43: =IFERROR(INDEX(INSUMOS!$Z:$Z,SMALL(INSUMOS!$AA$6:$AA$205,7)),"") | H43: =IFERROR(INDEX(INSUMOS!$Y:$Y,SMALL(INSUMOS!$AA$6:$AA$205,7)),"")
B44: =IFERROR(INDEX(INSUMOS!$B:$B,SMALL(INSUMOS!$AA$6:$AA$205,8)),"") | C44: =IFERROR(INDEX(INSUMOS!$T:$T,SMALL(INSUMOS!$AA$6:$AA$205,8)),"") | E44: =IFERROR(INDEX(INSUMOS!$J:$J,SMALL(INSUMOS!$AA$6:$AA$205,8)),"") | F44: =IFERROR(INDEX(INSUMOS!$Z:$Z,SMALL(INSUMOS!$AA$6:$AA$205,8)),"") | H44: =IFERROR(INDEX(INSUMOS!$Y:$Y,SMALL(INSUMOS!$AA$6:$AA$205,8)),"")
B45: =IFERROR(INDEX(INSUMOS!$B:$B,SMALL(INSUMOS!$AA$6:$AA$205,9)),"") | C45: =IFERROR(INDEX(INSUMOS!$T:$T,SMALL(INSUMOS!$AA$6:$AA$205,9)),"") | E45: =IFERROR(INDEX(INSUMOS!$J:$J,SMALL(INSUMOS!$AA$6:$AA$205,9)),"") | F45: =IFERROR(INDEX(INSUMOS!$Z:$Z,SMALL(INSUMOS!$AA$6:$AA$205,9)),"") | H45: =IFERROR(INDEX(INSUMOS!$Y:$Y,SMALL(INSUMOS!$AA$6:$AA$205,9)),"")
B46: =IFERROR(INDEX(INSUMOS!$B:$B,SMALL(INSUMOS!$AA$6:$AA$205,10)),"") | C46: =IFERROR(INDEX(INSUMOS!$T:$T,SMALL(INSUMOS!$AA$6:$AA$205,10)),"") | E46: =IFERROR(INDEX(INSUMOS!$J:$J,SMALL(INSUMOS!$AA$6:$AA$205,10)),"") | F46: =IFERROR(INDEX(INSUMOS!$Z:$Z,SMALL(INSUMOS!$AA$6:$AA$205,10)),"") | H46: =IFERROR(INDEX(INSUMOS!$Y:$Y,SMALL(INSUMOS!$AA$6:$AA$205,10)),"")
B47: =IFERROR(INDEX(INSUMOS!$B:$B,SMALL(INSUMOS!$AA$6:$AA$205,11)),"") | C47: =IFERROR(INDEX(INSUMOS!$T:$T,SMALL(INSUMOS!$AA$6:$AA$205,11)),"") | E47: =IFERROR(INDEX(INSUMOS!$J:$J,SMALL(INSUMOS!$AA$6:$AA$205,11)),"") | F47: =IFERROR(INDEX(INSUMOS!$Z:$Z,SMALL(INSUMOS!$AA$6:$AA$205,11)),"") | H47: =IFERROR(INDEX(INSUMOS!$Y:$Y,SMALL(INSUMOS!$AA$6:$AA$205,11)),"")
B48: =IFERROR(INDEX(INSUMOS!$B:$B,SMALL(INSUMOS!$AA$6:$AA$205,12)),"") | C48: =IFERROR(INDEX(INSUMOS!$T:$T,SMALL(INSUMOS!$AA$6:$AA$205,12)),"") | E48: =IFERROR(INDEX(INSUMOS!$J:$J,SMALL(INSUMOS!$AA$6:$AA$205,12)),"") | F48: =IFERROR(INDEX(INSUMOS!$Z:$Z,SMALL(INSUMOS!$AA$6:$AA$205,12)),"") | H48: =IFERROR(INDEX(INSUMOS!$Y:$Y,SMALL(INSUMOS!$AA$6:$AA$205,12)),"")
B49: =IFERROR(INDEX(INSUMOS!$B:$B,SMALL(INSUMOS!$AA$6:$AA$205,13)),"") | C49: =IFERROR(INDEX(INSUMOS!$T:$T,SMALL(INSUMOS!$AA$6:$AA$205,13)),"") | E49: =IFERROR(INDEX(INSUMOS!$J:$J,SMALL(INSUMOS!$AA$6:$AA$205,13)),"") | F49: =IFERROR(INDEX(INSUMOS!$Z:$Z,SMALL(INSUMOS!$AA$6:$AA$205,13)),"") | H49: =IFERROR(INDEX(INSUMOS!$Y:$Y,SMALL(INSUMOS!$AA$6:$AA$205,13)),"")
B50: =IFERROR(INDEX(INSUMOS!$B:$B,SMALL(INSUMOS!$AA$6:$AA$205,14)),"") | C50: =IFERROR(INDEX(INSUMOS!$T:$T,SMALL(INSUMOS!$AA$6:$AA$205,14)),"") | E50: =IFERROR(INDEX(INSUMOS!$J:$J,SMALL(INSUMOS!$AA$6:$AA$205,14)),"") | F50: =IFERROR(INDEX(INSUMOS!$Z:$Z,SMALL(INSUMOS!$AA$6:$AA$205,14)),"") | H50: =IFERROR(INDEX(INSUMOS!$Y:$Y,SMALL(INSUMOS!$AA$6:$AA$205,14)),"")
B51: =IFERROR(INDEX(INSUMOS!$B:$B,SMALL(INSUMOS!$AA$6:$AA$205,15)),"") | C51: =IFERROR(INDEX(INSUMOS!$T:$T,SMALL(INSUMOS!$AA$6:$AA$205,15)),"") | E51: =IFERROR(INDEX(INSUMOS!$J:$J,SMALL(INSUMOS!$AA$6:$AA$205,15)),"") | F51: =IFERROR(INDEX(INSUMOS!$Z:$Z,SMALL(INSUMOS!$AA$6:$AA$205,15)),"") | H51: =IFERROR(INDEX(INSUMOS!$Y:$Y,SMALL(INSUMOS!$AA$6:$AA$205,15)),"")

Sheet INSUMOS
A1: INSUMOS E INVENTARIO
A2: Catálogo de materias primas y empaques. Todas las cantidades en UNIDAD BASE (g, ml o u). Stock actual = inicial + compras − consumo por ventas (recetas) ± mermas/ajustes.
A3: Costo vigente = último costo de COMPRAS (si existe) o el precio de catálogo. Costo real = costo ÷ % aprovechamiento (cáscara, hojas, residuos).
T4: Valor total inventario: | U4: =SUM(U6:U205) -> 388439.3 | W4: Faltantes ₡: | X4: =SUM(X6:X205) -> 0
A5: Código | B5: Insumo | C5: Categoría | D5: Unidad base | E5: Presentación de compra | F5: Contenido por presentación (unid. base) | G5: Precio presentación sin IVA (catálogo) | H5: % IVA en compra | I5: % aprovecha-miento | J5: Proveedor principal | K5: Stock mínimo (unid. base) | L5: Stock inicial (unid. base) | M5: Costo catálogo por unid. base | N5: Último costo de compra por unid. base | O5: Costo vigente por unid. base | P5: Costo REAL por unid. base (con aprovech.) | Q5: Entradas (compras) | R5: Consumo por ventas (recetas) | S5: Mermas y ajustes (±) | T5: STOCK TEÓRICO ACTUAL | U5: Valor del inventario | V5: Conteo físico (unid. base) | W5: Diferencia (físico − teórico) | X5: Valor de la diferencia | Y5: Estado | Z5: Sugerido a comprar (presentaciones) | AA5: aux alerta
A6: I001 | B6: Fresas frescas | C6: Fruta | D6: g | E6: Caja 5 kg | F6: 5000 | G6: 14000 | H6: 0.01 | I6: 0.85 | J6: Productor / feria | K6: 5000 | L6: 12000 | M6: =IF($A6="","",IFERROR($G6/$F6,0)) -> 2.8 | N6: =IF($A6="","",IFERROR(SUMIFS(COMPRAS!$N$6:$N$1005,COMPRAS!$D$6:$D$1005,$A6,COMPRAS!$R$6:$R$1005,1)/COUNTIFS(COMPRAS!$D$6:$D$1005,$A6,COMPRAS!$R$6:$R$1005,1),0)) -> 2.8 | O6: =IF($A6="","",IF($N6>0,$N6,$M6)) -> 2.8 | P6: =IF($A6="","",IF(N($I6)>0,$O6/$I6,$O6)) -> 3.2941176 | Q6: =IF($A6="","",SUMIFS(COMPRAS!$I$6:$I$1005,COMPRAS!$D$6:$D$1005,$A6)) -> 15000 | R6: =IF($A6="","",SUMIFS(RECETAS!$L$6:$L$605,RECETAS!$C$6:$C$605,$A6)) -> 17258.824 | S6: =IF($A6="","",SUMIFS(MERMAS!$J$6:$J$505,MERMAS!$B$6:$B$505,$A6)) -> -600 | T6: =IF($A6="","",N($L6)+$Q6-$R6+$S6) -> 9141.1765 | U6: =IF($A6="","",$T6*$O6) -> 25595.294 | W6: =IF(OR($A6="",$V6=""),"",$V6-$T6) | X6: =IF($W6="","",$W6*$O6) | Y6: =IF($A6="","",IF($T6<=0,"AGOTADO",IF($T6<=N($K6),"REORDENAR","OK"))) -> OK | Z6: =IF($A6="","",IF($T6<=N($K6),ROUNDUP((2*N($K6)-$T6)/$F6,0),0)) -> 0 | AA6: =IF(OR($Y6="REORDENAR",$Y6="AGOTADO"),ROW(),"")
A7: I002 | B7: Mango maduro | C7: Fruta | D7: g | E7: Kilo | F7: 1000 | G7: 1200 | H7: 0.01 | I7: 0.65 | J7: Productor / feria | K7: 2000 | L7: 5000 | M7: =IF($A7="","",IFERROR($G7/$F7,0)) -> 1.2 | N7: =IF($A7="","",IFERROR(SUMIFS(COMPRAS!$N$6:$N$1005,COMPRAS!$D$6:$D$1005,$A7,COMPRAS!$R$6:$R$1005,1)/COUNTIFS(COMPRAS!$D$6:$D$1005,$A7,COMPRAS!$R$6:$R$1005,1),0)) -> 1.3 | O7: =IF($A7="","",IF($N7>0,$N7,$M7)) -> 1.3 | P7: =IF($A7="","",IF(N($I7)>0,$O7/$I7,$O7)) -> 2 | Q7: =IF($A7="","",SUMIFS(COMPRAS!$I$6:$I$1005,COMPRAS!$D$6:$D$1005,$A7)) -> 5000 | R7: =IF($A7="","",SUMIFS(RECETAS!$L$6:$L$605,RECETAS!$C$6:$C$605,$A7)) -> 3600 | S7: =IF($A7="","",SUMIFS(MERMAS!$J$6:$J$505,MERMAS!$B$6:$B$505,$A7)) -> 0 | T7: =IF($A7="","",N($L7)+$Q7-$R7+$S7) -> 6400 | U7: =IF($A7="","",$T7*$O7) -> 8320 | W7: =IF(OR($A7="",$V7=""),"",$V7-$T7) | X7: =IF($W7="","",$W7*$O7) | Y7: =IF($A7="","",IF($T7<=0,"AGOTADO",IF($T7<=N($K7),"REORDENAR","OK"))) -> OK | Z7: =IF($A7="","",IF($T7<=N($K7),ROUNDUP((2*N($K7)-$T7)/$F7,0),0)) -> 0 | AA7: =IF(OR($Y7="REORDENAR",$Y7="AGOTADO"),ROW(),"")
A8: I003 | B8: Pulpa de maracuyá | C8: Fruta | D8: g | E8: Bolsa 1 kg | F8: 1000 | G8: 2800 | H8: 0.01 | I8: 1 | J8: Distribuidora | K8: 1000 | L8: 3000 | M8: =IF($A8="","",IFERROR($G8/$F8,0)) -> 2.8 | N8: =IF($A8="","",IFERROR(SUMIFS(COMPRAS!$N$6:$N$1005,COMPRAS!$D$6:$D$1005,$A8,COMPRAS!$R$6:$R$1005,1)/COUNTIFS(COMPRAS!$D$6:$D$1005,$A8,COMPRAS!$R$6:$R$1005,1),0)) -> 0 | O8: =IF($A8="","",IF($N8>0,$N8,$M8)) -> 2.8 | P8: =IF($A8="","",IF(N($I8)>0,$O8/$I8,$O8)) -> 2.8 | Q8: =IF($A8="","",SUMIFS(COMPRAS!$I$6:$I$1005,COMPRAS!$D$6:$D$1005,$A8)) -> 0 | R8: =IF($A8="","",SUMIFS(RECETAS!$L$6:$L$605,RECETAS!$C$6:$C$605,$A8)) -> 780 | S8: =IF($A8="","",SUMIFS(MERMAS!$J$6:$J$505,MERMAS!$B$6:$B$505,$A8)) -> 0 | T8: =IF($A8="","",N($L8)+$Q8-$R8+$S8) -> 2220 | U8: =IF($A8="","",$T8*$O8) -> 6216 | W8: =IF(OR($A8="",$V8=""),"",$V8-$T8) | X8: =IF($W8="","",$W8*$O8) | Y8: =IF($A8="","",IF($T8<=0,"AGOTADO",IF($T8<=N($K8),"REORDENAR","OK"))) -> OK | Z8: =IF($A8="","",IF($T8<=N($K8),ROUNDUP((2*N($K8)-$T8)/$F8,0),0)) -> 0 | AA8: =IF(OR($Y8="REORDENAR",$Y8="AGOTADO"),ROW(),"")
A9: I004 | B9: Crema dulce | C9: Lácteos | D9: ml | E9: Caja 1 L | F9: 1000 | G9: 2500 | H9: 0.01 | I9: 1 | J9: Distribuidora lácteos | K9: 4000 | L9: 10000 | M9: =IF($A9="","",IFERROR($G9/$F9,0)) -> 2.5 | N9: =IF($A9="","",IFERROR(SUMIFS(COMPRAS!$N$6:$N$1005,COMPRAS!$D$6:$D$1005,$A9,COMPRAS!$R$6:$R$1005,1)/COUNTIFS(COMPRAS!$D$6:$D$1005,$A9,COMPRAS!$R$6:$R$1005,1),0)) -> 2.55 | O9: =IF($A9="","",IF($N9>0,$N9,$M9)) -> 2.55 | P9: =IF($A9="","",IF(N($I9)>0,$O9/$I9,$O9)) -> 2.55 | Q9: =IF($A9="","",SUMIFS(COMPRAS!$I$6:$I$1005,COMPRAS!$D$6:$D$1005,$A9)) -> 12000 | R9: =IF($A9="","",SUMIFS(RECETAS!$L$6:$L$605,RECETAS!$C$6:$C$605,$A9)) -> 7645 | S9: =IF($A9="","",SUMIFS(MERMAS!$J$6:$J$505,MERMAS!$B$6:$B$505,$A9)) -> -500 | T9: =IF($A9="","",N($L9)+$Q9-$R9+$S9) -> 13855 | U9: =IF($A9="","",$T9*$O9) -> 35330.25 | W9: =IF(OR($A9="",$V9=""),"",$V9-$T9) | X9: =IF($W9="","",$W9*$O9) | Y9: =IF($A9="","",IF($T9<=0,"AGOTADO",IF($T9<=N($K9),"REORDENAR","OK"))) -> OK | Z9: =IF($A9="","",IF($T9<=N($K9),ROUNDUP((2*N($K9)-$T9)/$F9,0),0)) -> 0 | AA9: =IF(OR($Y9="REORDENAR",$Y9="AGOTADO"),ROW(),"")
A10: I005 | B10: Leche condensada | C10: Lácteos | D10: g | E10: Lata 397 g | F10: 397 | G10: 1250 | H10: 0.13 | I10: 0.97 | J10: Mayorista | K10: 3970 | L10: 7940 | M10: =IF($A10="","",IFERROR($G10/$F10,0)) -> 3.1486146 | N10: =IF($A10="","",IFERROR(SUMIFS(COMPRAS!$N$6:$N$1005,COMPRAS!$D$6:$D$1005,$A10,COMPRAS!$R$6:$R$1005,1)/COUNTIFS(COMPRAS!$D$6:$D$1005,$A10,COMPRAS!$R$6:$R$1005,1),0)) -> 3.1486146 | O10: =IF($A10="","",IF($N10>0,$N10,$M10)) -> 3.1486146 | P10: =IF($A10="","",IF(N($I10)>0,$O10/$I10,$O10)) -> 3.2459944 | Q10: =IF($A10="","",SUMIFS(COMPRAS!$I$6:$I$1005,COMPRAS!$D$6:$D$1005,$A10)) -> 9528 | R10: =IF($A10="","",SUMIFS(RECETAS!$L$6:$L$605,RECETAS!$C$6:$C$605,$A10)) -> 3592.7835 | S10: =IF($A10="","",SUMIFS(MERMAS!$J$6:$J$505,MERMAS!$B$6:$B$505,$A10)) -> 0 | T10: =IF($A10="","",N($L10)+$Q10-$R10+$S10) -> 13875.216 | U10: =IF($A10="","",$T10*$O10) -> 43687.709 | W10: =IF(OR($A10="",$V10=""),"",$V10-$T10) | X10: =IF($W10="","",$W10*$O10) | Y10: =IF($A10="","",IF($T10<=0,"AGOTADO",IF($T10<=N($K10),"REORDENAR","OK"))) -> OK | Z10: =IF($A10="","",IF($T10<=N($K10),ROUNDUP((2*N($K10)-$T10)/$F10,0),0)) -> 0 | AA10: =IF(OR($Y10="REORDENAR",$Y10="AGOTADO"),ROW(),"")
A11: I006 | B11: Esencia de vainilla | C11: Abarrotes | D11: ml | E11: Frasco 250 ml | F11: 250 | G11: 1800 | H11: 0.13 | I11: 1 | J11: Mayorista | K11: 250 | L11: 500 | M11: =IF($A11="","",IFERROR($G11/$F11,0)) -> 7.2 | N11: =IF($A11="","",IFERROR(SUMIFS(COMPRAS!$N$6:$N$1005,COMPRAS!$D$6:$D$1005,$A11,COMPRAS!$R$6:$R$1005,1)/COUNTIFS(COMPRAS!$D$6:$D$1005,$A11,COMPRAS!$R$6:$R$1005,1),0)) -> 0 | O11: =IF($A11="","",IF($N11>0,$N11,$M11)) -> 7.2 | P11: =IF($A11="","",IF(N($I11)>0,$O11/$I11,$O11)) -> 7.2 | Q11: =IF($A11="","",SUMIFS(COMPRAS!$I$6:$I$1005,COMPRAS!$D$6:$D$1005,$A11)) -> 0 | R11: =IF($A11="","",SUMIFS(RECETAS!$L$6:$L$605,RECETAS!$C$6:$C$605,$A11)) -> 151 | S11: =IF($A11="","",SUMIFS(MERMAS!$J$6:$J$505,MERMAS!$B$6:$B$505,$A11)) -> 0 | T11: =IF($A11="","",N($L11)+$Q11-$R11+$S11) -> 349 | U11: =IF($A11="","",$T11*$O11) -> 2512.8 | W11: =IF(OR($A11="",$V11=""),"",$V11-$T11) | X11: =IF($W11="","",$W11*$O11) | Y11: =IF($A11="","",IF($T11<=0,"AGOTADO",IF($T11<=N($K11),"REORDENAR","OK"))) -> OK | Z11: =IF($A11="","",IF($T11<=N($K11),ROUNDUP((2*N($K11)-$T11)/$F11,0),0)) -> 0 | AA11: =IF(OR($Y11="REORDENAR",$Y11="AGOTADO"),ROW(),"")
A12: I007 | B12: Azúcar | C12: Abarrotes | D12: g | E12: Bolsa 2 kg | F12: 2000 | G12: 1700 | H12: 0.01 | I12: 1 | J12: Mayorista | K12: 2000 | L12: 4000 | M12: =IF($A12="","",IFERROR($G12/$F12,0)) -> 0.85 | N12: =IF($A12="","",IFERROR(SUMIFS(COMPRAS!$N$6:$N$1005,COMPRAS!$D$6:$D$1005,$A12,COMPRAS!$R$6:$R$1005,1)/COUNTIFS(COMPRAS!$D$6:$D$1005,$A12,COMPRAS!$R$6:$R$1005,1),0)) -> 0 | O12: =IF($A12="","",IF($N12>0,$N12,$M12)) -> 0.85 | P12: =IF($A12="","",IF(N($I12)>0,$O12/$I12,$O12)) -> 0.85 | Q12: =IF($A12="","",SUMIFS(COMPRAS!$I$6:$I$1005,COMPRAS!$D$6:$D$1005,$A12)) -> 0 | R12: =IF($A12="","",SUMIFS(RECETAS!$L$6:$L$605,RECETAS!$C$6:$C$605,$A12)) -> 120 | S12: =IF($A12="","",SUMIFS(MERMAS!$J$6:$J$505,MERMAS!$B$6:$B$505,$A12)) -> 0 | T12: =IF($A12="","",N($L12)+$Q12-$R12+$S12) -> 3880 | U12: =IF($A12="","",$T12*$O12) -> 3298 | W12: =IF(OR($A12="",$V12=""),"",$V12-$T12) | X12: =IF($W12="","",$W12*$O12) | Y12: =IF($A12="","",IF($T12<=0,"AGOTADO",IF($T12<=N($K12),"REORDENAR","OK"))) -> OK | Z12: =IF($A12="","",IF($T12<=N($K12),ROUNDUP((2*N($K12)-$T12)/$F12,0),0)) -> 0 | AA12: =IF(OR($Y12="REORDENAR",$Y12="AGOTADO"),ROW(),"")
A13: I008 | B13: Galleta Oreo triturada | C13: Toppings | D13: g | E13: Paquete 432 g | F13: 432 | G13: 2600 | H13: 0.13 | I13: 0.95 | J13: Mayorista | K13: 864 | L13: 2160 | M13: =IF($A13="","",IFERROR($G13/$F13,0)) -> 6.0185185 | N13: =IF($A13="","",IFERROR(SUMIFS(COMPRAS!$N$6:$N$1005,COMPRAS!$D$6:$D$1005,$A13,COMPRAS!$R$6:$R$1005,1)/COUNTIFS(COMPRAS!$D$6:$D$1005,$A13,COMPRAS!$R$6:$R$1005,1),0)) -> 6.0185185 | O13: =IF($A13="","",IF($N13>0,$N13,$M13)) -> 6.0185185 | P13: =IF($A13="","",IF(N($I13)>0,$O13/$I13,$O13)) -> 6.3352827 | Q13: =IF($A13="","",SUMIFS(COMPRAS!$I$6:$I$1005,COMPRAS!$D$6:$D$1005,$A13)) -> 1728 | R13: =IF($A13="","",SUMIFS(RECETAS!$L$6:$L$605,RECETAS!$C$6:$C$605,$A13)) -> 1789.4737 | S13: =IF($A13="","",SUMIFS(MERMAS!$J$6:$J$505,MERMAS!$B$6:$B$505,$A13)) -> 0 | T13: =IF($A13="","",N($L13)+$Q13-$R13+$S13) -> 2098.5263 | U13: =IF($A13="","",$T13*$O13) -> 12630.019 | W13: =IF(OR($A13="",$V13=""),"",$V13-$T13) | X13: =IF($W13="","",$W13*$O13) | Y13: =IF($A13="","",IF($T13<=0,"AGOTADO",IF($T13<=N($K13),"REORDENAR","OK"))) -> OK | Z13: =IF($A13="","",IF($T13<=N($K13),ROUNDUP((2*N($K13)-$T13)/$F13,0),0)) -> 0 | AA13: =IF(OR($Y13="REORDENAR",$Y13="AGOTADO"),ROW(),"")
A14: I009 | B14: Brownie (topping) | C14: Toppings | D14: g | E14: Bandeja 1 kg | F14: 1000 | G14: 5500 | H14: 0.13 | I14: 0.95 | J14: Panadería | K14: 500 | L14: 1000 | M14: =IF($A14="","",IFERROR($G14/$F14,0)) -> 5.5 | N14: =IF($A14="","",IFERROR(SUMIFS(COMPRAS!$N$6:$N$1005,COMPRAS!$D$6:$D$1005,$A14,COMPRAS!$R$6:$R$1005,1)/COUNTIFS(COMPRAS!$D$6:$D$1005,$A14,COMPRAS!$R$6:$R$1005,1),0)) -> 0 | O14: =IF($A14="","",IF($N14>0,$N14,$M14)) -> 5.5 | P14: =IF($A14="","",IF(N($I14)>0,$O14/$I14,$O14)) -> 5.7894737 | Q14: =IF($A14="","",SUMIFS(COMPRAS!$I$6:$I$1005,COMPRAS!$D$6:$D$1005,$A14)) -> 0 | R14: =IF($A14="","",SUMIFS(RECETAS!$L$6:$L$605,RECETAS!$C$6:$C$605,$A14)) -> 221.05263 | S14: =IF($A14="","",SUMIFS(MERMAS!$J$6:$J$505,MERMAS!$B$6:$B$505,$A14)) -> 0 | T14: =IF($A14="","",N($L14)+$Q14-$R14+$S14) -> 778.94737 | U14: =IF($A14="","",$T14*$O14) -> 4284.2105 | W14: =IF(OR($A14="",$V14=""),"",$V14-$T14) | X14: =IF($W14="","",$W14*$O14) | Y14: =IF($A14="","",IF($T14<=0,"AGOTADO",IF($T14<=N($K14),"REORDENAR","OK"))) -> OK | Z14: =IF($A14="","",IF($T14<=N($K14),ROUNDUP((2*N($K14)-$T14)/$F14,0),0)) -> 0 | AA14: =IF(OR($Y14="REORDENAR",$Y14="AGOTADO"),ROW(),"")
A15: I010 | B15: Marshmallows | C15: Toppings | D15: g | E15: Bolsa 500 g | F15: 500 | G15: 2200 | H15: 0.13 | I15: 1 | J15: Mayorista | K15: 500 | L15: 1000 | M15: =IF($A15="","",IFERROR($G15/$F15,0)) -> 4.4 | N15: =IF($A15="","",IFERROR(SUMIFS(COMPRAS!$N$6:$N$1005,COMPRAS!$D$6:$D$1005,$A15,COMPRAS!$R$6:$R$1005,1)/COUNTIFS(COMPRAS!$D$6:$D$1005,$A15,COMPRAS!$R$6:$R$1005,1),0)) -> 0 | O15: =IF($A15="","",IF($N15>0,$N15,$M15)) -> 4.4 | P15: =IF($A15="","",IF(N($I15)>0,$O15/$I15,$O15)) -> 4.4 | Q15: =IF($A15="","",SUMIFS(COMPRAS!$I$6:$I$1005,COMPRAS!$D$6:$D$1005,$A15)) -> 0 | R15: =IF($A15="","",SUMIFS(RECETAS!$L$6:$L$605,RECETAS!$C$6:$C$605,$A15)) -> 440 | S15: =IF($A15="","",SUMIFS(MERMAS!$J$6:$J$505,MERMAS!$B$6:$B$505,$A15)) -> 0 | T15: =IF($A15="","",N($L15)+$Q15-$R15+$S15) -> 560 | U15: =IF($A15="","",$T15*$O15) -> 2464 | W15: =IF(OR($A15="",$V15=""),"",$V15-$T15) | X15: =IF($W15="","",$W15*$O15) | Y15: =IF($A15="","",IF($T15<=0,"AGOTADO",IF($T15<=N($K15),"REORDENAR","OK"))) -> OK | Z15: =IF($A15="","",IF($T15<=N($K15),ROUNDUP((2*N($K15)-$T15)/$F15,0),0)) -> 0 | AA15: =IF(OR($Y15="REORDENAR",$Y15="AGOTADO"),ROW(),"")
A16: I011 | B16: Gomitas | C16: Toppings | D16: g | E16: Bolsa 1 kg | F16: 1000 | G16: 3800 | H16: 0.13 | I16: 1 | J16: Mayorista | K16: 500 | L16: 1000 | M16: =IF($A16="","",IFERROR($G16/$F16,0)) -> 3.8 | N16: =IF($A16="","",IFERROR(SUMIFS(COMPRAS!$N$6:$N$1005,COMPRAS!$D$6:$D$1005,$A16,COMPRAS!$R$6:$R$1005,1)/COUNTIFS(COMPRAS!$D$6:$D$1005,$A16,COMPRAS!$R$6:$R$1005,1),0)) -> 0 | O16: =IF($A16="","",IF($N16>0,$N16,$M16)) -> 3.8 | P16: =IF($A16="","",IF(N($I16)>0,$O16/$I16,$O16)) -> 3.8 | Q16: =IF($A16="","",SUMIFS(COMPRAS!$I$6:$I$1005,COMPRAS!$D$6:$D$1005,$A16)) -> 0 | R16: =IF($A16="","",SUMIFS(RECETAS!$L$6:$L$605,RECETAS!$C$6:$C$605,$A16)) -> 440 | S16: =IF($A16="","",SUMIFS(MERMAS!$J$6:$J$505,MERMAS!$B$6:$B$505,$A16)) -> 0 | T16: =IF($A16="","",N($L16)+$Q16-$R16+$S16) -> 560 | U16: =IF($A16="","",$T16*$O16) -> 2128 | W16: =IF(OR($A16="",$V16=""),"",$V16-$T16) | X16: =IF($W16="","",$W16*$O16) | Y16: =IF($A16="","",IF($T16<=0,"AGOTADO",IF($T16<=N($K16),"REORDENAR","OK"))) -> OK | Z16: =IF($A16="","",IF($T16<=N($K16),ROUNDUP((2*N($K16)-$T16)/$F16,0),0)) -> 0 | AA16: =IF(OR($Y16="REORDENAR",$Y16="AGOTADO"),ROW(),"")
A17: I012 | B17: Granola | C17: Toppings | D17: g | E17: Bolsa 1 kg | F17: 1000 | G17: 4200 | H17: 0.13 | I17: 1 | J17: Mayorista | K17: 500 | L17: 1000 | M17: =IF($A17="","",IFERROR($G17/$F17,0)) -> 4.2 | N17: =IF($A17="","",IFERROR(SUMIFS(COMPRAS!$N$6:$N$1005,COMPRAS!$D$6:$D$1005,$A17,COMPRAS!$R$6:$R$1005,1)/COUNTIFS(COMPRAS!$D$6:$D$1005,$A17,COMPRAS!$R$6:$R$1005,1),0)) -> 0 | O17: =IF($A17="","",IF($N17>0,$N17,$M17)) -> 4.2 | P17: =IF($A17="","",IF(N($I17)>0,$O17/$I17,$O17)) -> 4.2 | Q17: =IF($A17="","",SUMIFS(COMPRAS!$I$6:$I$1005,COMPRAS!$D$6:$D$1005,$A17)) -> 0 | R17: =IF($A17="","",SUMIFS(RECETAS!$L$6:$L$605,RECETAS!$C$6:$C$605,$A17)) -> 600 | S17: =IF($A17="","",SUMIFS(MERMAS!$J$6:$J$505,MERMAS!$B$6:$B$505,$A17)) -> 0 | T17: =IF($A17="","",N($L17)+$Q17-$R17+$S17) -> 400 | U17: =IF($A17="","",$T17*$O17) -> 1680 | W17: =IF(OR($A17="",$V17=""),"",$V17-$T17) | X17: =IF($W17="","",$W17*$O17) | Y17: =IF($A17="","",IF($T17<=0,"AGOTADO",IF($T17<=N($K17),"REORDENAR","OK"))) -> REORDENAR | Z17: =IF($A17="","",IF($T17<=N($K17),ROUNDUP((2*N($K17)-$T17)/$F17,0),0)) -> 1 | AA17: =IF(OR($Y17="REORDENAR",$Y17="AGOTADO"),ROW(),"") -> 17
... A36: I031 | B36: Huevos | C36: Abarrotes | D36: u | E36: Cartón 30 u | F36: 30 | G36: 3000 | H36: 0.01 | I36: 1 | J36: Granja | K36: 30 | L36: 60 | M36: =IF($A36="","",IFERROR($G36/$F36,0)) -> 100 | N36: =IF($A36="","",IFERROR(SUMIFS(COMPRAS!$N$6:$N$1005,COMPRAS!$D$6:$D$1005,$A36,COMPRAS!$R$6:$R$1005,1)/COUNTIFS(COMPRAS!$D$6:$D$1005,$A36,COMPRAS!$R$6:$R$1005,1),0)) -> 0 | O36: =IF($A36="","",IF($N36>0,$N36,$M36)) -> 100 | P36: =IF($A36="","",IF(N($I36)>0,$O36/$I36,$O36)) -> 100 | Q36: =IF($A36="","",SUMIFS(COMPRAS!$I$6:$I$1005,COMPRAS!$D$6:$D$1005,$A36)) -> 0 | R36: =IF($A36="","",SUMIFS(RECETAS!$L$6:$L$605,RECETAS!$C$6:$C$605,$A36)) -> 1.8 | S36: =IF($A36="","",SUMIFS(MERMAS!$J$6:$J$505,MERMAS!$B$6:$B$505,$A36)) -> 0 | T36: =IF($A36="","",N($L36)+$Q36-$R36+$S36) -> 58.2 | U36: =IF($A36="","",$T36*$O36) -> 5820 | W36: =IF(OR($A36="",$V36=""),"",$V36-$T36) | X36: =IF($W36="","",$W36*$O36) | Y36: =IF($A36="","",IF($T36<=0,"AGOTADO",IF($T36<=N($K36),"REORDENAR","OK"))) -> OK | Z36: =IF($A36="","",IF($T36<=N($K36),ROUNDUP((2*N($K36)-$T36)/$F36,0),0)) -> 0 | AA36: =IF(OR($Y36="REORDENAR",$Y36="AGOTADO"),ROW(),"")
M37: =IF($A37="","",IFERROR($G37/$F37,0)) | N37: =IF($A37="","",IFERROR(SUMIFS(COMPRAS!$N$6:$N$1005,COMPRAS!$D$6:$D$1005,$A37,COMPRAS!$R$6:$R$1005,1)/COUNTIFS(COMPRAS!$D$6:$D$1005,$A37,COMPRAS!$R$6:$R$1005,1),0)) | O37: =IF($A37="","",IF($N37>0,$N37,$M37)) | P37: =IF($A37="","",IF(N($I37)>0,$O37/$I37,$O37)) | Q37: =IF($A37="","",SUMIFS(COMPRAS!$I$6:$I$1005,COMPRAS!$D$6:$D$1005,$A37)) | R37: =IF($A37="","",SUMIFS(RECETAS!$L$6:$L$605,RECETAS!$C$6:$C$605,$A37)) | S37: =IF($A37="","",SUMIFS(MERMAS!$J$6:$J$505,MERMAS!$B$6:$B$505,$A37)) | T37: =IF($A37="","",N($L37)+$Q37-$R37+$S37) | U37: =IF($A37="","",$T37*$O37) | W37: =IF(OR($A37="",$V37=""),"",$V37-$T37) | X37: =IF($W37="","",$W37*$O37) | Y37: =IF($A37="","",IF($T37<=0,"AGOTADO",IF($T37<=N($K37),"REORDENAR","OK"))) | Z37: =IF($A37="","",IF($T37<=N($K37),ROUNDUP((2*N($K37)-$T37)/$F37,0),0)) | AA37: =IF(OR($Y37="REORDENAR",$Y37="AGOTADO"),ROW(),"")
M38: =IF($A38="","",IFERROR($G38/$F38,0)) | N38: =IF($A38="","",IFERROR(SUMIFS(COMPRAS!$N$6:$N$1005,COMPRAS!$D$6:$D$1005,$A38,COMPRAS!$R$6:$R$1005,1)/COUNTIFS(COMPRAS!$D$6:$D$1005,$A38,COMPRAS!$R$6:$R$1005,1),0)) | O38: =IF($A38="","",IF($N38>0,$N38,$M38)) | P38: =IF($A38="","",IF(N($I38)>0,$O38/$I38,$O38)) | Q38: =IF($A38="","",SUMIFS(COMPRAS!$I$6:$I$1005,COMPRAS!$D$6:$D$1005,$A38)) | R38: =IF($A38="","",SUMIFS(RECETAS!$L$6:$L$605,RECETAS!$C$6:$C$605,$A38)) | S38: =IF($A38="","",SUMIFS(MERMAS!$J$6:$J$505,MERMAS!$B$6:$B$505,$A38)) | T38: =IF($A38="","",N($L38)+$Q38-$R38+$S38) | U38: =IF($A38="","",$T38*$O38) | W38: =IF(OR($A38="",$V38=""),"",$V38-$T38) | X38: =IF($W38="","",$W38*$O38) | Y38: =IF($A38="","",IF($T38<=0,"AGOTADO",IF($T38<=N($K38),"REORDENAR","OK"))) | Z38: =IF($A38="","",IF($T38<=N($K38),ROUNDUP((2*N($K38)-$T38)/$F38,0),0)) | AA38: =IF(OR($Y38="REORDENAR",$Y38="AGOTADO"),ROW(),"")
M39: =IF($A39="","",IFERROR($G39/$F39,0)) | N39: =IF($A39="","",IFERROR(SUMIFS(COMPRAS!$N$6:$N$1005,COMPRAS!$D$6:$D$1005,$A39,COMPRAS!$R$6:$R$1005,1)/COUNTIFS(COMPRAS!$D$6:$D$1005,$A39,COMPRAS!$R$6:$R$1005,1),0)) | O39: =IF($A39="","",IF($N39>0,$N39,$M39)) | P39: =IF($A39="","",IF(N($I39)>0,$O39/$I39,$O39)) | Q39: =IF($A39="","",SUMIFS(COMPRAS!$I$6:$I$1005,COMPRAS!$D$6:$D$1005,$A39)) | R39: =IF($A39="","",SUMIFS(RECETAS!$L$6:$L$605,RECETAS!$C$6:$C$605,$A39)) | S39: =IF($A39="","",SUMIFS(MERMAS!$J$6:$J$505,MERMAS!$B$6:$B$505,$A39)) | T39: =IF($A39="","",N($L39)+$Q39-$R39+$S39) | U39: =IF($A39="","",$T39*$O39) | W39: =IF(OR($A39="",$V39=""),"",$V39-$T39) | X39: =IF($W39="","",$W39*$O39) | Y39: =IF($A39="","",IF($T39<=0,"AGOTADO",IF($T39<=N($K39),"REORDENAR","OK"))) | Z39: =IF($A39="","",IF($T39<=N($K39),ROUNDUP((2*N($K39)-$T39)/$F39,0),0)) | AA39: =IF(OR($Y39="REORDENAR",$Y39="AGOTADO"),ROW(),"")
M40: =IF($A40="","",IFERROR($G40/$F40,0)) | N40: =IF($A40="","",IFERROR(SUMIFS(COMPRAS!$N$6:$N$1005,COMPRAS!$D$6:$D$1005,$A40,COMPRAS!$R$6:$R$1005,1)/COUNTIFS(COMPRAS!$D$6:$D$1005,$A40,COMPRAS!$R$6:$R$1005,1),0)) | O40: =IF($A40="","",IF($N40>0,$N40,$M40)) | P40: =IF($A40="","",IF(N($I40)>0,$O40/$I40,$O40)) | Q40: =IF($A40="","",SUMIFS(COMPRAS!$I$6:$I$1005,COMPRAS!$D$6:$D$1005,$A40)) | R40: =IF($A40="","",SUMIFS(RECETAS!$L$6:$L$605,RECETAS!$C$6:$C$605,$A40)) | S40: =IF($A40="","",SUMIFS(MERMAS!$J$6:$J$505,MERMAS!$B$6:$B$505,$A40)) | T40: =IF($A40="","",N($L40)+$Q40-$R40+$S40) | U40: =IF($A40="","",$T40*$O40) | W40: =IF(OR($A40="",$V40=""),"",$V40-$T40) | X40: =IF($W40="","",$W40*$O40) | Y40: =IF($A40="","",IF($T40<=0,"AGOTADO",IF($T40<=N($K40),"REORDENAR","OK"))) | Z40: =IF($A40="","",IF($T40<=N($K40),ROUNDUP((2*N($K40)-$T40)/$F40,0),0)) | AA40: =IF(OR($Y40="REORDENAR",$Y40="AGOTADO"),ROW(),"")
M41: =IF($A41="","",IFERROR($G41/$F41,0)) | N41: =IF($A41="","",IFERROR(SUMIFS(COMPRAS!$N$6:$N$1005,COMPRAS!$D$6:$D$1005,$A41,COMPRAS!$R$6:$R$1005,1)/COUNTIFS(COMPRAS!$D$6:$D$1005,$A41,COMPRAS!$R$6:$R$1005,1),0)) | O41: =IF($A41="","",IF($N41>0,$N41,$M41)) | P41: =IF($A41="","",IF(N($I41)>0,$O41/$I41,$O41)) | Q41: =IF($A41="","",SUMIFS(COMPRAS!$I$6:$I$1005,COMPRAS!$D$6:$D$1005,$A41)) | R41: =IF($A41="","",SUMIFS(RECETAS!$L$6:$L$605,RECETAS!$C$6:$C$605,$A41)) | S41: =IF($A41="","",SUMIFS(MERMAS!$J$6:$J$505,MERMAS!$B$6:$B$505,$A41)) | T41: =IF($A41="","",N($L41)+$Q41-$R41+$S41) | U41: =IF($A41="","",$T41*$O41) | W41: =IF(OR($A41="",$V41=""),"",$V41-$T41) | X41: =IF($W41="","",$W41*$O41) | Y41: =IF($A41="","",IF($T41<=0,"AGOTADO",IF($T41<=N($K41),"REORDENAR","OK"))) | Z41: =IF($A41="","",IF($T41<=N($K41),ROUNDUP((2*N($K41)-$T41)/$F41,0),0)) | AA41: =IF(OR($Y41="REORDENAR",$Y41="AGOTADO"),ROW(),"")
M42: =IF($A42="","",IFERROR($G42/$F42,0)) | N42: =IF($A42="","",IFERROR(SUMIFS(COMPRAS!$N$6:$N$1005,COMPRAS!$D$6:$D$1005,$A42,COMPRAS!$R$6:$R$1005,1)/COUNTIFS(COMPRAS!$D$6:$D$1005,$A42,COMPRAS!$R$6:$R$1005,1),0)) | O42: =IF($A42="","",IF($N42>0,$N42,$M42)) | P42: =IF($A42="","",IF(N($I42)>0,$O42/$I42,$O42)) | Q42: =IF($A42="","",SUMIFS(COMPRAS!$I$6:$I$1005,COMPRAS!$D$6:$D$1005,$A42)) | R42: =IF($A42="","",SUMIFS(RECETAS!$L$6:$L$605,RECETAS!$C$6:$C$605,$A42)) | S42: =IF($A42="","",SUMIFS(MERMAS!$J$6:$J$505,MERMAS!$B$6:$B$505,$A42)) | T42: =IF($A42="","",N($L42)+$Q42-$R42+$S42) | U42: =IF($A42="","",$T42*$O42) | W42: =IF(OR($A42="",$V42=""),"",$V42-$T42) | X42: =IF($W42="","",$W42*$O42) | Y42: =IF($A42="","",IF($T42<=0,"AGOTADO",IF($T42<=N($K42),"REORDENAR","OK"))) | Z42: =IF($A42="","",IF($T42<=N($K42),ROUNDUP((2*N($K42)-$T42)/$F42,0),0)) | AA42: =IF(OR($Y42="REORDENAR",$Y42="AGOTADO"),ROW(),"")
M43: =IF($A43="","",IFERROR($G43/$F43,0)) | N43: =IF($A43="","",IFERROR(SUMIFS(COMPRAS!$N$6:$N$1005,COMPRAS!$D$6:$D$1005,$A43,COMPRAS!$R$6:$R$1005,1)/COUNTIFS(COMPRAS!$D$6:$D$1005,$A43,COMPRAS!$R$6:$R$1005,1),0)) | O43: =IF($A43="","",IF($N43>0,$N43,$M43)) | P43: =IF($A43="","",IF(N($I43)>0,$O43/$I43,$O43)) | Q43: =IF($A43="","",SUMIFS(COMPRAS!$I$6:$I$1005,COMPRAS!$D$6:$D$1005,$A43)) | R43: =IF($A43="","",SUMIFS(RECETAS!$L$6:$L$605,RECETAS!$C$6:$C$605,$A43)) | S43: =IF($A43="","",SUMIFS(MERMAS!$J$6:$J$505,MERMAS!$B$6:$B$505,$A43)) | T43: =IF($A43="","",N($L43)+$Q43-$R43+$S43) | U43: =IF($A43="","",$T43*$O43) | W43: =IF(OR($A43="",$V43=""),"",$V43-$T43) | X43: =IF($W43="","",$W43*$O43) | Y43: =IF($A43="","",IF($T43<=0,"AGOTADO",IF($T43<=N($K43),"REORDENAR","OK"))) | Z43: =IF($A43="","",IF($T43<=N($K43),ROUNDUP((2*N($K43)-$T43)/$F43,0),0)) | AA43: =IF(OR($Y43="REORDENAR",$Y43="AGOTADO"),ROW(),"")
M44: =IF($A44="","",IFERROR($G44/$F44,0)) | N44: =IF($A44="","",IFERROR(SUMIFS(COMPRAS!$N$6:$N$1005,COMPRAS!$D$6:$D$1005,$A44,COMPRAS!$R$6:$R$1005,1)/COUNTIFS(COMPRAS!$D$6:$D$1005,$A44,COMPRAS!$R$6:$R$1005,1),0)) | O44: =IF($A44="","",IF($N44>0,$N44,$M44)) | P44: =IF($A44="","",IF(N($I44)>0,$O44/$I44,$O44)) | Q44: =IF($A44="","",SUMIFS(COMPRAS!$I$6:$I$1005,COMPRAS!$D$6:$D$1005,$A44)) | R44: =IF($A44="","",SUMIFS(RECETAS!$L$6:$L$605,RECETAS!$C$6:$C$605,$A44)) | S44: =IF($A44="","",SUMIFS(MERMAS!$J$6:$J$505,MERMAS!$B$6:$B$505,$A44)) | T44: =IF($A44="","",N($L44)+$Q44-$R44+$S44) | U44: =IF($A44="","",$T44*$O44) | W44: =IF(OR($A44="",$V44=""),"",$V44-$T44) | X44: =IF($W44="","",$W44*$O44) | Y44: =IF($A44="","",IF($T44<=0,"AGOTADO",IF($T44<=N($K44),"REORDENAR","OK"))) | Z44: =IF($A44="","",IF($T44<=N($K44),ROUNDUP((2*N($K44)-$T44)/$F44,0),0)) | AA44: =IF(OR($Y44="REORDENAR",$Y44="AGOTADO"),ROW(),"")
M45: =IF($A45="","",IFERROR($G45/$F45,0)) | N45: =IF($A45="","",IFERROR(SUMIFS(COMPRAS!$N$6:$N$1005,COMPRAS!$D$6:$D$1005,$A45,COMPRAS!$R$6:$R$1005,1)/COUNTIFS(COMPRAS!$D$6:$D$1005,$A45,COMPRAS!$R$6:$R$1005,1),0)) | O45: =IF($A45="","",IF($N45>0,$N45,$M45)) | P45: =IF($A45="","",IF(N($I45)>0,$O45/$I45,$O45)) | Q45: =IF($A45="","",SUMIFS(COMPRAS!$I$6:$I$1005,COMPRAS!$D$6:$D$1005,$A45)) | R45: =IF($A45="","",SUMIFS(RECETAS!$L$6:$L$605,RECETAS!$C$6:$C$605,$A45)) | S45: =IF($A45="","",SUMIFS(MERMAS!$J$6:$J$505,MERMAS!$B$6:$B$505,$A45)) | T45: =IF($A45="","",N($L45)+$Q45-$R45+$S45) | U45: =IF($A45="","",$T45*$O45) | W45: =IF(OR($A45="",$V45=""),"",$V45-$T45) | X45: =IF($W45="","",$W45*$O45) | Y45: =IF($A45="","",IF($T45<=0,"AGOTADO",IF($T45<=N($K45),"REORDENAR","OK"))) | Z45: =IF($A45="","",IF($T45<=N($K45),ROUNDUP((2*N($K45)-$T45)/$F45,0),0)) | AA45: =IF(OR($Y45="REORDENAR",$Y45="AGOTADO"),ROW(),"")
M46: =IF($A46="","",IFERROR($G46/$F46,0)) | N46: =IF($A46="","",IFERROR(SUMIFS(COMPRAS!$N$6:$N$1005,COMPRAS!$D$6:$D$1005,$A46,COMPRAS!$R$6:$R$1005,1)/COUNTIFS(COMPRAS!$D$6:$D$1005,$A46,COMPRAS!$R$6:$R$1005,1),0)) | O46: =IF($A46="","",IF($N46>0,$N46,$M46)) | P46: =IF($A46="","",IF(N($I46)>0,$O46/$I46,$O46)) | Q46: =IF($A46="","",SUMIFS(COMPRAS!$I$6:$I$1005,COMPRAS!$D$6:$D$1005,$A46)) | R46: =IF($A46="","",SUMIFS(RECETAS!$L$6:$L$605,RECETAS!$C$6:$C$605,$A46)) | S46: =IF($A46="","",SUMIFS(MERMAS!$J$6:$J$505,MERMAS!$B$6:$B$505,$A46)) | T46: =IF($A46="","",N($L46)+$Q46-$R46+$S46) | U46: =IF($A46="","",$T46*$O46) | W46: =IF(OR($A46="",$V46=""),"",$V46-$T46) | X46: =IF($W46="","",$W46*$O46) | Y46: =IF($A46="","",IF($T46<=0,"AGOTADO",IF($T46<=N($K46),"REORDENAR","OK"))) | Z46: =IF($A46="","",IF($T46<=N($K46),ROUNDUP((2*N($K46)-$T46)/$F46,0),0)) | AA46: =IF(OR($Y46="REORDENAR",$Y46="AGOTADO"),ROW(),"")
M47: =IF($A47="","",IFERROR($G47/$F47,0)) | N47: =IF($A47="","",IFERROR(SUMIFS(COMPRAS!$N$6:$N$1005,COMPRAS!$D$6:$D$1005,$A47,COMPRAS!$R$6:$R$1005,1)/COUNTIFS(COMPRAS!$D$6:$D$1005,$A47,COMPRAS!$R$6:$R$1005,1),0)) | O47: =IF($A47="","",IF($N47>0,$N47,$M47)) | P47: =IF($A47="","",IF(N($I47)>0,$O47/$I47,$O47)) | Q47: =IF($A47="","",SUMIFS(COMPRAS!$I$6:$I$1005,COMPRAS!$D$6:$D$1005,$A47)) | R47: =IF($A47="","",SUMIFS(RECETAS!$L$6:$L$605,RECETAS!$C$6:$C$605,$A47)) | S47: =IF($A47="","",SUMIFS(MERMAS!$J$6:$J$505,MERMAS!$B$6:$B$505,$A47)) | T47: =IF($A47="","",N($L47)+$Q47-$R47+$S47) | U47: =IF($A47="","",$T47*$O47) | W47: =IF(OR($A47="",$V47=""),"",$V47-$T47) | X47: =IF($W47="","",$W47*$O47) | Y47: =IF($A47="","",IF($T47<=0,"AGOTADO",IF($T47<=N($K47),"REORDENAR","OK"))) | Z47: =IF($A47="","",IF($T47<=N($K47),ROUNDUP((2*N($K47)-$T47)/$F47,0),0)) | AA47: =IF(OR($Y47="REORDENAR",$Y47="AGOTADO"),ROW(),"")
M48: =IF($A48="","",IFERROR($G48/$F48,0)) | N48: =IF($A48="","",IFERROR(SUMIFS(COMPRAS!$N$6:$N$1005,COMPRAS!$D$6:$D$1005,$A48,COMPRAS!$R$6:$R$1005,1)/COUNTIFS(COMPRAS!$D$6:$D$1005,$A48,COMPRAS!$R$6:$R$1005,1),0)) | O48: =IF($A48="","",IF($N48>0,$N48,$M48)) | P48: =IF($A48="","",IF(N($I48)>0,$O48/$I48,$O48)) | Q48: =IF($A48="","",SUMIFS(COMPRAS!$I$6:$I$1005,COMPRAS!$D$6:$D$1005,$A48)) | R48: =IF($A48="","",SUMIFS(RECETAS!$L$6:$L$605,RECETAS!$C$6:$C$605,$A48)) | S48: =IF($A48="","",SUMIFS(MERMAS!$J$6:$J$505,MERMAS!$B$6:$B$505,$A48)) | T48: =IF($A48="","",N($L48)+$Q48-$R48+$S48) | U48: =IF($A48="","",$T48*$O48) | W48: =IF(OR($A48="",$V48=""),"",$V48-$T48) | X48: =IF($W48="","",$W48*$O48) | Y48: =IF($A48="","",IF($T48<=0,"AGOTADO",IF($T48<=N($K48),"REORDENAR","OK"))) | Z48: =IF($A48="","",IF($T48<=N($K48),ROUNDUP((2*N($K48)-$T48)/$F48,0),0)) | AA48: =IF(OR($Y48="REORDENAR",$Y48="AGOTADO"),ROW(),"")
... M205: =IF($A205="","",IFERROR($G205/$F205,0)) | N205: =IF($A205="","",IFERROR(SUMIFS(COMPRAS!$N$6:$N$1005,COMPRAS!$D$6:$D$1005,$A205,COMPRAS!$R$6:$R$1005,1)/COUNTIFS(COMPRAS!$D$6:$D$1005,$A205,COMPRAS!$R$6:$R$1005,1),0)) | O205: =IF($A205="","",IF($N205>0,$N205,$M205)) | P205: =IF($A205="","",IF(N($I205)>0,$O205/$I205,$O205)) | Q205: =IF($A205="","",SUMIFS(COMPRAS!$I$6:$I$1005,COMPRAS!$D$6:$D$1005,$A205)) | R205: =IF($A205="","",SUMIFS(RECETAS!$L$6:$L$605,RECETAS!$C$6:$C$605,$A205)) | S205: =IF($A205="","",SUMIFS(MERMAS!$J$6:$J$505,MERMAS!$B$6:$B$505,$A205)) | T205: =IF($A205="","",N($L205)+$Q205-$R205+$S205) | U205: =IF($A205="","",$T205*$O205) | W205: =IF(OR($A205="",$V205=""),"",$V205-$T205) | X205: =IF($W205="","",$W205*$O205) | Y205: =IF($A205="","",IF($T205<=0,"AGOTADO",IF($T205<=N($K205),"REORDENAR","OK"))) | Z205: =IF($A205="","",IF($T205<=N($K205),ROUNDUP((2*N($K205)-$T205)/$F205,0),0)) | AA205: =IF(OR($Y205="REORDENAR",$Y205="AGOTADO"),ROW(),"")

Sheet COMPRAS
A1: REGISTRO DE COMPRAS A PROVEEDORES
A2: Una línea por insumo de cada factura. La cantidad se escribe en PRESENTACIONES (cajas, paquetes, latas); el libro la convierte a unidad base y la suma al inventario.
L4: Pendiente de pago: | M4: =SUMIFS(M6:M1005,P6:P1005,"Pendiente") -> 51246
A5: Fecha | B5: N° factura | C5: Proveedor | D5: Código insumo | E5: Insumo | F5: Presentación | G5: Cantidad (presenta-ciones) | H5: Contenido por presentación | I5: Cantidad en unid. base | J5: Subtotal sin IVA | K5: % IVA | L5: IVA | M5: Total factura línea | N5: Costo por unid. base | O5: Forma de pago | P5: Estado de pago | Q5: Mes | R5: Última compra del insumo (1=sí)
A6: 46296 | B6: FA-1021 | C6: Productor / feria | D6: I001 | E6: =IF($D6="","",IFERROR(INDEX(INSUMOS!$B$6:$B$205,MATCH($D6,INSUMOS!$A$6:$A$205,0)),"¿Código?")) -> Fresas frescas | F6: =IF($D6="","",IFERROR(INDEX(INSUMOS!$E$6:$E$205,MATCH($D6,INSUMOS!$A$6:$A$205,0)),"")) -> Caja 5 kg | G6: 3 | H6: =IF($D6="","",IFERROR(INDEX(INSUMOS!$F$6:$F$205,MATCH($D6,INSUMOS!$A$6:$A$205,0)),0)) -> 5000 | I6: =IF($D6="","",N($G6)*$H6) -> 15000 | J6: 42000 | K6: =IF($D6="","",IFERROR(INDEX(INSUMOS!$H$6:$H$205,MATCH($D6,INSUMOS!$A$6:$A$205,0)),IVA_VENTAS)) -> 0.01 | L6: =IF($D6="","",N($J6)*$K6) -> 420 | M6: =IF($D6="","",N($J6)+$L6) -> 42420 | N6: =IF($D6="","",IFERROR(N($J6)/$I6,0)) -> 2.8 | O6: Contado | P6: Pagado | Q6: =IF($A6="","",DATE(YEAR($A6),MONTH($A6),1)) -> 46296 | R6: =IF(OR($A6="",$D6=""),"",IF(COUNTIFS($D$6:$D$1005,$D6,$A$6:$A$1005,">"&$A6)=0,1,0)) -> 1
A7: 46296 | B7: FA-1021 | C7: Productor / feria | D7: I002 | E7: =IF($D7="","",IFERROR(INDEX(INSUMOS!$B$6:$B$205,MATCH($D7,INSUMOS!$A$6:$A$205,0)),"¿Código?")) -> Mango maduro | F7: =IF($D7="","",IFERROR(INDEX(INSUMOS!$E$6:$E$205,MATCH($D7,INSUMOS!$A$6:$A$205,0)),"")) -> Kilo | G7: 5 | H7: =IF($D7="","",IFERROR(INDEX(INSUMOS!$F$6:$F$205,MATCH($D7,INSUMOS!$A$6:$A$205,0)),0)) -> 1000 | I7: =IF($D7="","",N($G7)*$H7) -> 5000 | J7: 6500 | K7: =IF($D7="","",IFERROR(INDEX(INSUMOS!$H$6:$H$205,MATCH($D7,INSUMOS!$A$6:$A$205,0)),IVA_VENTAS)) -> 0.01 | L7: =IF($D7="","",N($J7)*$K7) -> 65 | M7: =IF($D7="","",N($J7)+$L7) -> 6565 | N7: =IF($D7="","",IFERROR(N($J7)/$I7,0)) -> 1.3 | O7: Contado | P7: Pagado | Q7: =IF($A7="","",DATE(YEAR($A7),MONTH($A7),1)) -> 46296 | R7: =IF(OR($A7="",$D7=""),"",IF(COUNTIFS($D$6:$D$1005,$D7,$A$6:$A$1005,">"&$A7)=0,1,0)) -> 1
A8: 46297 | B8: D-5530 | C8: Distribuidora lácteos | D8: I004 | E8: =IF($D8="","",IFERROR(INDEX(INSUMOS!$B$6:$B$205,MATCH($D8,INSUMOS!$A$6:$A$205,0)),"¿Código?")) -> Crema dulce | F8: =IF($D8="","",IFERROR(INDEX(INSUMOS!$E$6:$E$205,MATCH($D8,INSUMOS!$A$6:$A$205,0)),"")) -> Caja 1 L | G8: 12 | H8: =IF($D8="","",IFERROR(INDEX(INSUMOS!$F$6:$F$205,MATCH($D8,INSUMOS!$A$6:$A$205,0)),0)) -> 1000 | I8: =IF($D8="","",N($G8)*$H8) -> 12000 | J8: 30600 | K8: =IF($D8="","",IFERROR(INDEX(INSUMOS!$H$6:$H$205,MATCH($D8,INSUMOS!$A$6:$A$205,0)),IVA_VENTAS)) -> 0.01 | L8: =IF($D8="","",N($J8)*$K8) -> 306 | M8: =IF($D8="","",N($J8)+$L8) -> 30906 | N8: =IF($D8="","",IFERROR(N($J8)/$I8,0)) -> 2.55 | O8: Crédito | P8: Pendiente | Q8: =IF($A8="","",DATE(YEAR($A8),MONTH($A8),1)) -> 46296 | R8: =IF(OR($A8="",$D8=""),"",IF(COUNTIFS($D$6:$D$1005,$D8,$A$6:$A$1005,">"&$A8)=0,1,0)) -> 1
A9: 46297 | B9: M-8812 | C9: Mayorista | D9: I005 | E9: =IF($D9="","",IFERROR(INDEX(INSUMOS!$B$6:$B$205,MATCH($D9,INSUMOS!$A$6:$A$205,0)),"¿Código?")) -> Leche condensada | F9: =IF($D9="","",IFERROR(INDEX(INSUMOS!$E$6:$E$205,MATCH($D9,INSUMOS!$A$6:$A$205,0)),"")) -> Lata 397 g | G9: 24 | H9: =IF($D9="","",IFERROR(INDEX(INSUMOS!$F$6:$F$205,MATCH($D9,INSUMOS!$A$6:$A$205,0)),0)) -> 397 | I9: =IF($D9="","",N($G9)*$H9) -> 9528 | J9: 30000 | K9: =IF($D9="","",IFERROR(INDEX(INSUMOS!$H$6:$H$205,MATCH($D9,INSUMOS!$A$6:$A$205,0)),IVA_VENTAS)) -> 0.13 | L9: =IF($D9="","",N($J9)*$K9) -> 3900 | M9: =IF($D9="","",N($J9)+$L9) -> 33900 | N9: =IF($D9="","",IFERROR(N($J9)/$I9,0)) -> 3.1486146 | O9: Contado | P9: Pagado | Q9: =IF($A9="","",DATE(YEAR($A9),MONTH($A9),1)) -> 46296 | R9: =IF(OR($A9="",$D9=""),"",IF(COUNTIFS($D$6:$D$1005,$D9,$A$6:$A$1005,">"&$A9)=0,1,0)) -> 1
A10: 46297 | B10: M-8812 | C10: Mayorista | D10: I008 | E10: =IF($D10="","",IFERROR(INDEX(INSUMOS!$B$6:$B$205,MATCH($D10,INSUMOS!$A$6:$A$205,0)),"¿Código?")) -> Galleta Oreo triturada | F10: =IF($D10="","",IFERROR(INDEX(INSUMOS!$E$6:$E$205,MATCH($D10,INSUMOS!$A$6:$A$205,0)),"")) -> Paquete 432 g | G10: 4 | H10: =IF($D10="","",IFERROR(INDEX(INSUMOS!$F$6:$F$205,MATCH($D10,INSUMOS!$A$6:$A$205,0)),0)) -> 432 | I10: =IF($D10="","",N($G10)*$H10) -> 1728 | J10: 10400 | K10: =IF($D10="","",IFERROR(INDEX(INSUMOS!$H$6:$H$205,MATCH($D10,INSUMOS!$A$6:$A$205,0)),IVA_VENTAS)) -> 0.13 | L10: =IF($D10="","",N($J10)*$K10) -> 1352 | M10: =IF($D10="","",N($J10)+$L10) -> 11752 | N10: =IF($D10="","",IFERROR(N($J10)/$I10,0)) -> 6.0185185 | O10: Contado | P10: Pagado | Q10: =IF($A10="","",DATE(YEAR($A10),MONTH($A10),1)) -> 46296 | R10: =IF(OR($A10="",$D10=""),"",IF(COUNTIFS($D$6:$D$1005,$D10,$A$6:$A$1005,">"&$A10)=0,1,0)) -> 1
A11: 46298 | B11: E-0099 | C11: Empaques CR | D11: I021 | E11: =IF($D11="","",IFERROR(INDEX(INSUMOS!$B$6:$B$205,MATCH($D11,INSUMOS!$A$6:$A$205,0)),"¿Código?")) -> Vaso 12 oz con tapa | F11: =IF($D11="","",IFERROR(INDEX(INSUMOS!$E$6:$E$205,MATCH($D11,INSUMOS!$A$6:$A$205,0)),"")) -> Paquete 50 u | G11: 4 | H11: =IF($D11="","",IFERROR(INDEX(INSUMOS!$F$6:$F$205,MATCH($D11,INSUMOS!$A$6:$A$205,0)),0)) -> 50 | I11: =IF($D11="","",N($G11)*$H11) -> 200 | J11: 18000 | K11: =IF($D11="","",IFERROR(INDEX(INSUMOS!$H$6:$H$205,MATCH($D11,INSUMOS!$A$6:$A$205,0)),IVA_VENTAS)) -> 0.13 | L11: =IF($D11="","",N($J11)*$K11) -> 2340 | M11: =IF($D11="","",N($J11)+$L11) -> 20340 | N11: =IF($D11="","",IFERROR(N($J11)/$I11,0)) -> 90 | O11: Crédito | P11: Pendiente | Q11: =IF($A11="","",DATE(YEAR($A11),MONTH($A11),1)) -> 46296 | R11: =IF(OR($A11="",$D11=""),"",IF(COUNTIFS($D$6:$D$1005,$D11,$A$6:$A$1005,">"&$A11)=0,1,0)) -> 1
E12: =IF($D12="","",IFERROR(INDEX(INSUMOS!$B$6:$B$205,MATCH($D12,INSUMOS!$A$6:$A$205,0)),"¿Código?")) | F12: =IF($D12="","",IFERROR(INDEX(INSUMOS!$E$6:$E$205,MATCH($D12,INSUMOS!$A$6:$A$205,0)),"")) | H12: =IF($D12="","",IFERROR(INDEX(INSUMOS!$F$6:$F$205,MATCH($D12,INSUMOS!$A$6:$A$205,0)),0)) | I12: =IF($D12="","",N($G12)*$H12) | K12: =IF($D12="","",IFERROR(INDEX(INSUMOS!$H$6:$H$205,MATCH($D12,INSUMOS!$A$6:$A$205,0)),IVA_VENTAS)) | L12: =IF($D12="","",N($J12)*$K12) | M12: =IF($D12="","",N($J12)+$L12) | N12: =IF($D12="","",IFERROR(N($J12)/$I12,0)) | Q12: =IF($A12="","",DATE(YEAR($A12),MONTH($A12),1)) | R12: =IF(OR($A12="",$D12=""),"",IF(COUNTIFS($D$6:$D$1005,$D12,$A$6:$A$1005,">"&$A12)=0,1,0))
E13: =IF($D13="","",IFERROR(INDEX(INSUMOS!$B$6:$B$205,MATCH($D13,INSUMOS!$A$6:$A$205,0)),"¿Código?")) | F13: =IF($D13="","",IFERROR(INDEX(INSUMOS!$E$6:$E$205,MATCH($D13,INSUMOS!$A$6:$A$205,0)),"")) | H13: =IF($D13="","",IFERROR(INDEX(INSUMOS!$F$6:$F$205,MATCH($D13,INSUMOS!$A$6:$A$205,0)),0)) | I13: =IF($D13="","",N($G13)*$H13) | K13: =IF($D13="","",IFERROR(INDEX(INSUMOS!$H$6:$H$205,MATCH($D13,INSUMOS!$A$6:$A$205,0)),IVA_VENTAS)) | L13: =IF($D13="","",N($J13)*$K13) | M13: =IF($D13="","",N($J13)+$L13) | N13: =IF($D13="","",IFERROR(N($J13)/$I13,0)) | Q13: =IF($A13="","",DATE(YEAR($A13),MONTH($A13),1)) | R13: =IF(OR($A13="",$D13=""),"",IF(COUNTIFS($D$6:$D$1005,$D13,$A$6:$A$1005,">"&$A13)=0,1,0))
E14: =IF($D14="","",IFERROR(INDEX(INSUMOS!$B$6:$B$205,MATCH($D14,INSUMOS!$A$6:$A$205,0)),"¿Código?")) | F14: =IF($D14="","",IFERROR(INDEX(INSUMOS!$E$6:$E$205,MATCH($D14,INSUMOS!$A$6:$A$205,0)),"")) | H14: =IF($D14="","",IFERROR(INDEX(INSUMOS!$F$6:$F$205,MATCH($D14,INSUMOS!$A$6:$A$205,0)),0)) | I14: =IF($D14="","",N($G14)*$H14) | K14: =IF($D14="","",IFERROR(INDEX(INSUMOS!$H$6:$H$205,MATCH($D14,INSUMOS!$A$6:$A$205,0)),IVA_VENTAS)) | L14: =IF($D14="","",N($J14)*$K14) | M14: =IF($D14="","",N($J14)+$L14) | N14: =IF($D14="","",IFERROR(N($J14)/$I14,0)) | Q14: =IF($A14="","",DATE(YEAR($A14),MONTH($A14),1)) | R14: =IF(OR($A14="",$D14=""),"",IF(COUNTIFS($D$6:$D$1005,$D14,$A$6:$A$1005,">"&$A14)=0,1,0))
E15: =IF($D15="","",IFERROR(INDEX(INSUMOS!$B$6:$B$205,MATCH($D15,INSUMOS!$A$6:$A$205,0)),"¿Código?")) | F15: =IF($D15="","",IFERROR(INDEX(INSUMOS!$E$6:$E$205,MATCH($D15,INSUMOS!$A$6:$A$205,0)),"")) | H15: =IF($D15="","",IFERROR(INDEX(INSUMOS!$F$6:$F$205,MATCH($D15,INSUMOS!$A$6:$A$205,0)),0)) | I15: =IF($D15="","",N($G15)*$H15) | K15: =IF($D15="","",IFERROR(INDEX(INSUMOS!$H$6:$H$205,MATCH($D15,INSUMOS!$A$6:$A$205,0)),IVA_VENTAS)) | L15: =IF($D15="","",N($J15)*$K15) | M15: =IF($D15="","",N($J15)+$L15) | N15: =IF($D15="","",IFERROR(N($J15)/$I15,0)) | Q15: =IF($A15="","",DATE(YEAR($A15),MONTH($A15),1)) | R15: =IF(OR($A15="",$D15=""),"",IF(COUNTIFS($D$6:$D$1005,$D15,$A$6:$A$1005,">"&$A15)=0,1,0))
E16: =IF($D16="","",IFERROR(INDEX(INSUMOS!$B$6:$B$205,MATCH($D16,INSUMOS!$A$6:$A$205,0)),"¿Código?")) | F16: =IF($D16="","",IFERROR(INDEX(INSUMOS!$E$6:$E$205,MATCH($D16,INSUMOS!$A$6:$A$205,0)),"")) | H16: =IF($D16="","",IFERROR(INDEX(INSUMOS!$F$6:$F$205,MATCH($D16,INSUMOS!$A$6:$A$205,0)),0)) | I16: =IF($D16="","",N($G16)*$H16) | K16: =IF($D16="","",IFERROR(INDEX(INSUMOS!$H$6:$H$205,MATCH($D16,INSUMOS!$A$6:$A$205,0)),IVA_VENTAS)) | L16: =IF($D16="","",N($J16)*$K16) | M16: =IF($D16="","",N($J16)+$L16) | N16: =IF($D16="","",IFERROR(N($J16)/$I16,0)) | Q16: =IF($A16="","",DATE(YEAR($A16),MONTH($A16),1)) | R16: =IF(OR($A16="",$D16=""),"",IF(COUNTIFS($D$6:$D$1005,$D16,$A$6:$A$1005,">"&$A16)=0,1,0))
E17: =IF($D17="","",IFERROR(INDEX(INSUMOS!$B$6:$B$205,MATCH($D17,INSUMOS!$A$6:$A$205,0)),"¿Código?")) | F17: =IF($D17="","",IFERROR(INDEX(INSUMOS!$E$6:$E$205,MATCH($D17,INSUMOS!$A$6:$A$205,0)),"")) | H17: =IF($D17="","",IFERROR(INDEX(INSUMOS!$F$6:$F$205,MATCH($D17,INSUMOS!$A$6:$A$205,0)),0)) | I17: =IF($D17="","",N($G17)*$H17) | K17: =IF($D17="","",IFERROR(INDEX(INSUMOS!$H$6:$H$205,MATCH($D17,INSUMOS!$A$6:$A$205,0)),IVA_VENTAS)) | L17: =IF($D17="","",N($J17)*$K17) | M17: =IF($D17="","",N($J17)+$L17) | N17: =IF($D17="","",IFERROR(N($J17)/$I17,0)) | Q17: =IF($A17="","",DATE(YEAR($A17),MONTH($A17),1)) | R17: =IF(OR($A17="",$D17=""),"",IF(COUNTIFS($D$6:$D$1005,$D17,$A$6:$A$1005,">"&$A17)=0,1,0))
E18: =IF($D18="","",IFERROR(INDEX(INSUMOS!$B$6:$B$205,MATCH($D18,INSUMOS!$A$6:$A$205,0)),"¿Código?")) | F18: =IF($D18="","",IFERROR(INDEX(INSUMOS!$E$6:$E$205,MATCH($D18,INSUMOS!$A$6:$A$205,0)),"")) | H18: =IF($D18="","",IFERROR(INDEX(INSUMOS!$F$6:$F$205,MATCH($D18,INSUMOS!$A$6:$A$205,0)),0)) | I18: =IF($D18="","",N($G18)*$H18) | K18: =IF($D18="","",IFERROR(INDEX(INSUMOS!$H$6:$H$205,MATCH($D18,INSUMOS!$A$6:$A$205,0)),IVA_VENTAS)) | L18: =IF($D18="","",N($J18)*$K18) | M18: =IF($D18="","",N($J18)+$L18) | N18: =IF($D18="","",IFERROR(N($J18)/$I18,0)) | Q18: =IF($A18="","",DATE(YEAR($A18),MONTH($A18),1)) | R18: =IF(OR($A18="",$D18=""),"",IF(COUNTIFS($D$6:$D$1005,$D18,$A$6:$A$1005,">"&$A18)=0,1,0))
E19: =IF($D19="","",IFERROR(INDEX(INSUMOS!$B$6:$B$205,MATCH($D19,INSUMOS!$A$6:$A$205,0)),"¿Código?")) | F19: =IF($D19="","",IFERROR(INDEX(INSUMOS!$E$6:$E$205,MATCH($D19,INSUMOS!$A$6:$A$205,0)),"")) | H19: =IF($D19="","",IFERROR(INDEX(INSUMOS!$F$6:$F$205,MATCH($D19,INSUMOS!$A$6:$A$205,0)),0)) | I19: =IF($D19="","",N($G19)*$H19) | K19: =IF($D19="","",IFERROR(INDEX(INSUMOS!$H$6:$H$205,MATCH($D19,INSUMOS!$A$6:$A$205,0)),IVA_VENTAS)) | L19: =IF($D19="","",N($J19)*$K19) | M19: =IF($D19="","",N($J19)+$L19) | N19: =IF($D19="","",IFERROR(N($J19)/$I19,0)) | Q19: =IF($A19="","",DATE(YEAR($A19),MONTH($A19),1)) | R19: =IF(OR($A19="",$D19=""),"",IF(COUNTIFS($D$6:$D$1005,$D19,$A$6:$A$1005,">"&$A19)=0,1,0))
E20: =IF($D20="","",IFERROR(INDEX(INSUMOS!$B$6:$B$205,MATCH($D20,INSUMOS!$A$6:$A$205,0)),"¿Código?")) | F20: =IF($D20="","",IFERROR(INDEX(INSUMOS!$E$6:$E$205,MATCH($D20,INSUMOS!$A$6:$A$205,0)),"")) | H20: =IF($D20="","",IFERROR(INDEX(INSUMOS!$F$6:$F$205,MATCH($D20,INSUMOS!$A$6:$A$205,0)),0)) | I20: =IF($D20="","",N($G20)*$H20) | K20: =IF($D20="","",IFERROR(INDEX(INSUMOS!$H$6:$H$205,MATCH($D20,INSUMOS!$A$6:$A$205,0)),IVA_VENTAS)) | L20: =IF($D20="","",N($J20)*$K20) | M20: =IF($D20="","",N($J20)+$L20) | N20: =IF($D20="","",IFERROR(N($J20)/$I20,0)) | Q20: =IF($A20="","",DATE(YEAR($A20),MONTH($A20),1)) | R20: =IF(OR($A20="",$D20=""),"",IF(COUNTIFS($D$6:$D$1005,$D20,$A$6:$A$1005,">"&$A20)=0,1,0))
E21: =IF($D21="","",IFERROR(INDEX(INSUMOS!$B$6:$B$205,MATCH($D21,INSUMOS!$A$6:$A$205,0)),"¿Código?")) | F21: =IF($D21="","",IFERROR(INDEX(INSUMOS!$E$6:$E$205,MATCH($D21,INSUMOS!$A$6:$A$205,0)),"")) | H21: =IF($D21="","",IFERROR(INDEX(INSUMOS!$F$6:$F$205,MATCH($D21,INSUMOS!$A$6:$A$205,0)),0)) | I21: =IF($D21="","",N($G21)*$H21) | K21: =IF($D21="","",IFERROR(INDEX(INSUMOS!$H$6:$H$205,MATCH($D21,INSUMOS!$A$6:$A$205,0)),IVA_VENTAS)) | L21: =IF($D21="","",N($J21)*$K21) | M21: =IF($D21="","",N($J21)+$L21) | N21: =IF($D21="","",IFERROR(N($J21)/$I21,0)) | Q21: =IF($A21="","",DATE(YEAR($A21),MONTH($A21),1)) | R21: =IF(OR($A21="",$D21=""),"",IF(COUNTIFS($D$6:$D$1005,$D21,$A$6:$A$1005,">"&$A21)=0,1,0))
E22: =IF($D22="","",IFERROR(INDEX(INSUMOS!$B$6:$B$205,MATCH($D22,INSUMOS!$A$6:$A$205,0)),"¿Código?")) | F22: =IF($D22="","",IFERROR(INDEX(INSUMOS!$E$6:$E$205,MATCH($D22,INSUMOS!$A$6:$A$205,0)),"")) | H22: =IF($D22="","",IFERROR(INDEX(INSUMOS!$F$6:$F$205,MATCH($D22,INSUMOS!$A$6:$A$205,0)),0)) | I22: =IF($D22="","",N($G22)*$H22) | K22: =IF($D22="","",IFERROR(INDEX(INSUMOS!$H$6:$H$205,MATCH($D22,INSUMOS!$A$6:$A$205,0)),IVA_VENTAS)) | L22: =IF($D22="","",N($J22)*$K22) | M22: =IF($D22="","",N($J22)+$L22) | N22: =IF($D22="","",IFERROR(N($J22)/$I22,0)) | Q22: =IF($A22="","",DATE(YEAR($A22),MONTH($A22),1)) | R22: =IF(OR($A22="",$D22=""),"",IF(COUNTIFS($D$6:$D$1005,$D22,$A$6:$A$1005,">"&$A22)=0,1,0))
E23: =IF($D23="","",IFERROR(INDEX(INSUMOS!$B$6:$B$205,MATCH($D23,INSUMOS!$A$6:$A$205,0)),"¿Código?")) | F23: =IF($D23="","",IFERROR(INDEX(INSUMOS!$E$6:$E$205,MATCH($D23,INSUMOS!$A$6:$A$205,0)),"")) | H23: =IF($D23="","",IFERROR(INDEX(INSUMOS!$F$6:$F$205,MATCH($D23,INSUMOS!$A$6:$A$205,0)),0)) | I23: =IF($D23="","",N($G23)*$H23) | K23: =IF($D23="","",IFERROR(INDEX(INSUMOS!$H$6:$H$205,MATCH($D23,INSUMOS!$A$6:$A$205,0)),IVA_VENTAS)) | L23: =IF($D23="","",N($J23)*$K23) | M23: =IF($D23="","",N($J23)+$L23) | N23: =IF($D23="","",IFERROR(N($J23)/$I23,0)) | Q23: =IF($A23="","",DATE(YEAR($A23),MONTH($A23),1)) | R23: =IF(OR($A23="",$D23=""),"",IF(COUNTIFS($D$6:$D$1005,$D23,$A$6:$A$1005,">"&$A23)=0,1,0))
... E1005: =IF($D1005="","",IFERROR(INDEX(INSUMOS!$B$6:$B$205,MATCH($D1005,INSUMOS!$A$6:$A$205,0)),"¿Código?")) | F1005: =IF($D1005="","",IFERROR(INDEX(INSUMOS!$E$6:$E$205,MATCH($D1005,INSUMOS!$A$6:$A$205,0)),"")) | H1005: =IF($D1005="","",IFERROR(INDEX(INSUMOS!$F$6:$F$205,MATCH($D1005,INSUMOS!$A$6:$A$205,0)),0)) | I1005: =IF($D1005="","",N($G1005)*$H1005) | K1005: =IF($D1005="","",IFERROR(INDEX(INSUMOS!$H$6:$H$205,MATCH($D1005,INSUMOS!$A$6:$A$205,0)),IVA_VENTAS)) | L1005: =IF($D1005="","",N($J1005)*$K1005) | M1005: =IF($D1005="","",N($J1005)+$L1005) | N1005: =IF($D1005="","",IFERROR(N($J1005)/$I1005,0)) | Q1005: =IF($A1005="","",DATE(YEAR($A1005),MONTH($A1005),1)) | R1005: =IF(OR($A1005="",$D1005=""),"",IF(COUNTIFS($D$6:$D$1005,$D1005,$A$6:$A$1005,">"&$A1005)=0,1,0))

Sheet RECETAS
A1: RECETAS (FICHAS DE COSTO POR INGREDIENTE)
A2: Una línea por ingrediente. Cantidad NETA usada por porción (o por lote si en PRODUCTOS indicó más porciones). Incluya empaque (vaso, tapa, cuchara, servilleta). La nómina fija NO va aquí.
A5: Código producto | B5: Producto | C5: Código insumo | D5: Insumo | E5: Unidad | F5: Cantidad neta por receta | G5: Costo real por unidad | H5: Costo de la línea (receta) | I5: Porciones de la receta | J5: Costo por porción | K5: Unidades vendidas del producto | L5: Consumo bruto de inventario | M5: N° línea | N5: Clave
A6: P001 | B6: =IF($A6="","",IFERROR(INDEX(PRODUCTOS!$B$6:$B$105,MATCH($A6,PRODUCTOS!$A$6:$A$105,0)),"¿Código?")) -> Fresas con crema Pequeño (8 oz) | C6: I001 | D6: =IF($C6="","",IFERROR(INDEX(INSUMOS!$B$6:$B$205,MATCH($C6,INSUMOS!$A$6:$A$205,0)),"¿Código?")) -> Fresas frescas | E6: =IF($C6="","",IFERROR(INDEX(INSUMOS!$D$6:$D$205,MATCH($C6,INSUMOS!$A$6:$A$205,0)),"")) -> g | F6: 90 | G6: =IF(OR($A6="",$C6=""),"",IFERROR(INDEX(INSUMOS!$P$6:$P$205,MATCH($C6,INSUMOS!$A$6:$A$205,0)),0)) -> 3.2941176 | H6: =IF(OR($A6="",$C6=""),"",N($F6)*$G6) -> 296.47059 | I6: =IF(OR($A6="",$C6=""),"",IFERROR(MAX(1,INDEX(PRODUCTOS!$G$6:$G$105,MATCH($A6,PRODUCTOS!$A$6:$A$105,0))),1)) -> 1 | J6: =IF(OR($A6="",$C6=""),"",$H6/$I6) -> 296.47059 | K6: =IF(OR($A6="",$C6=""),"",SUMIFS(VENTAS!$E$6:$E$2005,VENTAS!$C$6:$C$2005,$A6)) -> 27 | L6: =IF(OR($A6="",$C6=""),"",IFERROR(N($F6)/INDEX(INSUMOS!$I$6:$I$205,MATCH($C6,INSUMOS!$A$6:$A$205,0)),N($F6))/$I6*$K6) -> 2858.8235 | M6: =IF($A6="","",COUNTIF($A$6:$A6,$A6)) -> 1 | N6: =IF($A6="","",$A6&"|"&$M6) -> P001|1
A7: P001 | B7: =IF($A7="","",IFERROR(INDEX(PRODUCTOS!$B$6:$B$105,MATCH($A7,PRODUCTOS!$A$6:$A$105,0)),"¿Código?")) -> Fresas con crema Pequeño (8 oz) | C7: I004 | D7: =IF($C7="","",IFERROR(INDEX(INSUMOS!$B$6:$B$205,MATCH($C7,INSUMOS!$A$6:$A$205,0)),"¿Código?")) -> Crema dulce | E7: =IF($C7="","",IFERROR(INDEX(INSUMOS!$D$6:$D$205,MATCH($C7,INSUMOS!$A$6:$A$205,0)),"")) -> ml | F7: 45 | G7: =IF(OR($A7="",$C7=""),"",IFERROR(INDEX(INSUMOS!$P$6:$P$205,MATCH($C7,INSUMOS!$A$6:$A$205,0)),0)) -> 2.55 | H7: =IF(OR($A7="",$C7=""),"",N($F7)*$G7) -> 114.75 | I7: =IF(OR($A7="",$C7=""),"",IFERROR(MAX(1,INDEX(PRODUCTOS!$G$6:$G$105,MATCH($A7,PRODUCTOS!$A$6:$A$105,0))),1)) -> 1 | J7: =IF(OR($A7="",$C7=""),"",$H7/$I7) -> 114.75 | K7: =IF(OR($A7="",$C7=""),"",SUMIFS(VENTAS!$E$6:$E$2005,VENTAS!$C$6:$C$2005,$A7)) -> 27 | L7: =IF(OR($A7="",$C7=""),"",IFERROR(N($F7)/INDEX(INSUMOS!$I$6:$I$205,MATCH($C7,INSUMOS!$A$6:$A$205,0)),N($F7))/$I7*$K7) -> 1215 | M7: =IF($A7="","",COUNTIF($A$6:$A7,$A7)) -> 2 | N7: =IF($A7="","",$A7&"|"&$M7) -> P001|2
A8: P001 | B8: =IF($A8="","",IFERROR(INDEX(PRODUCTOS!$B$6:$B$105,MATCH($A8,PRODUCTOS!$A$6:$A$105,0)),"¿Código?")) -> Fresas con crema Pequeño (8 oz) | C8: I005 | D8: =IF($C8="","",IFERROR(INDEX(INSUMOS!$B$6:$B$205,MATCH($C8,INSUMOS!$A$6:$A$205,0)),"¿Código?")) -> Leche condensada | E8: =IF($C8="","",IFERROR(INDEX(INSUMOS!$D$6:$D$205,MATCH($C8,INSUMOS!$A$6:$A$205,0)),"")) -> g | F8: 20 | G8: =IF(OR($A8="",$C8=""),"",IFERROR(INDEX(INSUMOS!$P$6:$P$205,MATCH($C8,INSUMOS!$A$6:$A$205,0)),0)) -> 3.2459944 | H8: =IF(OR($A8="",$C8=""),"",N($F8)*$G8) -> 64.919889 | I8: =IF(OR($A8="",$C8=""),"",IFERROR(MAX(1,INDEX(PRODUCTOS!$G$6:$G$105,MATCH($A8,PRODUCTOS!$A$6:$A$105,0))),1)) -> 1 | J8: =IF(OR($A8="",$C8=""),"",$H8/$I8) -> 64.919889 | K8: =IF(OR($A8="",$C8=""),"",SUMIFS(VENTAS!$E$6:$E$2005,VENTAS!$C$6:$C$2005,$A8)) -> 27 | L8: =IF(OR($A8="",$C8=""),"",IFERROR(N($F8)/INDEX(INSUMOS!$I$6:$I$205,MATCH($C8,INSUMOS!$A$6:$A$205,0)),N($F8))/$I8*$K8) -> 556.70103 | M8: =IF($A8="","",COUNTIF($A$6:$A8,$A8)) -> 3 | N8: =IF($A8="","",$A8&"|"&$M8) -> P001|3
A9: P001 | B9: =IF($A9="","",IFERROR(INDEX(PRODUCTOS!$B$6:$B$105,MATCH($A9,PRODUCTOS!$A$6:$A$105,0)),"¿Código?")) -> Fresas con crema Pequeño (8 oz) | C9: I006 | D9: =IF($C9="","",IFERROR(INDEX(INSUMOS!$B$6:$B$205,MATCH($C9,INSUMOS!$A$6:$A$205,0)),"¿Código?")) -> Esencia de vainilla | E9: =IF($C9="","",IFERROR(INDEX(INSUMOS!$D$6:$D$205,MATCH($C9,INSUMOS!$A$6:$A$205,0)),"")) -> ml | F9: 1 | G9: =IF(OR($A9="",$C9=""),"",IFERROR(INDEX(INSUMOS!$P$6:$P$205,MATCH($C9,INSUMOS!$A$6:$A$205,0)),0)) -> 7.2 | H9: =IF(OR($A9="",$C9=""),"",N($F9)*$G9) -> 7.2 | I9: =IF(OR($A9="",$C9=""),"",IFERROR(MAX(1,INDEX(PRODUCTOS!$G$6:$G$105,MATCH($A9,PRODUCTOS!$A$6:$A$105,0))),1)) -> 1 | J9: =IF(OR($A9="",$C9=""),"",$H9/$I9) -> 7.2 | K9: =IF(OR($A9="",$C9=""),"",SUMIFS(VENTAS!$E$6:$E$2005,VENTAS!$C$6:$C$2005,$A9)) -> 27 | L9: =IF(OR($A9="",$C9=""),"",IFERROR(N($F9)/INDEX(INSUMOS!$I$6:$I$205,MATCH($C9,INSUMOS!$A$6:$A$205,0)),N($F9))/$I9*$K9) -> 27 | M9: =IF($A9="","",COUNTIF($A$6:$A9,$A9)) -> 4 | N9: =IF($A9="","",$A9&"|"&$M9) -> P001|4
A10: P001 | B10: =IF($A10="","",IFERROR(INDEX(PRODUCTOS!$B$6:$B$105,MATCH($A10,PRODUCTOS!$A$6:$A$105,0)),"¿Código?")) -> Fresas con crema Pequeño (8 oz) | C10: I008 | D10: =IF($C10="","",IFERROR(INDEX(INSUMOS!$B$6:$B$205,MATCH($C10,INSUMOS!$A$6:$A$205,0)),"¿Código?")) -> Galleta Oreo triturada | E10: =IF($C10="","",IFERROR(INDEX(INSUMOS!$D$6:$D$205,MATCH($C10,INSUMOS!$A$6:$A$205,0)),"")) -> g | F10: 15 | G10: =IF(OR($A10="",$C10=""),"",IFERROR(INDEX(INSUMOS!$P$6:$P$205,MATCH($C10,INSUMOS!$A$6:$A$205,0)),0)) -> 6.3352827 | H10: =IF(OR($A10="",$C10=""),"",N($F10)*$G10) -> 95.02924 | I10: =IF(OR($A10="",$C10=""),"",IFERROR(MAX(1,INDEX(PRODUCTOS!$G$6:$G$105,MATCH($A10,PRODUCTOS!$A$6:$A$105,0))),1)) -> 1 | J10: =IF(OR($A10="",$C10=""),"",$H10/$I10) -> 95.02924 | K10: =IF(OR($A10="",$C10=""),"",SUMIFS(VENTAS!$E$6:$E$2005,VENTAS!$C$6:$C$2005,$A10)) -> 27 | L10: =IF(OR($A10="",$C10=""),"",IFERROR(N($F10)/INDEX(INSUMOS!$I$6:$I$205,MATCH($C10,INSUMOS!$A$6:$A$205,0)),N($F10))/$I10*$K10) -> 426.31579 | M10: =IF($A10="","",COUNTIF($A$6:$A10,$A10)) -> 5 | N10: =IF($A10="","",$A10&"|"&$M10) -> P001|5
A11: P001 | B11: =IF($A11="","",IFERROR(INDEX(PRODUCTOS!$B$6:$B$105,MATCH($A11,PRODUCTOS!$A$6:$A$105,0)),"¿Código?")) -> Fresas con crema Pequeño (8 oz) | C11: I020 | D11: =IF($C11="","",IFERROR(INDEX(INSUMOS!$B$6:$B$205,MATCH($C11,INSUMOS!$A$6:$A$205,0)),"¿Código?")) -> Vaso 8 oz con tapa | E11: =IF($C11="","",IFERROR(INDEX(INSUMOS!$D$6:$D$205,MATCH($C11,INSUMOS!$A$6:$A$205,0)),"")) -> u | F11: 1 | G11: =IF(OR($A11="",$C11=""),"",IFERROR(INDEX(INSUMOS!$P$6:$P$205,MATCH($C11,INSUMOS!$A$6:$A$205,0)),0)) -> 75 | H11: =IF(OR($A11="",$C11=""),"",N($F11)*$G11) -> 75 | I11: =IF(OR($A11="",$C11=""),"",IFERROR(MAX(1,INDEX(PRODUCTOS!$G$6:$G$105,MATCH($A11,PRODUCTOS!$A$6:$A$105,0))),1)) -> 1 | J11: =IF(OR($A11="",$C11=""),"",$H11/$I11) -> 75 | K11: =IF(OR($A11="",$C11=""),"",SUMIFS(VENTAS!$E$6:$E$2005,VENTAS!$C$6:$C$2005,$A11)) -> 27 | L11: =IF(OR($A11="",$C11=""),"",IFERROR(N($F11)/INDEX(INSUMOS!$I$6:$I$205,MATCH($C11,INSUMOS!$A$6:$A$205,0)),N($F11))/$I11*$K11) -> 27 | M11: =IF($A11="","",COUNTIF($A$6:$A11,$A11)) -> 6 | N11: =IF($A11="","",$A11&"|"&$M11) -> P001|6
A12: P001 | B12: =IF($A12="","",IFERROR(INDEX(PRODUCTOS!$B$6:$B$105,MATCH($A12,PRODUCTOS!$A$6:$A$105,0)),"¿Código?")) -> Fresas con crema Pequeño (8 oz) | C12: I024 | D12: =IF($C12="","",IFERROR(INDEX(INSUMOS!$B$6:$B$205,MATCH($C12,INSUMOS!$A$6:$A$205,0)),"¿Código?")) -> Cuchara plástica | E12: =IF($C12="","",IFERROR(INDEX(INSUMOS!$D$6:$D$205,MATCH($C12,INSUMOS!$A$6:$A$205,0)),"")) -> u | F12: 1 | G12: =IF(OR($A12="",$C12=""),"",IFERROR(INDEX(INSUMOS!$P$6:$P$205,MATCH($C12,INSUMOS!$A$6:$A$205,0)),0)) -> 15 | H12: =IF(OR($A12="",$C12=""),"",N($F12)*$G12) -> 15 | I12: =IF(OR($A12="",$C12=""),"",IFERROR(MAX(1,INDEX(PRODUCTOS!$G$6:$G$105,MATCH($A12,PRODUCTOS!$A$6:$A$105,0))),1)) -> 1 | J12: =IF(OR($A12="",$C12=""),"",$H12/$I12) -> 15 | K12: =IF(OR($A12="",$C12=""),"",SUMIFS(VENTAS!$E$6:$E$2005,VENTAS!$C$6:$C$2005,$A12)) -> 27 | L12: =IF(OR($A12="",$C12=""),"",IFERROR(N($F12)/INDEX(INSUMOS!$I$6:$I$205,MATCH($C12,INSUMOS!$A$6:$A$205,0)),N($F12))/$I12*$K12) -> 27 | M12: =IF($A12="","",COUNTIF($A$6:$A12,$A12)) -> 7 | N12: =IF($A12="","",$A12&"|"&$M12) -> P001|7
A13: P001 | B13: =IF($A13="","",IFERROR(INDEX(PRODUCTOS!$B$6:$B$105,MATCH($A13,PRODUCTOS!$A$6:$A$105,0)),"¿Código?")) -> Fresas con crema Pequeño (8 oz) | C13: I025 | D13: =IF($C13="","",IFERROR(INDEX(INSUMOS!$B$6:$B$205,MATCH($C13,INSUMOS!$A$6:$A$205,0)),"¿Código?")) -> Servilleta | E13: =IF($C13="","",IFERROR(INDEX(INSUMOS!$D$6:$D$205,MATCH($C13,INSUMOS!$A$6:$A$205,0)),"")) -> u | F13: 1 | G13: =IF(OR($A13="",$C13=""),"",IFERROR(INDEX(INSUMOS!$P$6:$P$205,MATCH($C13,INSUMOS!$A$6:$A$205,0)),0)) -> 5 | H13: =IF(OR($A13="",$C13=""),"",N($F13)*$G13) -> 5 | I13: =IF(OR($A13="",$C13=""),"",IFERROR(MAX(1,INDEX(PRODUCTOS!$G$6:$G$105,MATCH($A13,PRODUCTOS!$A$6:$A$105,0))),1)) -> 1 | J13: =IF(OR($A13="",$C13=""),"",$H13/$I13) -> 5 | K13: =IF(OR($A13="",$C13=""),"",SUMIFS(VENTAS!$E$6:$E$2005,VENTAS!$C$6:$C$2005,$A13)) -> 27 | L13: =IF(OR($A13="",$C13=""),"",IFERROR(N($F13)/INDEX(INSUMOS!$I$6:$I$205,MATCH($C13,INSUMOS!$A$6:$A$205,0)),N($F13))/$I13*$K13) -> 27 | M13: =IF($A13="","",COUNTIF($A$6:$A13,$A13)) -> 8 | N13: =IF($A13="","",$A13&"|"&$M13) -> P001|8
A14: P002 | B14: =IF($A14="","",IFERROR(INDEX(PRODUCTOS!$B$6:$B$105,MATCH($A14,PRODUCTOS!$A$6:$A$105,0)),"¿Código?")) -> Fresas con crema Mediano (12 oz) | C14: I001 | D14: =IF($C14="","",IFERROR(INDEX(INSUMOS!$B$6:$B$205,MATCH($C14,INSUMOS!$A$6:$A$205,0)),"¿Código?")) -> Fresas frescas | E14: =IF($C14="","",IFERROR(INDEX(INSUMOS!$D$6:$D$205,MATCH($C14,INSUMOS!$A$6:$A$205,0)),"")) -> g | F14: 140 | G14: =IF(OR($A14="",$C14=""),"",IFERROR(INDEX(INSUMOS!$P$6:$P$205,MATCH($C14,INSUMOS!$A$6:$A$205,0)),0)) -> 3.2941176 | H14: =IF(OR($A14="",$C14=""),"",N($F14)*$G14) -> 461.17647 | I14: =IF(OR($A14="",$C14=""),"",IFERROR(MAX(1,INDEX(PRODUCTOS!$G$6:$G$105,MATCH($A14,PRODUCTOS!$A$6:$A$105,0))),1)) -> 1 | J14: =IF(OR($A14="",$C14=""),"",$H14/$I14) -> 461.17647 | K14: =IF(OR($A14="",$C14=""),"",SUMIFS(VENTAS!$E$6:$E$2005,VENTAS!$C$6:$C$2005,$A14)) -> 40 | L14: =IF(OR($A14="",$C14=""),"",IFERROR(N($F14)/INDEX(INSUMOS!$I$6:$I$205,MATCH($C14,INSUMOS!$A$6:$A$205,0)),N($F14))/$I14*$K14) -> 6588.2353 | M14: =IF($A14="","",COUNTIF($A$6:$A14,$A14)) -> 1 | N14: =IF($A14="","",$A14&"|"&$M14) -> P002|1
A15: P002 | B15: =IF($A15="","",IFERROR(INDEX(PRODUCTOS!$B$6:$B$105,MATCH($A15,PRODUCTOS!$A$6:$A$105,0)),"¿Código?")) -> Fresas con crema Mediano (12 oz) | C15: I004 | D15: =IF($C15="","",IFERROR(INDEX(INSUMOS!$B$6:$B$205,MATCH($C15,INSUMOS!$A$6:$A$205,0)),"¿Código?")) -> Crema dulce | E15: =IF($C15="","",IFERROR(INDEX(INSUMOS!$D$6:$D$205,MATCH($C15,INSUMOS!$A$6:$A$205,0)),"")) -> ml | F15: 65 | G15: =IF(OR($A15="",$C15=""),"",IFERROR(INDEX(INSUMOS!$P$6:$P$205,MATCH($C15,INSUMOS!$A$6:$A$205,0)),0)) -> 2.55 | H15: =IF(OR($A15="",$C15=""),"",N($F15)*$G15) -> 165.75 | I15: =IF(OR($A15="",$C15=""),"",IFERROR(MAX(1,INDEX(PRODUCTOS!$G$6:$G$105,MATCH($A15,PRODUCTOS!$A$6:$A$105,0))),1)) -> 1 | J15: =IF(OR($A15="",$C15=""),"",$H15/$I15) -> 165.75 | K15: =IF(OR($A15="",$C15=""),"",SUMIFS(VENTAS!$E$6:$E$2005,VENTAS!$C$6:$C$2005,$A15)) -> 40 | L15: =IF(OR($A15="",$C15=""),"",IFERROR(N($F15)/INDEX(INSUMOS!$I$6:$I$205,MATCH($C15,INSUMOS!$A$6:$A$205,0)),N($F15))/$I15*$K15) -> 2600 | M15: =IF($A15="","",COUNTIF($A$6:$A15,$A15)) -> 2 | N15: =IF($A15="","",$A15&"|"&$M15) -> P002|2
A16: P002 | B16: =IF($A16="","",IFERROR(INDEX(PRODUCTOS!$B$6:$B$105,MATCH($A16,PRODUCTOS!$A$6:$A$105,0)),"¿Código?")) -> Fresas con crema Mediano (12 oz) | C16: I005 | D16: =IF($C16="","",IFERROR(INDEX(INSUMOS!$B$6:$B$205,MATCH($C16,INSUMOS!$A$6:$A$205,0)),"¿Código?")) -> Leche condensada | E16: =IF($C16="","",IFERROR(INDEX(INSUMOS!$D$6:$D$205,MATCH($C16,INSUMOS!$A$6:$A$205,0)),"")) -> g | F16: 30 | G16: =IF(OR($A16="",$C16=""),"",IFERROR(INDEX(INSUMOS!$P$6:$P$205,MATCH($C16,INSUMOS!$A$6:$A$205,0)),0)) -> 3.2459944 | H16: =IF(OR($A16="",$C16=""),"",N($F16)*$G16) -> 97.379833 | I16: =IF(OR($A16="",$C16=""),"",IFERROR(MAX(1,INDEX(PRODUCTOS!$G$6:$G$105,MATCH($A16,PRODUCTOS!$A$6:$A$105,0))),1)) -> 1 | J16: =IF(OR($A16="",$C16=""),"",$H16/$I16) -> 97.379833 | K16: =IF(OR($A16="",$C16=""),"",SUMIFS(VENTAS!$E$6:$E$2005,VENTAS!$C$6:$C$2005,$A16)) -> 40 | L16: =IF(OR($A16="",$C16=""),"",IFERROR(N($F16)/INDEX(INSUMOS!$I$6:$I$205,MATCH($C16,INSUMOS!$A$6:$A$205,0)),N($F16))/$I16*$K16) -> 1237.1134 | M16: =IF($A16="","",COUNTIF($A$6:$A16,$A16)) -> 3 | N16: =IF($A16="","",$A16&"|"&$M16) -> P002|3
A17: P002 | B17: =IF($A17="","",IFERROR(INDEX(PRODUCTOS!$B$6:$B$105,MATCH($A17,PRODUCTOS!$A$6:$A$105,0)),"¿Código?")) -> Fresas con crema Mediano (12 oz) | C17: I006 | D17: =IF($C17="","",IFERROR(INDEX(INSUMOS!$B$6:$B$205,MATCH($C17,INSUMOS!$A$6:$A$205,0)),"¿Código?")) -> Esencia de vainilla | E17: =IF($C17="","",IFERROR(INDEX(INSUMOS!$D$6:$D$205,MATCH($C17,INSUMOS!$A$6:$A$205,0)),"")) -> ml | F17: 1.5 | G17: =IF(OR($A17="",$C17=""),"",IFERROR(INDEX(INSUMOS!$P$6:$P$205,MATCH($C17,INSUMOS!$A$6:$A$205,0)),0)) -> 7.2 | H17: =IF(OR($A17="",$C17=""),"",N($F17)*$G17) -> 10.8 | I17: =IF(OR($A17="",$C17=""),"",IFERROR(MAX(1,INDEX(PRODUCTOS!$G$6:$G$105,MATCH($A17,PRODUCTOS!$A$6:$A$105,0))),1)) -> 1 | J17: =IF(OR($A17="",$C17=""),"",$H17/$I17) -> 10.8 | K17: =IF(OR($A17="",$C17=""),"",SUMIFS(VENTAS!$E$6:$E$2005,VENTAS!$C$6:$C$2005,$A17)) -> 40 | L17: =IF(OR($A17="",$C17=""),"",IFERROR(N($F17)/INDEX(INSUMOS!$I$6:$I$205,MATCH($C17,INSUMOS!$A$6:$A$205,0)),N($F17))/$I17*$K17) -> 60 | M17: =IF($A17="","",COUNTIF($A$6:$A17,$A17)) -> 4 | N17: =IF($A17="","",$A17&"|"&$M17) -> P002|4
... A61: P009 | B61: =IF($A61="","",IFERROR(INDEX(PRODUCTOS!$B$6:$B$105,MATCH($A61,PRODUCTOS!$A$6:$A$105,0)),"¿Código?")) -> Brownie de la casa (lote de 20) | C61: I025 | D61: =IF($C61="","",IFERROR(INDEX(INSUMOS!$B$6:$B$205,MATCH($C61,INSUMOS!$A$6:$A$205,0)),"¿Código?")) -> Servilleta | E61: =IF($C61="","",IFERROR(INDEX(INSUMOS!$D$6:$D$205,MATCH($C61,INSUMOS!$A$6:$A$205,0)),"")) -> u | F61: 20 | G61: =IF(OR($A61="",$C61=""),"",IFERROR(INDEX(INSUMOS!$P$6:$P$205,MATCH($C61,INSUMOS!$A$6:$A$205,0)),0)) -> 5 | H61: =IF(OR($A61="",$C61=""),"",N($F61)*$G61) -> 100 | I61: =IF(OR($A61="",$C61=""),"",IFERROR(MAX(1,INDEX(PRODUCTOS!$G$6:$G$105,MATCH($A61,PRODUCTOS!$A$6:$A$105,0))),1)) -> 20 | J61: =IF(OR($A61="",$C61=""),"",$H61/$I61) -> 5 | K61: =IF(OR($A61="",$C61=""),"",SUMIFS(VENTAS!$E$6:$E$2005,VENTAS!$C$6:$C$2005,$A61)) -> 6 | L61: =IF(OR($A61="",$C61=""),"",IFERROR(N($F61)/INDEX(INSUMOS!$I$6:$I$205,MATCH($C61,INSUMOS!$A$6:$A$205,0)),N($F61))/$I61*$K61) -> 6 | M61: =IF($A61="","",COUNTIF($A$6:$A61,$A61)) -> 7 | N61: =IF($A61="","",$A61&"|"&$M61) -> P009|7
B62: =IF($A62="","",IFERROR(INDEX(PRODUCTOS!$B$6:$B$105,MATCH($A62,PRODUCTOS!$A$6:$A$105,0)),"¿Código?")) | D62: =IF($C62="","",IFERROR(INDEX(INSUMOS!$B$6:$B$205,MATCH($C62,INSUMOS!$A$6:$A$205,0)),"¿Código?")) | E62: =IF($C62="","",IFERROR(INDEX(INSUMOS!$D$6:$D$205,MATCH($C62,INSUMOS!$A$6:$A$205,0)),"")) | G62: =IF(OR($A62="",$C62=""),"",IFERROR(INDEX(INSUMOS!$P$6:$P$205,MATCH($C62,INSUMOS!$A$6:$A$205,0)),0)) | H62: =IF(OR($A62="",$C62=""),"",N($F62)*$G62) | I62: =IF(OR($A62="",$C62=""),"",IFERROR(MAX(1,INDEX(PRODUCTOS!$G$6:$G$105,MATCH($A62,PRODUCTOS!$A$6:$A$105,0))),1)) | J62: =IF(OR($A62="",$C62=""),"",$H62/$I62) | K62: =IF(OR($A62="",$C62=""),"",SUMIFS(VENTAS!$E$6:$E$2005,VENTAS!$C$6:$C$2005,$A62)) | L62: =IF(OR($A62="",$C62=""),"",IFERROR(N($F62)/INDEX(INSUMOS!$I$6:$I$205,MATCH($C62,INSUMOS!$A$6:$A$205,0)),N($F62))/$I62*$K62) | M62: =IF($A62="","",COUNTIF($A$6:$A62,$A62)) | N62: =IF($A62="","",$A62&"|"&$M62)
B63: =IF($A63="","",IFERROR(INDEX(PRODUCTOS!$B$6:$B$105,MATCH($A63,PRODUCTOS!$A$6:$A$105,0)),"¿Código?")) | D63: =IF($C63="","",IFERROR(INDEX(INSUMOS!$B$6:$B$205,MATCH($C63,INSUMOS!$A$6:$A$205,0)),"¿Código?")) | E63: =IF($C63="","",IFERROR(INDEX(INSUMOS!$D$6:$D$205,MATCH($C63,INSUMOS!$A$6:$A$205,0)),"")) | G63: =IF(OR($A63="",$C63=""),"",IFERROR(INDEX(INSUMOS!$P$6:$P$205,MATCH($C63,INSUMOS!$A$6:$A$205,0)),0)) | H63: =IF(OR($A63="",$C63=""),"",N($F63)*$G63) | I63: =IF(OR($A63="",$C63=""),"",IFERROR(MAX(1,INDEX(PRODUCTOS!$G$6:$G$105,MATCH($A63,PRODUCTOS!$A$6:$A$105,0))),1)) | J63: =IF(OR($A63="",$C63=""),"",$H63/$I63) | K63: =IF(OR($A63="",$C63=""),"",SUMIFS(VENTAS!$E$6:$E$2005,VENTAS!$C$6:$C$2005,$A63)) | L63: =IF(OR($A63="",$C63=""),"",IFERROR(N($F63)/INDEX(INSUMOS!$I$6:$I$205,MATCH($C63,INSUMOS!$A$6:$A$205,0)),N($F63))/$I63*$K63) | M63: =IF($A63="","",COUNTIF($A$6:$A63,$A63)) | N63: =IF($A63="","",$A63&"|"&$M63)
B64: =IF($A64="","",IFERROR(INDEX(PRODUCTOS!$B$6:$B$105,MATCH($A64,PRODUCTOS!$A$6:$A$105,0)),"¿Código?")) | D64: =IF($C64="","",IFERROR(INDEX(INSUMOS!$B$6:$B$205,MATCH($C64,INSUMOS!$A$6:$A$205,0)),"¿Código?")) | E64: =IF($C64="","",IFERROR(INDEX(INSUMOS!$D$6:$D$205,MATCH($C64,INSUMOS!$A$6:$A$205,0)),"")) | G64: =IF(OR($A64="",$C64=""),"",IFERROR(INDEX(INSUMOS!$P$6:$P$205,MATCH($C64,INSUMOS!$A$6:$A$205,0)),0)) | H64: =IF(OR($A64="",$C64=""),"",N($F64)*$G64) | I64: =IF(OR($A64="",$C64=""),"",IFERROR(MAX(1,INDEX(PRODUCTOS!$G$6:$G$105,MATCH($A64,PRODUCTOS!$A$6:$A$105,0))),1)) | J64: =IF(OR($A64="",$C64=""),"",$H64/$I64) | K64: =IF(OR($A64="",$C64=""),"",SUMIFS(VENTAS!$E$6:$E$2005,VENTAS!$C$6:$C$2005,$A64)) | L64: =IF(OR($A64="",$C64=""),"",IFERROR(N($F64)/INDEX(INSUMOS!$I$6:$I$205,MATCH($C64,INSUMOS!$A$6:$A$205,0)),N($F64))/$I64*$K64) | M64: =IF($A64="","",COUNTIF($A$6:$A64,$A64)) | N64: =IF($A64="","",$A64&"|"&$M64)
B65: =IF($A65="","",IFERROR(INDEX(PRODUCTOS!$B$6:$B$105,MATCH($A65,PRODUCTOS!$A$6:$A$105,0)),"¿Código?")) | D65: =IF($C65="","",IFERROR(INDEX(INSUMOS!$B$6:$B$205,MATCH($C65,INSUMOS!$A$6:$A$205,0)),"¿Código?")) | E65: =IF($C65="","",IFERROR(INDEX(INSUMOS!$D$6:$D$205,MATCH($C65,INSUMOS!$A$6:$A$205,0)),"")) | G65: =IF(OR($A65="",$C65=""),"",IFERROR(INDEX(INSUMOS!$P$6:$P$205,MATCH($C65,INSUMOS!$A$6:$A$205,0)),0)) | H65: =IF(OR($A65="",$C65=""),"",N($F65)*$G65) | I65: =IF(OR($A65="",$C65=""),"",IFERROR(MAX(1,INDEX(PRODUCTOS!$G$6:$G$105,MATCH($A65,PRODUCTOS!$A$6:$A$105,0))),1)) | J65: =IF(OR($A65="",$C65=""),"",$H65/$I65) | K65: =IF(OR($A65="",$C65=""),"",SUMIFS(VENTAS!$E$6:$E$2005,VENTAS!$C$6:$C$2005,$A65)) | L65: =IF(OR($A65="",$C65=""),"",IFERROR(N($F65)/INDEX(INSUMOS!$I$6:$I$205,MATCH($C65,INSUMOS!$A$6:$A$205,0)),N($F65))/$I65*$K65) | M65: =IF($A65="","",COUNTIF($A$6:$A65,$A65)) | N65: =IF($A65="","",$A65&"|"&$M65)
B66: =IF($A66="","",IFERROR(INDEX(PRODUCTOS!$B$6:$B$105,MATCH($A66,PRODUCTOS!$A$6:$A$105,0)),"¿Código?")) | D66: =IF($C66="","",IFERROR(INDEX(INSUMOS!$B$6:$B$205,MATCH($C66,INSUMOS!$A$6:$A$205,0)),"¿Código?")) | E66: =IF($C66="","",IFERROR(INDEX(INSUMOS!$D$6:$D$205,MATCH($C66,INSUMOS!$A$6:$A$205,0)),"")) | G66: =IF(OR($A66="",$C66=""),"",IFERROR(INDEX(INSUMOS!$P$6:$P$205,MATCH($C66,INSUMOS!$A$6:$A$205,0)),0)) | H66: =IF(OR($A66="",$C66=""),"",N($F66)*$G66) | I66: =IF(OR($A66="",$C66=""),"",IFERROR(MAX(1,INDEX(PRODUCTOS!$G$6:$G$105,MATCH($A66,PRODUCTOS!$A$6:$A$105,0))),1)) | J66: =IF(OR($A66="",$C66=""),"",$H66/$I66) | K66: =IF(OR($A66="",$C66=""),"",SUMIFS(VENTAS!$E$6:$E$2005,VENTAS!$C$6:$C$2005,$A66)) | L66: =IF(OR($A66="",$C66=""),"",IFERROR(N($F66)/INDEX(INSUMOS!$I$6:$I$205,MATCH($C66,INSUMOS!$A$6:$A$205,0)),N($F66))/$I66*$K66) | M66: =IF($A66="","",COUNTIF($A$6:$A66,$A66)) | N66: =IF($A66="","",$A66&"|"&$M66)
B67: =IF($A67="","",IFERROR(INDEX(PRODUCTOS!$B$6:$B$105,MATCH($A67,PRODUCTOS!$A$6:$A$105,0)),"¿Código?")) | D67: =IF($C67="","",IFERROR(INDEX(INSUMOS!$B$6:$B$205,MATCH($C67,INSUMOS!$A$6:$A$205,0)),"¿Código?")) | E67: =IF($C67="","",IFERROR(INDEX(INSUMOS!$D$6:$D$205,MATCH($C67,INSUMOS!$A$6:$A$205,0)),"")) | G67: =IF(OR($A67="",$C67=""),"",IFERROR(INDEX(INSUMOS!$P$6:$P$205,MATCH($C67,INSUMOS!$A$6:$A$205,0)),0)) | H67: =IF(OR($A67="",$C67=""),"",N($F67)*$G67) | I67: =IF(OR($A67="",$C67=""),"",IFERROR(MAX(1,INDEX(PRODUCTOS!$G$6:$G$105,MATCH($A67,PRODUCTOS!$A$6:$A$105,0))),1)) | J67: =IF(OR($A67="",$C67=""),"",$H67/$I67) | K67: =IF(OR($A67="",$C67=""),"",SUMIFS(VENTAS!$E$6:$E$2005,VENTAS!$C$6:$C$2005,$A67)) | L67: =IF(OR($A67="",$C67=""),"",IFERROR(N($F67)/INDEX(INSUMOS!$I$6:$I$205,MATCH($C67,INSUMOS!$A$6:$A$205,0)),N($F67))/$I67*$K67) | M67: =IF($A67="","",COUNTIF($A$6:$A67,$A67)) | N67: =IF($A67="","",$A67&"|"&$M67)
B68: =IF($A68="","",IFERROR(INDEX(PRODUCTOS!$B$6:$B$105,MATCH($A68,PRODUCTOS!$A$6:$A$105,0)),"¿Código?")) | D68: =IF($C68="","",IFERROR(INDEX(INSUMOS!$B$6:$B$205,MATCH($C68,INSUMOS!$A$6:$A$205,0)),"¿Código?")) | E68: =IF($C68="","",IFERROR(INDEX(INSUMOS!$D$6:$D$205,MATCH($C68,INSUMOS!$A$6:$A$205,0)),"")) | G68: =IF(OR($A68="",$C68=""),"",IFERROR(INDEX(INSUMOS!$P$6:$P$205,MATCH($C68,INSUMOS!$A$6:$A$205,0)),0)) | H68: =IF(OR($A68="",$C68=""),"",N($F68)*$G68) | I68: =IF(OR($A68="",$C68=""),"",IFERROR(MAX(1,INDEX(PRODUCTOS!$G$6:$G$105,MATCH($A68,PRODUCTOS!$A$6:$A$105,0))),1)) | J68: =IF(OR($A68="",$C68=""),"",$H68/$I68) | K68: =IF(OR($A68="",$C68=""),"",SUMIFS(VENTAS!$E$6:$E$2005,VENTAS!$C$6:$C$2005,$A68)) | L68: =IF(OR($A68="",$C68=""),"",IFERROR(N($F68)/INDEX(INSUMOS!$I$6:$I$205,MATCH($C68,INSUMOS!$A$6:$A$205,0)),N($F68))/$I68*$K68) | M68: =IF($A68="","",COUNTIF($A$6:$A68,$A68)) | N68: =IF($A68="","",$A68&"|"&$M68)
B69: =IF($A69="","",IFERROR(INDEX(PRODUCTOS!$B$6:$B$105,MATCH($A69,PRODUCTOS!$A$6:$A$105,0)),"¿Código?")) | D69: =IF($C69="","",IFERROR(INDEX(INSUMOS!$B$6:$B$205,MATCH($C69,INSUMOS!$A$6:$A$205,0)),"¿Código?")) | E69: =IF($C69="","",IFERROR(INDEX(INSUMOS!$D$6:$D$205,MATCH($C69,INSUMOS!$A$6:$A$205,0)),"")) | G69: =IF(OR($A69="",$C69=""),"",IFERROR(INDEX(INSUMOS!$P$6:$P$205,MATCH($C69,INSUMOS!$A$6:$A$205,0)),0)) | H69: =IF(OR($A69="",$C69=""),"",N($F69)*$G69) | I69: =IF(OR($A69="",$C69=""),"",IFERROR(MAX(1,INDEX(PRODUCTOS!$G$6:$G$105,MATCH($A69,PRODUCTOS!$A$6:$A$105,0))),1)) | J69: =IF(OR($A69="",$C69=""),"",$H69/$I69) | K69: =IF(OR($A69="",$C69=""),"",SUMIFS(VENTAS!$E$6:$E$2005,VENTAS!$C$6:$C$2005,$A69)) | L69: =IF(OR($A69="",$C69=""),"",IFERROR(N($F69)/INDEX(INSUMOS!$I$6:$I$205,MATCH($C69,INSUMOS!$A$6:$A$205,0)),N($F69))/$I69*$K69) | M69: =IF($A69="","",COUNTIF($A$6:$A69,$A69)) | N69: =IF($A69="","",$A69&"|"&$M69)
B70: =IF($A70="","",IFERROR(INDEX(PRODUCTOS!$B$6:$B$105,MATCH($A70,PRODUCTOS!$A$6:$A$105,0)),"¿Código?")) | D70: =IF($C70="","",IFERROR(INDEX(INSUMOS!$B$6:$B$205,MATCH($C70,INSUMOS!$A$6:$A$205,0)),"¿Código?")) | E70: =IF($C70="","",IFERROR(INDEX(INSUMOS!$D$6:$D$205,MATCH($C70,INSUMOS!$A$6:$A$205,0)),"")) | G70: =IF(OR($A70="",$C70=""),"",IFERROR(INDEX(INSUMOS!$P$6:$P$205,MATCH($C70,INSUMOS!$A$6:$A$205,0)),0)) | H70: =IF(OR($A70="",$C70=""),"",N($F70)*$G70) | I70: =IF(OR($A70="",$C70=""),"",IFERROR(MAX(1,INDEX(PRODUCTOS!$G$6:$G$105,MATCH($A70,PRODUCTOS!$A$6:$A$105,0))),1)) | J70: =IF(OR($A70="",$C70=""),"",$H70/$I70) | K70: =IF(OR($A70="",$C70=""),"",SUMIFS(VENTAS!$E$6:$E$2005,VENTAS!$C$6:$C$2005,$A70)) | L70: =IF(OR($A70="",$C70=""),"",IFERROR(N($F70)/INDEX(INSUMOS!$I$6:$I$205,MATCH($C70,INSUMOS!$A$6:$A$205,0)),N($F70))/$I70*$K70) | M70: =IF($A70="","",COUNTIF($A$6:$A70,$A70)) | N70: =IF($A70="","",$A70&"|"&$M70)
B71: =IF($A71="","",IFERROR(INDEX(PRODUCTOS!$B$6:$B$105,MATCH($A71,PRODUCTOS!$A$6:$A$105,0)),"¿Código?")) | D71: =IF($C71="","",IFERROR(INDEX(INSUMOS!$B$6:$B$205,MATCH($C71,INSUMOS!$A$6:$A$205,0)),"¿Código?")) | E71: =IF($C71="","",IFERROR(INDEX(INSUMOS!$D$6:$D$205,MATCH($C71,INSUMOS!$A$6:$A$205,0)),"")) | G71: =IF(OR($A71="",$C71=""),"",IFERROR(INDEX(INSUMOS!$P$6:$P$205,MATCH($C71,INSUMOS!$A$6:$A$205,0)),0)) | H71: =IF(OR($A71="",$C71=""),"",N($F71)*$G71) | I71: =IF(OR($A71="",$C71=""),"",IFERROR(MAX(1,INDEX(PRODUCTOS!$G$6:$G$105,MATCH($A71,PRODUCTOS!$A$6:$A$105,0))),1)) | J71: =IF(OR($A71="",$C71=""),"",$H71/$I71) | K71: =IF(OR($A71="",$C71=""),"",SUMIFS(VENTAS!$E$6:$E$2005,VENTAS!$C$6:$C$2005,$A71)) | L71: =IF(OR($A71="",$C71=""),"",IFERROR(N($F71)/INDEX(INSUMOS!$I$6:$I$205,MATCH($C71,INSUMOS!$A$6:$A$205,0)),N($F71))/$I71*$K71) | M71: =IF($A71="","",COUNTIF($A$6:$A71,$A71)) | N71: =IF($A71="","",$A71&"|"&$M71)
B72: =IF($A72="","",IFERROR(INDEX(PRODUCTOS!$B$6:$B$105,MATCH($A72,PRODUCTOS!$A$6:$A$105,0)),"¿Código?")) | D72: =IF($C72="","",IFERROR(INDEX(INSUMOS!$B$6:$B$205,MATCH($C72,INSUMOS!$A$6:$A$205,0)),"¿Código?")) | E72: =IF($C72="","",IFERROR(INDEX(INSUMOS!$D$6:$D$205,MATCH($C72,INSUMOS!$A$6:$A$205,0)),"")) | G72: =IF(OR($A72="",$C72=""),"",IFERROR(INDEX(INSUMOS!$P$6:$P$205,MATCH($C72,INSUMOS!$A$6:$A$205,0)),0)) | H72: =IF(OR($A72="",$C72=""),"",N($F72)*$G72) | I72: =IF(OR($A72="",$C72=""),"",IFERROR(MAX(1,INDEX(PRODUCTOS!$G$6:$G$105,MATCH($A72,PRODUCTOS!$A$6:$A$105,0))),1)) | J72: =IF(OR($A72="",$C72=""),"",$H72/$I72) | K72: =IF(OR($A72="",$C72=""),"",SUMIFS(VENTAS!$E$6:$E$2005,VENTAS!$C$6:$C$2005,$A72)) | L72: =IF(OR($A72="",$C72=""),"",IFERROR(N($F72)/INDEX(INSUMOS!$I$6:$I$205,MATCH($C72,INSUMOS!$A$6:$A$205,0)),N($F72))/$I72*$K72) | M72: =IF($A72="","",COUNTIF($A$6:$A72,$A72)) | N72: =IF($A72="","",$A72&"|"&$M72)
B73: =IF($A73="","",IFERROR(INDEX(PRODUCTOS!$B$6:$B$105,MATCH($A73,PRODUCTOS!$A$6:$A$105,0)),"¿Código?")) | D73: =IF($C73="","",IFERROR(INDEX(INSUMOS!$B$6:$B$205,MATCH($C73,INSUMOS!$A$6:$A$205,0)),"¿Código?")) | E73: =IF($C73="","",IFERROR(INDEX(INSUMOS!$D$6:$D$205,MATCH($C73,INSUMOS!$A$6:$A$205,0)),"")) | G73: =IF(OR($A73="",$C73=""),"",IFERROR(INDEX(INSUMOS!$P$6:$P$205,MATCH($C73,INSUMOS!$A$6:$A$205,0)),0)) | H73: =IF(OR($A73="",$C73=""),"",N($F73)*$G73) | I73: =IF(OR($A73="",$C73=""),"",IFERROR(MAX(1,INDEX(PRODUCTOS!$G$6:$G$105,MATCH($A73,PRODUCTOS!$A$6:$A$105,0))),1)) | J73: =IF(OR($A73="",$C73=""),"",$H73/$I73) | K73: =IF(OR($A73="",$C73=""),"",SUMIFS(VENTAS!$E$6:$E$2005,VENTAS!$C$6:$C$2005,$A73)) | L73: =IF(OR($A73="",$C73=""),"",IFERROR(N($F73)/INDEX(INSUMOS!$I$6:$I$205,MATCH($C73,INSUMOS!$A$6:$A$205,0)),N($F73))/$I73*$K73) | M73: =IF($A73="","",COUNTIF($A$6:$A73,$A73)) | N73: =IF($A73="","",$A73&"|"&$M73)
... B605: =IF($A605="","",IFERROR(INDEX(PRODUCTOS!$B$6:$B$105,MATCH($A605,PRODUCTOS!$A$6:$A$105,0)),"¿Código?")) | D605: =IF($C605="","",IFERROR(INDEX(INSUMOS!$B$6:$B$205,MATCH($C605,INSUMOS!$A$6:$A$205,0)),"¿Código?")) | E605: =IF($C605="","",IFERROR(INDEX(INSUMOS!$D$6:$D$205,MATCH($C605,INSUMOS!$A$6:$A$205,0)),"")) | G605: =IF(OR($A605="",$C605=""),"",IFERROR(INDEX(INSUMOS!$P$6:$P$205,MATCH($C605,INSUMOS!$A$6:$A$205,0)),0)) | H605: =IF(OR($A605="",$C605=""),"",N($F605)*$G605) | I605: =IF(OR($A605="",$C605=""),"",IFERROR(MAX(1,INDEX(PRODUCTOS!$G$6:$G$105,MATCH($A605,PRODUCTOS!$A$6:$A$105,0))),1)) | J605: =IF(OR($A605="",$C605=""),"",$H605/$I605) | K605: =IF(OR($A605="",$C605=""),"",SUMIFS(VENTAS!$E$6:$E$2005,VENTAS!$C$6:$C$2005,$A605)) | L605: =IF(OR($A605="",$C605=""),"",IFERROR(N($F605)/INDEX(INSUMOS!$I$6:$I$205,MATCH($C605,INSUMOS!$A$6:$A$205,0)),N($F605))/$I605*$K605) | M605: =IF($A605="","",COUNTIF($A$6:$A605,$A605)) | N605: =IF($A605="","",$A605&"|"&$M605)

Sheet FICHA_TECNICA
A1: FICHA TÉCNICA DEL PRODUCTO
A2: Elija el código del producto en la celda azul. Se arma sola con la receta, costos y margen.
B4: Producto: | C4: P001 | D4: =IFERROR(INDEX(PRODUCTOS!$B$6:$B$105,MATCH($C$4,PRODUCTOS!$A$6:$A$105,0)),"") -> Fresas con crema Pequeño (8 oz)
C5: Categoría | D5: =IFERROR(INDEX(PRODUCTOS!$C$6:$C$105,MATCH($C$4,PRODUCTOS!$A$6:$A$105,0)),"") -> Fresas con crema
C6: Porciones por receta | D6: =IFERROR(INDEX(PRODUCTOS!$G$6:$G$105,MATCH($C$4,PRODUCTOS!$A$6:$A$105,0)),1) -> 1
C7: Precio venta CON IVA | D7: =IFERROR(INDEX(PRODUCTOS!$D$6:$D$105,MATCH($C$4,PRODUCTOS!$A$6:$A$105,0)),0) -> 1950
C8: Precio neto (sin IVA) | D8: =IFERROR(INDEX(PRODUCTOS!$F$6:$F$105,MATCH($C$4,PRODUCTOS!$A$6:$A$105,0)),0) -> 1725.6637
B10: # | C10: Ingrediente / insumo | D10: Cantidad | E10: Unidad | F10: Costo unitario | G10: Costo total
B11: 1 | C11: =IFERROR(INDEX(RECETAS!$D$6:$D$605,MATCH($C$4&"|"&1,RECETAS!$N$6:$N$605,0)),"") -> Fresas frescas | D11: =IFERROR(INDEX(RECETAS!$F$6:$F$605,MATCH($C$4&"|"&1,RECETAS!$N$6:$N$605,0)),"") -> 90 | E11: =IFERROR(INDEX(RECETAS!$E$6:$E$605,MATCH($C$4&"|"&1,RECETAS!$N$6:$N$605,0)),"") -> g | F11: =IFERROR(INDEX(RECETAS!$G$6:$G$605,MATCH($C$4&"|"&1,RECETAS!$N$6:$N$605,0)),"") -> 3.2941176 | G11: =IFERROR(INDEX(RECETAS!$H$6:$H$605,MATCH($C$4&"|"&1,RECETAS!$N$6:$N$605,0)),"") -> 296.47059
B12: 2 | C12: =IFERROR(INDEX(RECETAS!$D$6:$D$605,MATCH($C$4&"|"&2,RECETAS!$N$6:$N$605,0)),"") -> Crema dulce | D12: =IFERROR(INDEX(RECETAS!$F$6:$F$605,MATCH($C$4&"|"&2,RECETAS!$N$6:$N$605,0)),"") -> 45 | E12: =IFERROR(INDEX(RECETAS!$E$6:$E$605,MATCH($C$4&"|"&2,RECETAS!$N$6:$N$605,0)),"") -> ml | F12: =IFERROR(INDEX(RECETAS!$G$6:$G$605,MATCH($C$4&"|"&2,RECETAS!$N$6:$N$605,0)),"") -> 2.55 | G12: =IFERROR(INDEX(RECETAS!$H$6:$H$605,MATCH($C$4&"|"&2,RECETAS!$N$6:$N$605,0)),"") -> 114.75
B13: 3 | C13: =IFERROR(INDEX(RECETAS!$D$6:$D$605,MATCH($C$4&"|"&3,RECETAS!$N$6:$N$605,0)),"") -> Leche condensada | D13: =IFERROR(INDEX(RECETAS!$F$6:$F$605,MATCH($C$4&"|"&3,RECETAS!$N$6:$N$605,0)),"") -> 20 | E13: =IFERROR(INDEX(RECETAS!$E$6:$E$605,MATCH($C$4&"|"&3,RECETAS!$N$6:$N$605,0)),"") -> g | F13: =IFERROR(INDEX(RECETAS!$G$6:$G$605,MATCH($C$4&"|"&3,RECETAS!$N$6:$N$605,0)),"") -> 3.2459944 | G13: =IFERROR(INDEX(RECETAS!$H$6:$H$605,MATCH($C$4&"|"&3,RECETAS!$N$6:$N$605,0)),"") -> 64.919889
B14: 4 | C14: =IFERROR(INDEX(RECETAS!$D$6:$D$605,MATCH($C$4&"|"&4,RECETAS!$N$6:$N$605,0)),"") -> Esencia de vainilla | D14: =IFERROR(INDEX(RECETAS!$F$6:$F$605,MATCH($C$4&"|"&4,RECETAS!$N$6:$N$605,0)),"") -> 1 | E14: =IFERROR(INDEX(RECETAS!$E$6:$E$605,MATCH($C$4&"|"&4,RECETAS!$N$6:$N$605,0)),"") -> ml | F14: =IFERROR(INDEX(RECETAS!$G$6:$G$605,MATCH($C$4&"|"&4,RECETAS!$N$6:$N$605,0)),"") -> 7.2 | G14: =IFERROR(INDEX(RECETAS!$H$6:$H$605,MATCH($C$4&"|"&4,RECETAS!$N$6:$N$605,0)),"") -> 7.2
B15: 5 | C15: =IFERROR(INDEX(RECETAS!$D$6:$D$605,MATCH($C$4&"|"&5,RECETAS!$N$6:$N$605,0)),"") -> Galleta Oreo triturada | D15: =IFERROR(INDEX(RECETAS!$F$6:$F$605,MATCH($C$4&"|"&5,RECETAS!$N$6:$N$605,0)),"") -> 15 | E15: =IFERROR(INDEX(RECETAS!$E$6:$E$605,MATCH($C$4&"|"&5,RECETAS!$N$6:$N$605,0)),"") -> g | F15: =IFERROR(INDEX(RECETAS!$G$6:$G$605,MATCH($C$4&"|"&5,RECETAS!$N$6:$N$605,0)),"") -> 6.3352827 | G15: =IFERROR(INDEX(RECETAS!$H$6:$H$605,MATCH($C$4&"|"&5,RECETAS!$N$6:$N$605,0)),"") -> 95.02924
B16: 6 | C16: =IFERROR(INDEX(RECETAS!$D$6:$D$605,MATCH($C$4&"|"&6,RECETAS!$N$6:$N$605,0)),"") -> Vaso 8 oz con tapa | D16: =IFERROR(INDEX(RECETAS!$F$6:$F$605,MATCH($C$4&"|"&6,RECETAS!$N$6:$N$605,0)),"") -> 1 | E16: =IFERROR(INDEX(RECETAS!$E$6:$E$605,MATCH($C$4&"|"&6,RECETAS!$N$6:$N$605,0)),"") -> u | F16: =IFERROR(INDEX(RECETAS!$G$6:$G$605,MATCH($C$4&"|"&6,RECETAS!$N$6:$N$605,0)),"") -> 75 | G16: =IFERROR(INDEX(RECETAS!$H$6:$H$605,MATCH($C$4&"|"&6,RECETAS!$N$6:$N$605,0)),"") -> 75
B17: 7 | C17: =IFERROR(INDEX(RECETAS!$D$6:$D$605,MATCH($C$4&"|"&7,RECETAS!$N$6:$N$605,0)),"") -> Cuchara plástica | D17: =IFERROR(INDEX(RECETAS!$F$6:$F$605,MATCH($C$4&"|"&7,RECETAS!$N$6:$N$605,0)),"") -> 1 | E17: =IFERROR(INDEX(RECETAS!$E$6:$E$605,MATCH($C$4&"|"&7,RECETAS!$N$6:$N$605,0)),"") -> u | F17: =IFERROR(INDEX(RECETAS!$G$6:$G$605,MATCH($C$4&"|"&7,RECETAS!$N$6:$N$605,0)),"") -> 15 | G17: =IFERROR(INDEX(RECETAS!$H$6:$H$605,MATCH($C$4&"|"&7,RECETAS!$N$6:$N$605,0)),"") -> 15
B18: 8 | C18: =IFERROR(INDEX(RECETAS!$D$6:$D$605,MATCH($C$4&"|"&8,RECETAS!$N$6:$N$605,0)),"") -> Servilleta | D18: =IFERROR(INDEX(RECETAS!$F$6:$F$605,MATCH($C$4&"|"&8,RECETAS!$N$6:$N$605,0)),"") -> 1 | E18: =IFERROR(INDEX(RECETAS!$E$6:$E$605,MATCH($C$4&"|"&8,RECETAS!$N$6:$N$605,0)),"") -> u | F18: =IFERROR(INDEX(RECETAS!$G$6:$G$605,MATCH($C$4&"|"&8,RECETAS!$N$6:$N$605,0)),"") -> 5 | G18: =IFERROR(INDEX(RECETAS!$H$6:$H$605,MATCH($C$4&"|"&8,RECETAS!$N$6:$N$605,0)),"") -> 5
B19: 9 | C19: =IFERROR(INDEX(RECETAS!$D$6:$D$605,MATCH($C$4&"|"&9,RECETAS!$N$6:$N$605,0)),"") | D19: =IFERROR(INDEX(RECETAS!$F$6:$F$605,MATCH($C$4&"|"&9,RECETAS!$N$6:$N$605,0)),"") | E19: =IFERROR(INDEX(RECETAS!$E$6:$E$605,MATCH($C$4&"|"&9,RECETAS!$N$6:$N$605,0)),"") | F19: =IFERROR(INDEX(RECETAS!$G$6:$G$605,MATCH($C$4&"|"&9,RECETAS!$N$6:$N$605,0)),"") | G19: =IFERROR(INDEX(RECETAS!$H$6:$H$605,MATCH($C$4&"|"&9,RECETAS!$N$6:$N$605,0)),"")
B20: 10 | C20: =IFERROR(INDEX(RECETAS!$D$6:$D$605,MATCH($C$4&"|"&10,RECETAS!$N$6:$N$605,0)),"") | D20: =IFERROR(INDEX(RECETAS!$F$6:$F$605,MATCH($C$4&"|"&10,RECETAS!$N$6:$N$605,0)),"") | E20: =IFERROR(INDEX(RECETAS!$E$6:$E$605,MATCH($C$4&"|"&10,RECETAS!$N$6:$N$605,0)),"") | F20: =IFERROR(INDEX(RECETAS!$G$6:$G$605,MATCH($C$4&"|"&10,RECETAS!$N$6:$N$605,0)),"") | G20: =IFERROR(INDEX(RECETAS!$H$6:$H$605,MATCH($C$4&"|"&10,RECETAS!$N$6:$N$605,0)),"")
B21: 11 | C21: =IFERROR(INDEX(RECETAS!$D$6:$D$605,MATCH($C$4&"|"&11,RECETAS!$N$6:$N$605,0)),"") | D21: =IFERROR(INDEX(RECETAS!$F$6:$F$605,MATCH($C$4&"|"&11,RECETAS!$N$6:$N$605,0)),"") | E21: =IFERROR(INDEX(RECETAS!$E$6:$E$605,MATCH($C$4&"|"&11,RECETAS!$N$6:$N$605,0)),"") | F21: =IFERROR(INDEX(RECETAS!$G$6:$G$605,MATCH($C$4&"|"&11,RECETAS!$N$6:$N$605,0)),"") | G21: =IFERROR(INDEX(RECETAS!$H$6:$H$605,MATCH($C$4&"|"&11,RECETAS!$N$6:$N$605,0)),"")
B22: 12 | C22: =IFERROR(INDEX(RECETAS!$D$6:$D$605,MATCH($C$4&"|"&12,RECETAS!$N$6:$N$605,0)),"") | D22: =IFERROR(INDEX(RECETAS!$F$6:$F$605,MATCH($C$4&"|"&12,RECETAS!$N$6:$N$605,0)),"") | E22: =IFERROR(INDEX(RECETAS!$E$6:$E$605,MATCH($C$4&"|"&12,RECETAS!$N$6:$N$605,0)),"") | F22: =IFERROR(INDEX(RECETAS!$G$6:$G$605,MATCH($C$4&"|"&12,RECETAS!$N$6:$N$605,0)),"") | G22: =IFERROR(INDEX(RECETAS!$H$6:$H$605,MATCH($C$4&"|"&12,RECETAS!$N$6:$N$605,0)),"")
B23: 13 | C23: =IFERROR(INDEX(RECETAS!$D$6:$D$605,MATCH($C$4&"|"&13,RECETAS!$N$6:$N$605,0)),"") | D23: =IFERROR(INDEX(RECETAS!$F$6:$F$605,MATCH($C$4&"|"&13,RECETAS!$N$6:$N$605,0)),"") | E23: =IFERROR(INDEX(RECETAS!$E$6:$E$605,MATCH($C$4&"|"&13,RECETAS!$N$6:$N$605,0)),"") | F23: =IFERROR(INDEX(RECETAS!$G$6:$G$605,MATCH($C$4&"|"&13,RECETAS!$N$6:$N$605,0)),"") | G23: =IFERROR(INDEX(RECETAS!$H$6:$H$605,MATCH($C$4&"|"&13,RECETAS!$N$6:$N$605,0)),"")
B24: 14 | C24: =IFERROR(INDEX(RECETAS!$D$6:$D$605,MATCH($C$4&"|"&14,RECETAS!$N$6:$N$605,0)),"") | D24: =IFERROR(INDEX(RECETAS!$F$6:$F$605,MATCH($C$4&"|"&14,RECETAS!$N$6:$N$605,0)),"") | E24: =IFERROR(INDEX(RECETAS!$E$6:$E$605,MATCH($C$4&"|"&14,RECETAS!$N$6:$N$605,0)),"") | F24: =IFERROR(INDEX(RECETAS!$G$6:$G$605,MATCH($C$4&"|"&14,RECETAS!$N$6:$N$605,0)),"") | G24: =IFERROR(INDEX(RECETAS!$H$6:$H$605,MATCH($C$4&"|"&14,RECETAS!$N$6:$N$605,0)),"")
B25: 15 | C25: =IFERROR(INDEX(RECETAS!$D$6:$D$605,MATCH($C$4&"|"&15,RECETAS!$N$6:$N$605,0)),"") | D25: =IFERROR(INDEX(RECETAS!$F$6:$F$605,MATCH($C$4&"|"&15,RECETAS!$N$6:$N$605,0)),"") | E25: =IFERROR(INDEX(RECETAS!$E$6:$E$605,MATCH($C$4&"|"&15,RECETAS!$N$6:$N$605,0)),"") | F25: =IFERROR(INDEX(RECETAS!$G$6:$G$605,MATCH($C$4&"|"&15,RECETAS!$N$6:$N$605,0)),"") | G25: =IFERROR(INDEX(RECETAS!$H$6:$H$605,MATCH($C$4&"|"&15,RECETAS!$N$6:$N$605,0)),"")
B26: 16 | C26: =IFERROR(INDEX(RECETAS!$D$6:$D$605,MATCH($C$4&"|"&16,RECETAS!$N$6:$N$605,0)),"") | D26: =IFERROR(INDEX(RECETAS!$F$6:$F$605,MATCH($C$4&"|"&16,RECETAS!$N$6:$N$605,0)),"") | E26: =IFERROR(INDEX(RECETAS!$E$6:$E$605,MATCH($C$4&"|"&16,RECETAS!$N$6:$N$605,0)),"") | F26: =IFERROR(INDEX(RECETAS!$G$6:$G$605,MATCH($C$4&"|"&16,RECETAS!$N$6:$N$605,0)),"") | G26: =IFERROR(INDEX(RECETAS!$H$6:$H$605,MATCH($C$4&"|"&16,RECETAS!$N$6:$N$605,0)),"")
B27: 17 | C27: =IFERROR(INDEX(RECETAS!$D$6:$D$605,MATCH($C$4&"|"&17,RECETAS!$N$6:$N$605,0)),"") | D27: =IFERROR(INDEX(RECETAS!$F$6:$F$605,MATCH($C$4&"|"&17,RECETAS!$N$6:$N$605,0)),"") | E27: =IFERROR(INDEX(RECETAS!$E$6:$E$605,MATCH($C$4&"|"&17,RECETAS!$N$6:$N$605,0)),"") | F27: =IFERROR(INDEX(RECETAS!$G$6:$G$605,MATCH($C$4&"|"&17,RECETAS!$N$6:$N$605,0)),"") | G27: =IFERROR(INDEX(RECETAS!$H$6:$H$605,MATCH($C$4&"|"&17,RECETAS!$N$6:$N$605,0)),"")
B28: 18 | C28: =IFERROR(INDEX(RECETAS!$D$6:$D$605,MATCH($C$4&"|"&18,RECETAS!$N$6:$N$605,0)),"") | D28: =IFERROR(INDEX(RECETAS!$F$6:$F$605,MATCH($C$4&"|"&18,RECETAS!$N$6:$N$605,0)),"") | E28: =IFERROR(INDEX(RECETAS!$E$6:$E$605,MATCH($C$4&"|"&18,RECETAS!$N$6:$N$605,0)),"") | F28: =IFERROR(INDEX(RECETAS!$G$6:$G$605,MATCH($C$4&"|"&18,RECETAS!$N$6:$N$605,0)),"") | G28: =IFERROR(INDEX(RECETAS!$H$6:$H$605,MATCH($C$4&"|"&18,RECETAS!$N$6:$N$605,0)),"")
B29: 19 | C29: =IFERROR(INDEX(RECETAS!$D$6:$D$605,MATCH($C$4&"|"&19,RECETAS!$N$6:$N$605,0)),"") | D29: =IFERROR(INDEX(RECETAS!$F$6:$F$605,MATCH($C$4&"|"&19,RECETAS!$N$6:$N$605,0)),"") | E29: =IFERROR(INDEX(RECETAS!$E$6:$E$605,MATCH($C$4&"|"&19,RECETAS!$N$6:$N$605,0)),"") | F29: =IFERROR(INDEX(RECETAS!$G$6:$G$605,MATCH($C$4&"|"&19,RECETAS!$N$6:$N$605,0)),"") | G29: =IFERROR(INDEX(RECETAS!$H$6:$H$605,MATCH($C$4&"|"&19,RECETAS!$N$6:$N$605,0)),"")
B30: 20 | C30: =IFERROR(INDEX(RECETAS!$D$6:$D$605,MATCH($C$4&"|"&20,RECETAS!$N$6:$N$605,0)),"") | D30: =IFERROR(INDEX(RECETAS!$F$6:$F$605,MATCH($C$4&"|"&20,RECETAS!$N$6:$N$605,0)),"") | E30: =IFERROR(INDEX(RECETAS!$E$6:$E$605,MATCH($C$4&"|"&20,RECETAS!$N$6:$N$605,0)),"") | F30: =IFERROR(INDEX(RECETAS!$G$6:$G$605,MATCH($C$4&"|"&20,RECETAS!$N$6:$N$605,0)),"") | G30: =IFERROR(INDEX(RECETAS!$H$6:$H$605,MATCH($C$4&"|"&20,RECETAS!$N$6:$N$605,0)),"")
B31: 21 | C31: =IFERROR(INDEX(RECETAS!$D$6:$D$605,MATCH($C$4&"|"&21,RECETAS!$N$6:$N$605,0)),"") | D31: =IFERROR(INDEX(RECETAS!$F$6:$F$605,MATCH($C$4&"|"&21,RECETAS!$N$6:$N$605,0)),"") | E31: =IFERROR(INDEX(RECETAS!$E$6:$E$605,MATCH($C$4&"|"&21,RECETAS!$N$6:$N$605,0)),"") | F31: =IFERROR(INDEX(RECETAS!$G$6:$G$605,MATCH($C$4&"|"&21,RECETAS!$N$6:$N$605,0)),"") | G31: =IFERROR(INDEX(RECETAS!$H$6:$H$605,MATCH($C$4&"|"&21,RECETAS!$N$6:$N$605,0)),"")
B32: 22 | C32: =IFERROR(INDEX(RECETAS!$D$6:$D$605,MATCH($C$4&"|"&22,RECETAS!$N$6:$N$605,0)),"") | D32: =IFERROR(INDEX(RECETAS!$F$6:$F$605,MATCH($C$4&"|"&22,RECETAS!$N$6:$N$605,0)),"") | E32: =IFERROR(INDEX(RECETAS!$E$6:$E$605,MATCH($C$4&"|"&22,RECETAS!$N$6:$N$605,0)),"") | F32: =IFERROR(INDEX(RECETAS!$G$6:$G$605,MATCH($C$4&"|"&22,RECETAS!$N$6:$N$605,0)),"") | G32: =IFERROR(INDEX(RECETAS!$H$6:$H$605,MATCH($C$4&"|"&22,RECETAS!$N$6:$N$605,0)),"")
B33: 23 | C33: =IFERROR(INDEX(RECETAS!$D$6:$D$605,MATCH($C$4&"|"&23,RECETAS!$N$6:$N$605,0)),"") | D33: =IFERROR(INDEX(RECETAS!$F$6:$F$605,MATCH($C$4&"|"&23,RECETAS!$N$6:$N$605,0)),"") | E33: =IFERROR(INDEX(RECETAS!$E$6:$E$605,MATCH($C$4&"|"&23,RECETAS!$N$6:$N$605,0)),"") | F33: =IFERROR(INDEX(RECETAS!$G$6:$G$605,MATCH($C$4&"|"&23,RECETAS!$N$6:$N$605,0)),"") | G33: =IFERROR(INDEX(RECETAS!$H$6:$H$605,MATCH($C$4&"|"&23,RECETAS!$N$6:$N$605,0)),"")
B34: 24 | C34: =IFERROR(INDEX(RECETAS!$D$6:$D$605,MATCH($C$4&"|"&24,RECETAS!$N$6:$N$605,0)),"") | D34: =IFERROR(INDEX(RECETAS!$F$6:$F$605,MATCH($C$4&"|"&24,RECETAS!$N$6:$N$605,0)),"") | E34: =IFERROR(INDEX(RECETAS!$E$6:$E$605,MATCH($C$4&"|"&24,RECETAS!$N$6:$N$605,0)),"") | F34: =IFERROR(INDEX(RECETAS!$G$6:$G$605,MATCH($C$4&"|"&24,RECETAS!$N$6:$N$605,0)),"") | G34: =IFERROR(INDEX(RECETAS!$H$6:$H$605,MATCH($C$4&"|"&24,RECETAS!$N$6:$N$605,0)),"")
B35: 25 | C35: =IFERROR(INDEX(RECETAS!$D$6:$D$605,MATCH($C$4&"|"&25,RECETAS!$N$6:$N$605,0)),"") | D35: =IFERROR(INDEX(RECETAS!$F$6:$F$605,MATCH($C$4&"|"&25,RECETAS!$N$6:$N$605,0)),"") | E35: =IFERROR(INDEX(RECETAS!$E$6:$E$605,MATCH($C$4&"|"&25,RECETAS!$N$6:$N$605,0)),"") | F35: =IFERROR(INDEX(RECETAS!$G$6:$G$605,MATCH($C$4&"|"&25,RECETAS!$N$6:$N$605,0)),"") | G35: =IFERROR(INDEX(RECETAS!$H$6:$H$605,MATCH($C$4&"|"&25,RECETAS!$N$6:$N$605,0)),"")
B36: Costo total de la receta | G36: =SUM(G11:G35) -> 673.36972
B37: Costo variable por porción | G37: =IFERROR(G36/D6,0) -> 673.36972
B38: Contribución por porción | G38: =D8-G37 -> 1052.294
B39: Margen de contribución % | G39: =IFERROR(G38/D8,0) -> 0.60979088
B40: Food cost % | G40: =IFERROR(G37/D8,0) -> 0.39020912
B41: Precio sugerido CON IVA (margen objetivo) | G41: =IFERROR(INDEX(PRODUCTOS!$N$6:$N$105,MATCH($C$4,PRODUCTOS!$A$6:$A$105,0)),0) -> 2174.0222
B42: Estado | G42: =IFERROR(INDEX(PRODUCTOS!$R$6:$R$105,MATCH($C$4,PRODUCTOS!$A$6:$A$105,0)),"") -> REVISAR PRECIO
B44: Preparación / notas
B45: =IFERROR(INDEX(PRODUCTOS!$S$6:$S$105,MATCH($C$4,PRODUCTOS!$A$6:$A$105,0))&"","") -> 1) Lavar y desinfectar fresas, quitar hojas y picar en cuartos. 2) Batir crema dulce con leche condensada y vainilla. 3) Capas: fresas – crema – fresas. 4) 1 topping incluido. 5) Glaseado leche condensada. Tapar y servir con cuchara.

Sheet PRODUCTOS
A1: PRODUCTOS DEL MENÚ: COSTEO Y PRECIOS
A2: Precio de venta CON IVA (el que ve el cliente). Costo variable viene de RECETAS. Precio sugerido = costo ÷ (1 − margen objetivo) → 'margen sobre ventas', no recargo sobre costo.
A3: Contribución = precio neto − costo variable: lo que cada venta aporta para pagar fijos (alquiler, planilla…) y generar utilidad.
A5: Código | B5: Producto | C5: Categoría | D5: Precio venta CON IVA | E5: % IVA | F5: Precio neto (sin IVA) | G5: Porciones por receta / lote | H5: Costo variable por porción | I5: Contribu-ción unitaria | J5: Margen de contribución % | K5: Food cost % | L5: Margen objetivo % | M5: Precio sugerido neto | N5: Precio sugerido CON IVA | O5: Recargo sobre costo % | P5: Ventas estimadas por mes (unid.) | Q5: Unidades vendidas (registradas) | R5: Estado | S5: Preparación / notas de la ficha técnica
A6: P001 | B6: Fresas con crema Pequeño (8 oz) | C6: Fresas con crema | D6: 1950 | E6: 0.13 | F6: =IF($A6="","",IFERROR($D6/(1+$E6),0)) -> 1725.6637 | G6: 1 | H6: =IF($A6="","",SUMIFS(RECETAS!$J$6:$J$605,RECETAS!$A$6:$A$605,$A6)) -> 673.36972 | I6: =IF($A6="","",$F6-$H6) -> 1052.294 | J6: =IF($A6="","",IFERROR($I6/$F6,0)) -> 0.60979088 | K6: =IF($A6="","",IFERROR($H6/$F6,0)) -> 0.39020912 | L6: 0.65 | M6: =IF($A6="","",IFERROR($H6/(1-IF(N($L6)>0,$L6,MARGEN_OBJ)),0)) -> 1923.9135 | N6: =IF($A6="","",$M6*(1+$E6)) -> 2174.0222 | O6: =IF($A6="","",IFERROR($I6/$H6,0)) -> 1.5627284 | P6: 300 | Q6: =IF($A6="","",SUMIFS(VENTAS!$E$6:$E$2005,VENTAS!$C$6:$C$2005,$A6)) -> 27 | R6: =IF($A6="","",IF($H6=0,"SIN RECETA",IF($K6>FOODCOST_MAX,"REVISAR PRECIO","OK"))) -> REVISAR PRECIO | S6: 1) Lavar y desinfectar fresas, quitar hojas y picar en cuartos. 2) Batir crema dulce con leche condensada y vainilla. 3) Capas: fresas – crema – fresas. 4) 1 topping incluido. 5) Glaseado leche condensada. Tapar y servir con cuchara.
A7: P002 | B7: Fresas con crema Mediano (12 oz) | C7: Fresas con crema | D7: 2950 | E7: 0.13 | F7: =IF($A7="","",IFERROR($D7/(1+$E7),0)) -> 2610.6195 | G7: 1 | H7: =IF($A7="","",SUMIFS(RECETAS!$J$6:$J$605,RECETAS!$A$6:$A$605,$A7)) -> 1003.1355 | I7: =IF($A7="","",$F7-$H7) -> 1607.4839 | J7: =IF($A7="","",IFERROR($I7/$F7,0)) -> 0.61574808 | K7: =IF($A7="","",IFERROR($H7/$F7,0)) -> 0.38425192 | L7: 0.65 | M7: =IF($A7="","",IFERROR($H7/(1-IF(N($L7)>0,$L7,MARGEN_OBJ)),0)) -> 2866.1016 | N7: =IF($A7="","",$M7*(1+$E7)) -> 3238.6948 | O7: =IF($A7="","",IFERROR($I7/$H7,0)) -> 1.6024593 | P7: 450 | Q7: =IF($A7="","",SUMIFS(VENTAS!$E$6:$E$2005,VENTAS!$C$6:$C$2005,$A7)) -> 40 | R7: =IF($A7="","",IF($H7=0,"SIN RECETA",IF($K7>FOODCOST_MAX,"REVISAR PRECIO","OK"))) -> REVISAR PRECIO | S7: Igual al pequeño en vaso de 12 oz. Incluye 2 toppings.
A8: P003 | B8: Fresas con crema Grande (16 oz) | C8: Fresas con crema | D8: 4950 | E8: 0.13 | F8: =IF($A8="","",IFERROR($D8/(1+$E8),0)) -> 4380.531 | G8: 1 | H8: =IF($A8="","",SUMIFS(RECETAS!$J$6:$J$605,RECETAS!$A$6:$A$605,$A8)) -> 1524.8813 | I8: =IF($A8="","",$F8-$H8) -> 2855.6497 | J8: =IF($A8="","",IFERROR($I8/$F8,0)) -> 0.65189579 | K8: =IF($A8="","",IFERROR($H8/$F8,0)) -> 0.34810421 | L8: 0.65 | M8: =IF($A8="","",IFERROR($H8/(1-IF(N($L8)>0,$L8,MARGEN_OBJ)),0)) -> 4356.8037 | N8: =IF($A8="","",$M8*(1+$E8)) -> 4923.1881 | O8: =IF($A8="","",IFERROR($I8/$H8,0)) -> 1.872703 | P8: 250 | Q8: =IF($A8="","",SUMIFS(VENTAS!$E$6:$E$2005,VENTAS!$C$6:$C$2005,$A8)) -> 20 | R8: =IF($A8="","",IF($H8=0,"SIN RECETA",IF($K8>FOODCOST_MAX,"REVISAR PRECIO","OK"))) -> OK | S8: Vaso de 16 oz. Incluye 3 toppings.
A9: P004 | B9: Fresas con crema Extra grande (24 oz) | C9: Fresas con crema | D9: 6950 | E9: 0.13 | F9: =IF($A9="","",IFERROR($D9/(1+$E9),0)) -> 6150.4425 | G9: 1 | H9: =IF($A9="","",SUMIFS(RECETAS!$J$6:$J$605,RECETAS!$A$6:$A$605,$A9)) -> 2350.2736 | I9: =IF($A9="","",$F9-$H9) -> 3800.1689 | J9: =IF($A9="","",IFERROR($I9/$F9,0)) -> 0.61786919 | K9: =IF($A9="","",IFERROR($H9/$F9,0)) -> 0.38213081 | L9: 0.65 | M9: =IF($A9="","",IFERROR($H9/(1-IF(N($L9)>0,$L9,MARGEN_OBJ)),0)) -> 6715.0673 | N9: =IF($A9="","",$M9*(1+$E9)) -> 7588.0261 | O9: =IF($A9="","",IFERROR($I9/$H9,0)) -> 1.6169049 | P9: 80 | Q9: =IF($A9="","",SUMIFS(VENTAS!$E$6:$E$2005,VENTAS!$C$6:$C$2005,$A9)) -> 7 | R9: =IF($A9="","",IF($H9=0,"SIN RECETA",IF($K9>FOODCOST_MAX,"REVISAR PRECIO","OK"))) -> REVISAR PRECIO | S9: Vaso de 24 oz. Incluye 4 toppings y bolsa.
A10: P005 | B10: Maracumango | C10: Especiales | D10: 4200 | E10: 0.13 | F10: =IF($A10="","",IFERROR($D10/(1+$E10),0)) -> 3716.8142 | G10: 1 | H10: =IF($A10="","",SUMIFS(RECETAS!$J$6:$J$605,RECETAS!$A$6:$A$605,$A10)) -> 908.37983 | I10: =IF($A10="","",$F10-$H10) -> 2808.4343 | J10: =IF($A10="","",IFERROR($I10/$F10,0)) -> 0.75560257 | K10: =IF($A10="","",IFERROR($H10/$F10,0)) -> 0.24439743 | L10: 0.65 | M10: =IF($A10="","",IFERROR($H10/(1-IF(N($L10)>0,$L10,MARGEN_OBJ)),0)) -> 2595.371 | N10: =IF($A10="","",$M10*(1+$E10)) -> 2932.7692 | O10: =IF($A10="","",IFERROR($I10/$H10,0)) -> 3.091696 | P10: 150 | Q10: =IF($A10="","",SUMIFS(VENTAS!$E$6:$E$2005,VENTAS!$C$6:$C$2005,$A10)) -> 13 | R10: =IF($A10="","",IF($H10=0,"SIN RECETA",IF($K10>FOODCOST_MAX,"REVISAR PRECIO","OK"))) -> OK | S10: Mango en cubos + pulpa de maracuyá + crema. Vaso 16 oz.
A11: P006 | B11: Topping extra | C11: Extras | D11: 200 | E11: 0.13 | F11: =IF($A11="","",IFERROR($D11/(1+$E11),0)) -> 176.99115 | G11: 1 | H11: =IF($A11="","",SUMIFS(RECETAS!$J$6:$J$605,RECETAS!$A$6:$A$605,$A11)) -> 95.02924 | I11: =IF($A11="","",$F11-$H11) -> 81.961911 | J11: =IF($A11="","",IFERROR($I11/$F11,0)) -> 0.4630848 | K11: =IF($A11="","",IFERROR($H11/$F11,0)) -> 0.5369152 | L11: 0.65 | M11: =IF($A11="","",IFERROR($H11/(1-IF(N($L11)>0,$L11,MARGEN_OBJ)),0)) -> 271.51211 | N11: =IF($A11="","",$M11*(1+$E11)) -> 306.80869 | O11: =IF($A11="","",IFERROR($I11/$H11,0)) -> 0.86249149 | P11: 200 | Q11: =IF($A11="","",SUMIFS(VENTAS!$E$6:$E$2005,VENTAS!$C$6:$C$2005,$A11)) -> 8 | R11: =IF($A11="","",IF($H11=0,"SIN RECETA",IF($K11>FOODCOST_MAX,"REVISAR PRECIO","OK"))) -> REVISAR PRECIO | S11: Porción 15 g (Oreo, granola, maní, gomitas…). Costeado con Oreo.
A12: P007 | B12: Topping extra premium | C12: Extras | D12: 300 | E12: 0.13 | F12: =IF($A12="","",IFERROR($D12/(1+$E12),0)) -> 265.48673 | G12: 1 | H12: =IF($A12="","",SUMIFS(RECETAS!$J$6:$J$605,RECETAS!$A$6:$A$605,$A12)) -> 142.5 | I12: =IF($A12="","",$F12-$H12) -> 122.98673 | J12: =IF($A12="","",IFERROR($I12/$F12,0)) -> 0.46325 | K12: =IF($A12="","",IFERROR($H12/$F12,0)) -> 0.53675 | L12: 0.65 | M12: =IF($A12="","",IFERROR($H12/(1-IF(N($L12)>0,$L12,MARGEN_OBJ)),0)) -> 407.14286 | N12: =IF($A12="","",$M12*(1+$E12)) -> 460.07143 | O12: =IF($A12="","",IFERROR($I12/$H12,0)) -> 0.86306474 | P12: 80 | Q12: =IF($A12="","",SUMIFS(VENTAS!$E$6:$E$2005,VENTAS!$C$6:$C$2005,$A12)) -> 4 | R12: =IF($A12="","",IF($H12=0,"SIN RECETA",IF($K12>FOODCOST_MAX,"REVISAR PRECIO","OK"))) -> REVISAR PRECIO | S12: Porción 15 g (almendras, arándanos o queso). Costeado con almendras.
A13: P008 | B13: Jarabe premium (Nutella / pistacho) | C13: Extras | D13: 400 | E13: 0.13 | F13: =IF($A13="","",IFERROR($D13/(1+$E13),0)) -> 353.9823 | G13: 1 | H13: =IF($A13="","",SUMIFS(RECETAS!$J$6:$J$605,RECETAS!$A$6:$A$605,$A13)) -> 238.59649 | I13: =IF($A13="","",$F13-$H13) -> 115.38581 | J13: =IF($A13="","",IFERROR($I13/$F13,0)) -> 0.32596491 | K13: =IF($A13="","",IFERROR($H13/$F13,0)) -> 0.67403509 | L13: 0.65 | M13: =IF($A13="","",IFERROR($H13/(1-IF(N($L13)>0,$L13,MARGEN_OBJ)),0)) -> 681.70426 | N13: =IF($A13="","",$M13*(1+$E13)) -> 770.32581 | O13: =IF($A13="","",IFERROR($I13/$H13,0)) -> 0.48360229 | P13: 120 | Q13: =IF($A13="","",SUMIFS(VENTAS!$E$6:$E$2005,VENTAS!$C$6:$C$2005,$A13)) -> 5 | R13: =IF($A13="","",IF($H13=0,"SIN RECETA",IF($K13>FOODCOST_MAX,"REVISAR PRECIO","OK"))) -> REVISAR PRECIO | S13: Porción 25 g. Costeado con Nutella.
A14: P009 | B14: Brownie de la casa (lote de 20) | C14: Postres | D14: 1500 | E14: 0.13 | F14: =IF($A14="","",IFERROR($D14/(1+$E14),0)) -> 1327.4336 | G14: 20 | H14: =IF($A14="","",SUMIFS(RECETAS!$J$6:$J$605,RECETAS!$A$6:$A$605,$A14)) -> 169.6 | I14: =IF($A14="","",$F14-$H14) -> 1157.8336 | J14: =IF($A14="","",IFERROR($I14/$F14,0)) -> 0.87223467 | K14: =IF($A14="","",IFERROR($H14/$F14,0)) -> 0.12776533 | L14: 0.65 | M14: =IF($A14="","",IFERROR($H14/(1-IF(N($L14)>0,$L14,MARGEN_OBJ)),0)) -> 484.57143 | N14: =IF($A14="","",$M14*(1+$E14)) -> 547.56571 | O14: =IF($A14="","",IFERROR($I14/$H14,0)) -> 6.8268492 | P14: 60 | Q14: =IF($A14="","",SUMIFS(VENTAS!$E$6:$E$2005,VENTAS!$C$6:$C$2005,$A14)) -> 6 | R14: =IF($A14="","",IF($H14=0,"SIN RECETA",IF($K14>FOODCOST_MAX,"REVISAR PRECIO","OK"))) -> OK | S14: Ejemplo de LOTE: la receta es para 20 porciones; el costo se divide entre 20. Horno 180 °C, 25 min.
F15: =IF($A15="","",IFERROR($D15/(1+$E15),0)) | H15: =IF($A15="","",SUMIFS(RECETAS!$J$6:$J$605,RECETAS!$A$6:$A$605,$A15)) | I15: =IF($A15="","",$F15-$H15) | J15: =IF($A15="","",IFERROR($I15/$F15,0)) | K15: =IF($A15="","",IFERROR($H15/$F15,0)) | M15: =IF($A15="","",IFERROR($H15/(1-IF(N($L15)>0,$L15,MARGEN_OBJ)),0)) | N15: =IF($A15="","",$M15*(1+$E15)) | O15: =IF($A15="","",IFERROR($I15/$H15,0)) | Q15: =IF($A15="","",SUMIFS(VENTAS!$E$6:$E$2005,VENTAS!$C$6:$C$2005,$A15)) | R15: =IF($A15="","",IF($H15=0,"SIN RECETA",IF($K15>FOODCOST_MAX,"REVISAR PRECIO","OK")))
F16: =IF($A16="","",IFERROR($D16/(1+$E16),0)) | H16: =IF($A16="","",SUMIFS(RECETAS!$J$6:$J$605,RECETAS!$A$6:$A$605,$A16)) | I16: =IF($A16="","",$F16-$H16) | J16: =IF($A16="","",IFERROR($I16/$F16,0)) | K16: =IF($A16="","",IFERROR($H16/$F16,0)) | M16: =IF($A16="","",IFERROR($H16/(1-IF(N($L16)>0,$L16,MARGEN_OBJ)),0)) | N16: =IF($A16="","",$M16*(1+$E16)) | O16: =IF($A16="","",IFERROR($I16/$H16,0)) | Q16: =IF($A16="","",SUMIFS(VENTAS!$E$6:$E$2005,VENTAS!$C$6:$C$2005,$A16)) | R16: =IF($A16="","",IF($H16=0,"SIN RECETA",IF($K16>FOODCOST_MAX,"REVISAR PRECIO","OK")))
F17: =IF($A17="","",IFERROR($D17/(1+$E17),0)) | H17: =IF($A17="","",SUMIFS(RECETAS!$J$6:$J$605,RECETAS!$A$6:$A$605,$A17)) | I17: =IF($A17="","",$F17-$H17) | J17: =IF($A17="","",IFERROR($I17/$F17,0)) | K17: =IF($A17="","",IFERROR($H17/$F17,0)) | M17: =IF($A17="","",IFERROR($H17/(1-IF(N($L17)>0,$L17,MARGEN_OBJ)),0)) | N17: =IF($A17="","",$M17*(1+$E17)) | O17: =IF($A17="","",IFERROR($I17/$H17,0)) | Q17: =IF($A17="","",SUMIFS(VENTAS!$E$6:$E$2005,VENTAS!$C$6:$C$2005,$A17)) | R17: =IF($A17="","",IF($H17=0,"SIN RECETA",IF($K17>FOODCOST_MAX,"REVISAR PRECIO","OK")))
F18: =IF($A18="","",IFERROR($D18/(1+$E18),0)) | H18: =IF($A18="","",SUMIFS(RECETAS!$J$6:$J$605,RECETAS!$A$6:$A$605,$A18)) | I18: =IF($A18="","",$F18-$H18) | J18: =IF($A18="","",IFERROR($I18/$F18,0)) | K18: =IF($A18="","",IFERROR($H18/$F18,0)) | M18: =IF($A18="","",IFERROR($H18/(1-IF(N($L18)>0,$L18,MARGEN_OBJ)),0)) | N18: =IF($A18="","",$M18*(1+$E18)) | O18: =IF($A18="","",IFERROR($I18/$H18,0)) | Q18: =IF($A18="","",SUMIFS(VENTAS!$E$6:$E$2005,VENTAS!$C$6:$C$2005,$A18)) | R18: =IF($A18="","",IF($H18=0,"SIN RECETA",IF($K18>FOODCOST_MAX,"REVISAR PRECIO","OK")))
F19: =IF($A19="","",IFERROR($D19/(1+$E19),0)) | H19: =IF($A19="","",SUMIFS(RECETAS!$J$6:$J$605,RECETAS!$A$6:$A$605,$A19)) | I19: =IF($A19="","",$F19-$H19) | J19: =IF($A19="","",IFERROR($I19/$F19,0)) | K19: =IF($A19="","",IFERROR($H19/$F19,0)) | M19: =IF($A19="","",IFERROR($H19/(1-IF(N($L19)>0,$L19,MARGEN_OBJ)),0)) | N19: =IF($A19="","",$M19*(1+$E19)) | O19: =IF($A19="","",IFERROR($I19/$H19,0)) | Q19: =IF($A19="","",SUMIFS(VENTAS!$E$6:$E$2005,VENTAS!$C$6:$C$2005,$A19)) | R19: =IF($A19="","",IF($H19=0,"SIN RECETA",IF($K19>FOODCOST_MAX,"REVISAR PRECIO","OK")))
F20: =IF($A20="","",IFERROR($D20/(1+$E20),0)) | H20: =IF($A20="","",SUMIFS(RECETAS!$J$6:$J$605,RECETAS!$A$6:$A$605,$A20)) | I20: =IF($A20="","",$F20-$H20) | J20: =IF($A20="","",IFERROR($I20/$F20,0)) | K20: =IF($A20="","",IFERROR($H20/$F20,0)) | M20: =IF($A20="","",IFERROR($H20/(1-IF(N($L20)>0,$L20,MARGEN_OBJ)),0)) | N20: =IF($A20="","",$M20*(1+$E20)) | O20: =IF($A20="","",IFERROR($I20/$H20,0)) | Q20: =IF($A20="","",SUMIFS(VENTAS!$E$6:$E$2005,VENTAS!$C$6:$C$2005,$A20)) | R20: =IF($A20="","",IF($H20=0,"SIN RECETA",IF($K20>FOODCOST_MAX,"REVISAR PRECIO","OK")))
F21: =IF($A21="","",IFERROR($D21/(1+$E21),0)) | H21: =IF($A21="","",SUMIFS(RECETAS!$J$6:$J$605,RECETAS!$A$6:$A$605,$A21)) | I21: =IF($A21="","",$F21-$H21) | J21: =IF($A21="","",IFERROR($I21/$F21,0)) | K21: =IF($A21="","",IFERROR($H21/$F21,0)) | M21: =IF($A21="","",IFERROR($H21/(1-IF(N($L21)>0,$L21,MARGEN_OBJ)),0)) | N21: =IF($A21="","",$M21*(1+$E21)) | O21: =IF($A21="","",IFERROR($I21/$H21,0)) | Q21: =IF($A21="","",SUMIFS(VENTAS!$E$6:$E$2005,VENTAS!$C$6:$C$2005,$A21)) | R21: =IF($A21="","",IF($H21=0,"SIN RECETA",IF($K21>FOODCOST_MAX,"REVISAR PRECIO","OK")))
F22: =IF($A22="","",IFERROR($D22/(1+$E22),0)) | H22: =IF($A22="","",SUMIFS(RECETAS!$J$6:$J$605,RECETAS!$A$6:$A$605,$A22)) | I22: =IF($A22="","",$F22-$H22) | J22: =IF($A22="","",IFERROR($I22/$F22,0)) | K22: =IF($A22="","",IFERROR($H22/$F22,0)) | M22: =IF($A22="","",IFERROR($H22/(1-IF(N($L22)>0,$L22,MARGEN_OBJ)),0)) | N22: =IF($A22="","",$M22*(1+$E22)) | O22: =IF($A22="","",IFERROR($I22/$H22,0)) | Q22: =IF($A22="","",SUMIFS(VENTAS!$E$6:$E$2005,VENTAS!$C$6:$C$2005,$A22)) | R22: =IF($A22="","",IF($H22=0,"SIN RECETA",IF($K22>FOODCOST_MAX,"REVISAR PRECIO","OK")))
F23: =IF($A23="","",IFERROR($D23/(1+$E23),0)) | H23: =IF($A23="","",SUMIFS(RECETAS!$J$6:$J$605,RECETAS!$A$6:$A$605,$A23)) | I23: =IF($A23="","",$F23-$H23) | J23: =IF($A23="","",IFERROR($I23/$F23,0)) | K23: =IF($A23="","",IFERROR($H23/$F23,0)) | M23: =IF($A23="","",IFERROR($H23/(1-IF(N($L23)>0,$L23,MARGEN_OBJ)),0)) | N23: =IF($A23="","",$M23*(1+$E23)) | O23: =IF($A23="","",IFERROR($I23/$H23,0)) | Q23: =IF($A23="","",SUMIFS(VENTAS!$E$6:$E$2005,VENTAS!$C$6:$C$2005,$A23)) | R23: =IF($A23="","",IF($H23=0,"SIN RECETA",IF($K23>FOODCOST_MAX,"REVISAR PRECIO","OK")))
F24: =IF($A24="","",IFERROR($D24/(1+$E24),0)) | H24: =IF($A24="","",SUMIFS(RECETAS!$J$6:$J$605,RECETAS!$A$6:$A$605,$A24)) | I24: =IF($A24="","",$F24-$H24) | J24: =IF($A24="","",IFERROR($I24/$F24,0)) | K24: =IF($A24="","",IFERROR($H24/$F24,0)) | M24: =IF($A24="","",IFERROR($H24/(1-IF(N($L24)>0,$L24,MARGEN_OBJ)),0)) | N24: =IF($A24="","",$M24*(1+$E24)) | O24: =IF($A24="","",IFERROR($I24/$H24,0)) | Q24: =IF($A24="","",SUMIFS(VENTAS!$E$6:$E$2005,VENTAS!$C$6:$C$2005,$A24)) | R24: =IF($A24="","",IF($H24=0,"SIN RECETA",IF($K24>FOODCOST_MAX,"REVISAR PRECIO","OK")))
F25: =IF($A25="","",IFERROR($D25/(1+$E25),0)) | H25: =IF($A25="","",SUMIFS(RECETAS!$J$6:$J$605,RECETAS!$A$6:$A$605,$A25)) | I25: =IF($A25="","",$F25-$H25) | J25: =IF($A25="","",IFERROR($I25/$F25,0)) | K25: =IF($A25="","",IFERROR($H25/$F25,0)) | M25: =IF($A25="","",IFERROR($H25/(1-IF(N($L25)>0,$L25,MARGEN_OBJ)),0)) | N25: =IF($A25="","",$M25*(1+$E25)) | O25: =IF($A25="","",IFERROR($I25/$H25,0)) | Q25: =IF($A25="","",SUMIFS(VENTAS!$E$6:$E$2005,VENTAS!$C$6:$C$2005,$A25)) | R25: =IF($A25="","",IF($H25=0,"SIN RECETA",IF($K25>FOODCOST_MAX,"REVISAR PRECIO","OK")))
F26: =IF($A26="","",IFERROR($D26/(1+$E26),0)) | H26: =IF($A26="","",SUMIFS(RECETAS!$J$6:$J$605,RECETAS!$A$6:$A$605,$A26)) | I26: =IF($A26="","",$F26-$H26) | J26: =IF($A26="","",IFERROR($I26/$F26,0)) | K26: =IF($A26="","",IFERROR($H26/$F26,0)) | M26: =IF($A26="","",IFERROR($H26/(1-IF(N($L26)>0,$L26,MARGEN_OBJ)),0)) | N26: =IF($A26="","",$M26*(1+$E26)) | O26: =IF($A26="","",IFERROR($I26/$H26,0)) | Q26: =IF($A26="","",SUMIFS(VENTAS!$E$6:$E$2005,VENTAS!$C$6:$C$2005,$A26)) | R26: =IF($A26="","",IF($H26=0,"SIN RECETA",IF($K26>FOODCOST_MAX,"REVISAR PRECIO","OK")))
... F105: =IF($A105="","",IFERROR($D105/(1+$E105),0)) | H105: =IF($A105="","",SUMIFS(RECETAS!$J$6:$J$605,RECETAS!$A$6:$A$605,$A105)) | I105: =IF($A105="","",$F105-$H105) | J105: =IF($A105="","",IFERROR($I105/$F105,0)) | K105: =IF($A105="","",IFERROR($H105/$F105,0)) | M105: =IF($A105="","",IFERROR($H105/(1-IF(N($L105)>0,$L105,MARGEN_OBJ)),0)) | N105: =IF($A105="","",$M105*(1+$E105)) | O105: =IF($A105="","",IFERROR($I105/$H105,0)) | Q105: =IF($A105="","",SUMIFS(VENTAS!$E$6:$E$2005,VENTAS!$C$6:$C$2005,$A105)) | R105: =IF($A105="","",IF($H105=0,"SIN RECETA",IF($K105>FOODCOST_MAX,"REVISAR PRECIO","OK")))

Sheet VENTAS
A1: REGISTRO DE VENTAS
A2: Puede registrar cada ticket o, al cierre del día, el total vendido por producto y medio de pago (reporte del POS). Cada venta descuenta del inventario los insumos de su receta.
A5: Fecha | B5: N° ticket / factura | C5: Código producto | D5: Producto | E5: Cantidad | F5: Precio unitario CON IVA | G5: Descuento (₡) | H5: Venta total CON IVA | I5: IVA | J5: Venta neta | K5: Costo variable (receta) | L5: Contribución | M5: Medio de pago | N5: Canal | O5: Mes
A6: 46298 | B6: Cierre 03/10 | C6: P001 | D6: =IF($C6="","",IFERROR(INDEX(PRODUCTOS!$B$6:$B$105,MATCH($C6,PRODUCTOS!$A$6:$A$105,0)),"¿Código?")) -> Fresas con crema Pequeño (8 oz) | E6: 12 | F6: =IF($C6="","",IFERROR(INDEX(PRODUCTOS!$D$6:$D$105,MATCH($C6,PRODUCTOS!$A$6:$A$105,0)),0)) -> 1950 | H6: =IF($C6="","",N($E6)*$F6-N($G6)) -> 23400 | I6: =IF($C6="","",$H6-$H6/(1+IFERROR(INDEX(PRODUCTOS!$E$6:$E$105,MATCH($C6,PRODUCTOS!$A$6:$A$105,0)),IVA_VENTAS))) -> 2692.0354 | J6: =IF($C6="","",$H6-$I6) -> 20707.965 | K6: =IF($C6="","",N($E6)*IFERROR(INDEX(PRODUCTOS!$H$6:$H$105,MATCH($C6,PRODUCTOS!$A$6:$A$105,0)),0)) -> 8080.4366 | L6: =IF($C6="","",$J6-$K6) -> 12627.528 | M6: Efectivo | N6: Local | O6: =IF($A6="","",DATE(YEAR($A6),MONTH($A6),1)) -> 46296
A7: 46298 | B7: Cierre 03/10 | C7: P002 | D7: =IF($C7="","",IFERROR(INDEX(PRODUCTOS!$B$6:$B$105,MATCH($C7,PRODUCTOS!$A$6:$A$105,0)),"¿Código?")) -> Fresas con crema Mediano (12 oz) | E7: 18 | F7: =IF($C7="","",IFERROR(INDEX(PRODUCTOS!$D$6:$D$105,MATCH($C7,PRODUCTOS!$A$6:$A$105,0)),0)) -> 2950 | H7: =IF($C7="","",N($E7)*$F7-N($G7)) -> 53100 | I7: =IF($C7="","",$H7-$H7/(1+IFERROR(INDEX(PRODUCTOS!$E$6:$E$105,MATCH($C7,PRODUCTOS!$A$6:$A$105,0)),IVA_VENTAS))) -> 6108.8496 | J7: =IF($C7="","",$H7-$I7) -> 46991.15 | K7: =IF($C7="","",N($E7)*IFERROR(INDEX(PRODUCTOS!$H$6:$H$105,MATCH($C7,PRODUCTOS!$A$6:$A$105,0)),0)) -> 18056.44 | L7: =IF($C7="","",$J7-$K7) -> 28934.711 | M7: SINPE Móvil | N7: Local | O7: =IF($A7="","",DATE(YEAR($A7),MONTH($A7),1)) -> 46296
A8: 46298 | B8: Cierre 03/10 | C8: P003 | D8: =IF($C8="","",IFERROR(INDEX(PRODUCTOS!$B$6:$B$105,MATCH($C8,PRODUCTOS!$A$6:$A$105,0)),"¿Código?")) -> Fresas con crema Grande (16 oz) | E8: 9 | F8: =IF($C8="","",IFERROR(INDEX(PRODUCTOS!$D$6:$D$105,MATCH($C8,PRODUCTOS!$A$6:$A$105,0)),0)) -> 4950 | H8: =IF($C8="","",N($E8)*$F8-N($G8)) -> 44550 | I8: =IF($C8="","",$H8-$H8/(1+IFERROR(INDEX(PRODUCTOS!$E$6:$E$105,MATCH($C8,PRODUCTOS!$A$6:$A$105,0)),IVA_VENTAS))) -> 5125.2212 | J8: =IF($C8="","",$H8-$I8) -> 39424.779 | K8: =IF($C8="","",N($E8)*IFERROR(INDEX(PRODUCTOS!$H$6:$H$105,MATCH($C8,PRODUCTOS!$A$6:$A$105,0)),0)) -> 13723.932 | L8: =IF($C8="","",$J8-$K8) -> 25700.847 | M8: Tarjeta | N8: Local | O8: =IF($A8="","",DATE(YEAR($A8),MONTH($A8),1)) -> 46296
A9: 46298 | B9: Cierre 03/10 | C9: P004 | D9: =IF($C9="","",IFERROR(INDEX(PRODUCTOS!$B$6:$B$105,MATCH($C9,PRODUCTOS!$A$6:$A$105,0)),"¿Código?")) -> Fresas con crema Extra grande (24 oz) | E9: 3 | F9: =IF($C9="","",IFERROR(INDEX(PRODUCTOS!$D$6:$D$105,MATCH($C9,PRODUCTOS!$A$6:$A$105,0)),0)) -> 6950 | H9: =IF($C9="","",N($E9)*$F9-N($G9)) -> 20850 | I9: =IF($C9="","",$H9-$H9/(1+IFERROR(INDEX(PRODUCTOS!$E$6:$E$105,MATCH($C9,PRODUCTOS!$A$6:$A$105,0)),IVA_VENTAS))) -> 2398.6726 | J9: =IF($C9="","",$H9-$I9) -> 18451.327 | K9: =IF($C9="","",N($E9)*IFERROR(INDEX(PRODUCTOS!$H$6:$H$105,MATCH($C9,PRODUCTOS!$A$6:$A$105,0)),0)) -> 7050.8207 | L9: =IF($C9="","",$J9-$K9) -> 11400.507 | M9: SINPE Móvil | N9: Local | O9: =IF($A9="","",DATE(YEAR($A9),MONTH($A9),1)) -> 46296
A10: 46298 | B10: Cierre 03/10 | C10: P005 | D10: =IF($C10="","",IFERROR(INDEX(PRODUCTOS!$B$6:$B$105,MATCH($C10,PRODUCTOS!$A$6:$A$105,0)),"¿Código?")) -> Maracumango | E10: 6 | F10: =IF($C10="","",IFERROR(INDEX(PRODUCTOS!$D$6:$D$105,MATCH($C10,PRODUCTOS!$A$6:$A$105,0)),0)) -> 4200 | H10: =IF($C10="","",N($E10)*$F10-N($G10)) -> 25200 | I10: =IF($C10="","",$H10-$H10/(1+IFERROR(INDEX(PRODUCTOS!$E$6:$E$105,MATCH($C10,PRODUCTOS!$A$6:$A$105,0)),IVA_VENTAS))) -> 2899.115 | J10: =IF($C10="","",$H10-$I10) -> 22300.885 | K10: =IF($C10="","",N($E10)*IFERROR(INDEX(PRODUCTOS!$H$6:$H$105,MATCH($C10,PRODUCTOS!$A$6:$A$105,0)),0)) -> 5450.279 | L10: =IF($C10="","",$J10-$K10) -> 16850.606 | M10: Efectivo | N10: Local | O10: =IF($A10="","",DATE(YEAR($A10),MONTH($A10),1)) -> 46296
A11: 46298 | B11: Cierre 03/10 | C11: P006 | D11: =IF($C11="","",IFERROR(INDEX(PRODUCTOS!$B$6:$B$105,MATCH($C11,PRODUCTOS!$A$6:$A$105,0)),"¿Código?")) -> Topping extra | E11: 8 | F11: =IF($C11="","",IFERROR(INDEX(PRODUCTOS!$D$6:$D$105,MATCH($C11,PRODUCTOS!$A$6:$A$105,0)),0)) -> 200 | H11: =IF($C11="","",N($E11)*$F11-N($G11)) -> 1600 | I11: =IF($C11="","",$H11-$H11/(1+IFERROR(INDEX(PRODUCTOS!$E$6:$E$105,MATCH($C11,PRODUCTOS!$A$6:$A$105,0)),IVA_VENTAS))) -> 184.0708 | J11: =IF($C11="","",$H11-$I11) -> 1415.9292 | K11: =IF($C11="","",N($E11)*IFERROR(INDEX(PRODUCTOS!$H$6:$H$105,MATCH($C11,PRODUCTOS!$A$6:$A$105,0)),0)) -> 760.23392 | L11: =IF($C11="","",$J11-$K11) -> 655.69529 | M11: Efectivo | N11: Local | O11: =IF($A11="","",DATE(YEAR($A11),MONTH($A11),1)) -> 46296
A12: 46298 | B12: Cierre 03/10 | C12: P008 | D12: =IF($C12="","",IFERROR(INDEX(PRODUCTOS!$B$6:$B$105,MATCH($C12,PRODUCTOS!$A$6:$A$105,0)),"¿Código?")) -> Jarabe premium (Nutella / pistacho) | E12: 5 | F12: =IF($C12="","",IFERROR(INDEX(PRODUCTOS!$D$6:$D$105,MATCH($C12,PRODUCTOS!$A$6:$A$105,0)),0)) -> 400 | H12: =IF($C12="","",N($E12)*$F12-N($G12)) -> 2000 | I12: =IF($C12="","",$H12-$H12/(1+IFERROR(INDEX(PRODUCTOS!$E$6:$E$105,MATCH($C12,PRODUCTOS!$A$6:$A$105,0)),IVA_VENTAS))) -> 230.0885 | J12: =IF($C12="","",$H12-$I12) -> 1769.9115 | K12: =IF($C12="","",N($E12)*IFERROR(INDEX(PRODUCTOS!$H$6:$H$105,MATCH($C12,PRODUCTOS!$A$6:$A$105,0)),0)) -> 1192.9825 | L12: =IF($C12="","",$J12-$K12) -> 576.92905 | M12: SINPE Móvil | N12: Local | O12: =IF($A12="","",DATE(YEAR($A12),MONTH($A12),1)) -> 46296
A13: 46299 | B13: Cierre 04/10 | C13: P001 | D13: =IF($C13="","",IFERROR(INDEX(PRODUCTOS!$B$6:$B$105,MATCH($C13,PRODUCTOS!$A$6:$A$105,0)),"¿Código?")) -> Fresas con crema Pequeño (8 oz) | E13: 15 | F13: =IF($C13="","",IFERROR(INDEX(PRODUCTOS!$D$6:$D$105,MATCH($C13,PRODUCTOS!$A$6:$A$105,0)),0)) -> 1950 | H13: =IF($C13="","",N($E13)*$F13-N($G13)) -> 29250 | I13: =IF($C13="","",$H13-$H13/(1+IFERROR(INDEX(PRODUCTOS!$E$6:$E$105,MATCH($C13,PRODUCTOS!$A$6:$A$105,0)),IVA_VENTAS))) -> 3365.0442 | J13: =IF($C13="","",$H13-$I13) -> 25884.956 | K13: =IF($C13="","",N($E13)*IFERROR(INDEX(PRODUCTOS!$H$6:$H$105,MATCH($C13,PRODUCTOS!$A$6:$A$105,0)),0)) -> 10100.546 | L13: =IF($C13="","",$J13-$K13) -> 15784.41 | M13: Efectivo | N13: Local | O13: =IF($A13="","",DATE(YEAR($A13),MONTH($A13),1)) -> 46296
A14: 46299 | B14: Cierre 04/10 | C14: P002 | D14: =IF($C14="","",IFERROR(INDEX(PRODUCTOS!$B$6:$B$105,MATCH($C14,PRODUCTOS!$A$6:$A$105,0)),"¿Código?")) -> Fresas con crema Mediano (12 oz) | E14: 22 | F14: =IF($C14="","",IFERROR(INDEX(PRODUCTOS!$D$6:$D$105,MATCH($C14,PRODUCTOS!$A$6:$A$105,0)),0)) -> 2950 | H14: =IF($C14="","",N($E14)*$F14-N($G14)) -> 64900 | I14: =IF($C14="","",$H14-$H14/(1+IFERROR(INDEX(PRODUCTOS!$E$6:$E$105,MATCH($C14,PRODUCTOS!$A$6:$A$105,0)),IVA_VENTAS))) -> 7466.3717 | J14: =IF($C14="","",$H14-$I14) -> 57433.628 | K14: =IF($C14="","",N($E14)*IFERROR(INDEX(PRODUCTOS!$H$6:$H$105,MATCH($C14,PRODUCTOS!$A$6:$A$105,0)),0)) -> 22068.982 | L14: =IF($C14="","",$J14-$K14) -> 35364.646 | M14: SINPE Móvil | N14: Local | O14: =IF($A14="","",DATE(YEAR($A14),MONTH($A14),1)) -> 46296
A15: 46299 | B15: Cierre 04/10 | C15: P003 | D15: =IF($C15="","",IFERROR(INDEX(PRODUCTOS!$B$6:$B$105,MATCH($C15,PRODUCTOS!$A$6:$A$105,0)),"¿Código?")) -> Fresas con crema Grande (16 oz) | E15: 11 | F15: =IF($C15="","",IFERROR(INDEX(PRODUCTOS!$D$6:$D$105,MATCH($C15,PRODUCTOS!$A$6:$A$105,0)),0)) -> 4950 | H15: =IF($C15="","",N($E15)*$F15-N($G15)) -> 54450 | I15: =IF($C15="","",$H15-$H15/(1+IFERROR(INDEX(PRODUCTOS!$E$6:$E$105,MATCH($C15,PRODUCTOS!$A$6:$A$105,0)),IVA_VENTAS))) -> 6264.1593 | J15: =IF($C15="","",$H15-$I15) -> 48185.841 | K15: =IF($C15="","",N($E15)*IFERROR(INDEX(PRODUCTOS!$H$6:$H$105,MATCH($C15,PRODUCTOS!$A$6:$A$105,0)),0)) -> 16773.694 | L15: =IF($C15="","",$J15-$K15) -> 31412.147 | M15: Tarjeta | N15: Local | O15: =IF($A15="","",DATE(YEAR($A15),MONTH($A15),1)) -> 46296
A16: 46299 | B16: Cierre 04/10 | C16: P004 | D16: =IF($C16="","",IFERROR(INDEX(PRODUCTOS!$B$6:$B$105,MATCH($C16,PRODUCTOS!$A$6:$A$105,0)),"¿Código?")) -> Fresas con crema Extra grande (24 oz) | E16: 4 | F16: =IF($C16="","",IFERROR(INDEX(PRODUCTOS!$D$6:$D$105,MATCH($C16,PRODUCTOS!$A$6:$A$105,0)),0)) -> 6950 | H16: =IF($C16="","",N($E16)*$F16-N($G16)) -> 27800 | I16: =IF($C16="","",$H16-$H16/(1+IFERROR(INDEX(PRODUCTOS!$E$6:$E$105,MATCH($C16,PRODUCTOS!$A$6:$A$105,0)),IVA_VENTAS))) -> 3198.2301 | J16: =IF($C16="","",$H16-$I16) -> 24601.77 | K16: =IF($C16="","",N($E16)*IFERROR(INDEX(PRODUCTOS!$H$6:$H$105,MATCH($C16,PRODUCTOS!$A$6:$A$105,0)),0)) -> 9401.0943 | L16: =IF($C16="","",$J16-$K16) -> 15200.676 | M16: Tarjeta | N16: Local | O16: =IF($A16="","",DATE(YEAR($A16),MONTH($A16),1)) -> 46296
A17: 46299 | B17: Cierre 04/10 | C17: P005 | D17: =IF($C17="","",IFERROR(INDEX(PRODUCTOS!$B$6:$B$105,MATCH($C17,PRODUCTOS!$A$6:$A$105,0)),"¿Código?")) -> Maracumango | E17: 7 | F17: =IF($C17="","",IFERROR(INDEX(PRODUCTOS!$D$6:$D$105,MATCH($C17,PRODUCTOS!$A$6:$A$105,0)),0)) -> 4200 | H17: =IF($C17="","",N($E17)*$F17-N($G17)) -> 29400 | I17: =IF($C17="","",$H17-$H17/(1+IFERROR(INDEX(PRODUCTOS!$E$6:$E$105,MATCH($C17,PRODUCTOS!$A$6:$A$105,0)),IVA_VENTAS))) -> 3382.3009 | J17: =IF($C17="","",$H17-$I17) -> 26017.699 | K17: =IF($C17="","",N($E17)*IFERROR(INDEX(PRODUCTOS!$H$6:$H$105,MATCH($C17,PRODUCTOS!$A$6:$A$105,0)),0)) -> 6358.6588 | L17: =IF($C17="","",$J17-$K17) -> 19659.04 | M17: SINPE Móvil | N17: Local | O17: =IF($A17="","",DATE(YEAR($A17),MONTH($A17),1)) -> 46296
... A19: 46299 | B19: Cierre 04/10 | C19: P009 | D19: =IF($C19="","",IFERROR(INDEX(PRODUCTOS!$B$6:$B$105,MATCH($C19,PRODUCTOS!$A$6:$A$105,0)),"¿Código?")) -> Brownie de la casa (lote de 20) | E19: 6 | F19: =IF($C19="","",IFERROR(INDEX(PRODUCTOS!$D$6:$D$105,MATCH($C19,PRODUCTOS!$A$6:$A$105,0)),0)) -> 1500 | H19: =IF($C19="","",N($E19)*$F19-N($G19)) -> 9000 | I19: =IF($C19="","",$H19-$H19/(1+IFERROR(INDEX(PRODUCTOS!$E$6:$E$105,MATCH($C19,PRODUCTOS!$A$6:$A$105,0)),IVA_VENTAS))) -> 1035.3982 | J19: =IF($C19="","",$H19-$I19) -> 7964.6018 | K19: =IF($C19="","",N($E19)*IFERROR(INDEX(PRODUCTOS!$H$6:$H$105,MATCH($C19,PRODUCTOS!$A$6:$A$105,0)),0)) -> 1017.6 | L19: =IF($C19="","",$J19-$K19) -> 6947.0018 | M19: Efectivo | N19: Local | O19: =IF($A19="","",DATE(YEAR($A19),MONTH($A19),1)) -> 46296
D20: =IF($C20="","",IFERROR(INDEX(PRODUCTOS!$B$6:$B$105,MATCH($C20,PRODUCTOS!$A$6:$A$105,0)),"¿Código?")) | F20: =IF($C20="","",IFERROR(INDEX(PRODUCTOS!$D$6:$D$105,MATCH($C20,PRODUCTOS!$A$6:$A$105,0)),0)) | H20: =IF($C20="","",N($E20)*$F20-N($G20)) | I20: =IF($C20="","",$H20-$H20/(1+IFERROR(INDEX(PRODUCTOS!$E$6:$E$105,MATCH($C20,PRODUCTOS!$A$6:$A$105,0)),IVA_VENTAS))) | J20: =IF($C20="","",$H20-$I20) | K20: =IF($C20="","",N($E20)*IFERROR(INDEX(PRODUCTOS!$H$6:$H$105,MATCH($C20,PRODUCTOS!$A$6:$A$105,0)),0)) | L20: =IF($C20="","",$J20-$K20) | O20: =IF($A20="","",DATE(YEAR($A20),MONTH($A20),1))
D21: =IF($C21="","",IFERROR(INDEX(PRODUCTOS!$B$6:$B$105,MATCH($C21,PRODUCTOS!$A$6:$A$105,0)),"¿Código?")) | F21: =IF($C21="","",IFERROR(INDEX(PRODUCTOS!$D$6:$D$105,MATCH($C21,PRODUCTOS!$A$6:$A$105,0)),0)) | H21: =IF($C21="","",N($E21)*$F21-N($G21)) | I21: =IF($C21="","",$H21-$H21/(1+IFERROR(INDEX(PRODUCTOS!$E$6:$E$105,MATCH($C21,PRODUCTOS!$A$6:$A$105,0)),IVA_VENTAS))) | J21: =IF($C21="","",$H21-$I21) | K21: =IF($C21="","",N($E21)*IFERROR(INDEX(PRODUCTOS!$H$6:$H$105,MATCH($C21,PRODUCTOS!$A$6:$A$105,0)),0)) | L21: =IF($C21="","",$J21-$K21) | O21: =IF($A21="","",DATE(YEAR($A21),MONTH($A21),1))
D22: =IF($C22="","",IFERROR(INDEX(PRODUCTOS!$B$6:$B$105,MATCH($C22,PRODUCTOS!$A$6:$A$105,0)),"¿Código?")) | F22: =IF($C22="","",IFERROR(INDEX(PRODUCTOS!$D$6:$D$105,MATCH($C22,PRODUCTOS!$A$6:$A$105,0)),0)) | H22: =IF($C22="","",N($E22)*$F22-N($G22)) | I22: =IF($C22="","",$H22-$H22/(1+IFERROR(INDEX(PRODUCTOS!$E$6:$E$105,MATCH($C22,PRODUCTOS!$A$6:$A$105,0)),IVA_VENTAS))) | J22: =IF($C22="","",$H22-$I22) | K22: =IF($C22="","",N($E22)*IFERROR(INDEX(PRODUCTOS!$H$6:$H$105,MATCH($C22,PRODUCTOS!$A$6:$A$105,0)),0)) | L22: =IF($C22="","",$J22-$K22) | O22: =IF($A22="","",DATE(YEAR($A22),MONTH($A22),1))
D23: =IF($C23="","",IFERROR(INDEX(PRODUCTOS!$B$6:$B$105,MATCH($C23,PRODUCTOS!$A$6:$A$105,0)),"¿Código?")) | F23: =IF($C23="","",IFERROR(INDEX(PRODUCTOS!$D$6:$D$105,MATCH($C23,PRODUCTOS!$A$6:$A$105,0)),0)) | H23: =IF($C23="","",N($E23)*$F23-N($G23)) | I23: =IF($C23="","",$H23-$H23/(1+IFERROR(INDEX(PRODUCTOS!$E$6:$E$105,MATCH($C23,PRODUCTOS!$A$6:$A$105,0)),IVA_VENTAS))) | J23: =IF($C23="","",$H23-$I23) | K23: =IF($C23="","",N($E23)*IFERROR(INDEX(PRODUCTOS!$H$6:$H$105,MATCH($C23,PRODUCTOS!$A$6:$A$105,0)),0)) | L23: =IF($C23="","",$J23-$K23) | O23: =IF($A23="","",DATE(YEAR($A23),MONTH($A23),1))
D24: =IF($C24="","",IFERROR(INDEX(PRODUCTOS!$B$6:$B$105,MATCH($C24,PRODUCTOS!$A$6:$A$105,0)),"¿Código?")) | F24: =IF($C24="","",IFERROR(INDEX(PRODUCTOS!$D$6:$D$105,MATCH($C24,PRODUCTOS!$A$6:$A$105,0)),0)) | H24: =IF($C24="","",N($E24)*$F24-N($G24)) | I24: =IF($C24="","",$H24-$H24/(1+IFERROR(INDEX(PRODUCTOS!$E$6:$E$105,MATCH($C24,PRODUCTOS!$A$6:$A$105,0)),IVA_VENTAS))) | J24: =IF($C24="","",$H24-$I24) | K24: =IF($C24="","",N($E24)*IFERROR(INDEX(PRODUCTOS!$H$6:$H$105,MATCH($C24,PRODUCTOS!$A$6:$A$105,0)),0)) | L24: =IF($C24="","",$J24-$K24) | O24: =IF($A24="","",DATE(YEAR($A24),MONTH($A24),1))
D25: =IF($C25="","",IFERROR(INDEX(PRODUCTOS!$B$6:$B$105,MATCH($C25,PRODUCTOS!$A$6:$A$105,0)),"¿Código?")) | F25: =IF($C25="","",IFERROR(INDEX(PRODUCTOS!$D$6:$D$105,MATCH($C25,PRODUCTOS!$A$6:$A$105,0)),0)) | H25: =IF($C25="","",N($E25)*$F25-N($G25)) | I25: =IF($C25="","",$H25-$H25/(1+IFERROR(INDEX(PRODUCTOS!$E$6:$E$105,MATCH($C25,PRODUCTOS!$A$6:$A$105,0)),IVA_VENTAS))) | J25: =IF($C25="","",$H25-$I25) | K25: =IF($C25="","",N($E25)*IFERROR(INDEX(PRODUCTOS!$H$6:$H$105,MATCH($C25,PRODUCTOS!$A$6:$A$105,0)),0)) | L25: =IF($C25="","",$J25-$K25) | O25: =IF($A25="","",DATE(YEAR($A25),MONTH($A25),1))
D26: =IF($C26="","",IFERROR(INDEX(PRODUCTOS!$B$6:$B$105,MATCH($C26,PRODUCTOS!$A$6:$A$105,0)),"¿Código?")) | F26: =IF($C26="","",IFERROR(INDEX(PRODUCTOS!$D$6:$D$105,MATCH($C26,PRODUCTOS!$A$6:$A$105,0)),0)) | H26: =IF($C26="","",N($E26)*$F26-N($G26)) | I26: =IF($C26="","",$H26-$H26/(1+IFERROR(INDEX(PRODUCTOS!$E$6:$E$105,MATCH($C26,PRODUCTOS!$A$6:$A$105,0)),IVA_VENTAS))) | J26: =IF($C26="","",$H26-$I26) | K26: =IF($C26="","",N($E26)*IFERROR(INDEX(PRODUCTOS!$H$6:$H$105,MATCH($C26,PRODUCTOS!$A$6:$A$105,0)),0)) | L26: =IF($C26="","",$J26-$K26) | O26: =IF($A26="","",DATE(YEAR($A26),MONTH($A26),1))
D27: =IF($C27="","",IFERROR(INDEX(PRODUCTOS!$B$6:$B$105,MATCH($C27,PRODUCTOS!$A$6:$A$105,0)),"¿Código?")) | F27: =IF($C27="","",IFERROR(INDEX(PRODUCTOS!$D$6:$D$105,MATCH($C27,PRODUCTOS!$A$6:$A$105,0)),0)) | H27: =IF($C27="","",N($E27)*$F27-N($G27)) | I27: =IF($C27="","",$H27-$H27/(1+IFERROR(INDEX(PRODUCTOS!$E$6:$E$105,MATCH($C27,PRODUCTOS!$A$6:$A$105,0)),IVA_VENTAS))) | J27: =IF($C27="","",$H27-$I27) | K27: =IF($C27="","",N($E27)*IFERROR(INDEX(PRODUCTOS!$H$6:$H$105,MATCH($C27,PRODUCTOS!$A$6:$A$105,0)),0)) | L27: =IF($C27="","",$J27-$K27) | O27: =IF($A27="","",DATE(YEAR($A27),MONTH($A27),1))
D28: =IF($C28="","",IFERROR(INDEX(PRODUCTOS!$B$6:$B$105,MATCH($C28,PRODUCTOS!$A$6:$A$105,0)),"¿Código?")) | F28: =IF($C28="","",IFERROR(INDEX(PRODUCTOS!$D$6:$D$105,MATCH($C28,PRODUCTOS!$A$6:$A$105,0)),0)) | H28: =IF($C28="","",N($E28)*$F28-N($G28)) | I28: =IF($C28="","",$H28-$H28/(1+IFERROR(INDEX(PRODUCTOS!$E$6:$E$105,MATCH($C28,PRODUCTOS!$A$6:$A$105,0)),IVA_VENTAS))) | J28: =IF($C28="","",$H28-$I28) | K28: =IF($C28="","",N($E28)*IFERROR(INDEX(PRODUCTOS!$H$6:$H$105,MATCH($C28,PRODUCTOS!$A$6:$A$105,0)),0)) | L28: =IF($C28="","",$J28-$K28) | O28: =IF($A28="","",DATE(YEAR($A28),MONTH($A28),1))
D29: =IF($C29="","",IFERROR(INDEX(PRODUCTOS!$B$6:$B$105,MATCH($C29,PRODUCTOS!$A$6:$A$105,0)),"¿Código?")) | F29: =IF($C29="","",IFERROR(INDEX(PRODUCTOS!$D$6:$D$105,MATCH($C29,PRODUCTOS!$A$6:$A$105,0)),0)) | H29: =IF($C29="","",N($E29)*$F29-N($G29)) | I29: =IF($C29="","",$H29-$H29/(1+IFERROR(INDEX(PRODUCTOS!$E$6:$E$105,MATCH($C29,PRODUCTOS!$A$6:$A$105,0)),IVA_VENTAS))) | J29: =IF($C29="","",$H29-$I29) | K29: =IF($C29="","",N($E29)*IFERROR(INDEX(PRODUCTOS!$H$6:$H$105,MATCH($C29,PRODUCTOS!$A$6:$A$105,0)),0)) | L29: =IF($C29="","",$J29-$K29) | O29: =IF($A29="","",DATE(YEAR($A29),MONTH($A29),1))
D30: =IF($C30="","",IFERROR(INDEX(PRODUCTOS!$B$6:$B$105,MATCH($C30,PRODUCTOS!$A$6:$A$105,0)),"¿Código?")) | F30: =IF($C30="","",IFERROR(INDEX(PRODUCTOS!$D$6:$D$105,MATCH($C30,PRODUCTOS!$A$6:$A$105,0)),0)) | H30: =IF($C30="","",N($E30)*$F30-N($G30)) | I30: =IF($C30="","",$H30-$H30/(1+IFERROR(INDEX(PRODUCTOS!$E$6:$E$105,MATCH($C30,PRODUCTOS!$A$6:$A$105,0)),IVA_VENTAS))) | J30: =IF($C30="","",$H30-$I30) | K30: =IF($C30="","",N($E30)*IFERROR(INDEX(PRODUCTOS!$H$6:$H$105,MATCH($C30,PRODUCTOS!$A$6:$A$105,0)),0)) | L30: =IF($C30="","",$J30-$K30) | O30: =IF($A30="","",DATE(YEAR($A30),MONTH($A30),1))
D31: =IF($C31="","",IFERROR(INDEX(PRODUCTOS!$B$6:$B$105,MATCH($C31,PRODUCTOS!$A$6:$A$105,0)),"¿Código?")) | F31: =IF($C31="","",IFERROR(INDEX(PRODUCTOS!$D$6:$D$105,MATCH($C31,PRODUCTOS!$A$6:$A$105,0)),0)) | H31: =IF($C31="","",N($E31)*$F31-N($G31)) | I31: =IF($C31="","",$H31-$H31/(1+IFERROR(INDEX(PRODUCTOS!$E$6:$E$105,MATCH($C31,PRODUCTOS!$A$6:$A$105,0)),IVA_VENTAS))) | J31: =IF($C31="","",$H31-$I31) | K31: =IF($C31="","",N($E31)*IFERROR(INDEX(PRODUCTOS!$H$6:$H$105,MATCH($C31,PRODUCTOS!$A$6:$A$105,0)),0)) | L31: =IF($C31="","",$J31-$K31) | O31: =IF($A31="","",DATE(YEAR($A31),MONTH($A31),1))
... D2005: =IF($C2005="","",IFERROR(INDEX(PRODUCTOS!$B$6:$B$105,MATCH($C2005,PRODUCTOS!$A$6:$A$105,0)),"¿Código?")) | F2005: =IF($C2005="","",IFERROR(INDEX(PRODUCTOS!$D$6:$D$105,MATCH($C2005,PRODUCTOS!$A$6:$A$105,0)),0)) | H2005: =IF($C2005="","",N($E2005)*$F2005-N($G2005)) | I2005: =IF($C2005="","",$H2005-$H2005/(1+IFERROR(INDEX(PRODUCTOS!$E$6:$E$105,MATCH($C2005,PRODUCTOS!$A$6:$A$105,0)),IVA_VENTAS))) | J2005: =IF($C2005="","",$H2005-$I2005) | K2005: =IF($C2005="","",N($E2005)*IFERROR(INDEX(PRODUCTOS!$H$6:$H$105,MATCH($C2005,PRODUCTOS!$A$6:$A$105,0)),0)) | L2005: =IF($C2005="","",$J2005-$K2005) | O2005: =IF($A2005="","",DATE(YEAR($A2005),MONTH($A2005),1))

Sheet MERMAS
A1: MERMAS, CORTESÍAS Y AJUSTES DE INVENTARIO
A2: Cantidad siempre POSITIVA en unidad base. Todo resta del inventario excepto 'Ajuste (+) sobrante'. Use los ajustes para cuadrar con el conteo físico.
A5: Fecha | B5: Código insumo | C5: Insumo | D5: Unidad | E5: Tipo de movimiento | F5: Cantidad (unid. base) | G5: Motivo / detalle | H5: Responsable | I5: Costo por unid. base | J5: Cantidad con signo | K5: Valor (₡, negativo = pérdida) | L5: Mes
A6: 46298 | B6: I001 | C6: =IF($B6="","",IFERROR(INDEX(INSUMOS!$B$6:$B$205,MATCH($B6,INSUMOS!$A$6:$A$205,0)),"¿Código?")) -> Fresas frescas | D6: =IF($B6="","",IFERROR(INDEX(INSUMOS!$D$6:$D$205,MATCH($B6,INSUMOS!$A$6:$A$205,0)),"")) -> g | E6: Merma | F6: 600 | G6: Fresas golpeadas / pasadas | H6: Encargado | I6: =IF($B6="","",IFERROR(INDEX(INSUMOS!$O$6:$O$205,MATCH($B6,INSUMOS!$A$6:$A$205,0)),0)) -> 2.8 | J6: =IF($B6="","",IF($E6="Ajuste (+) sobrante",1,-1)*N($F6)) -> -600 | K6: =IF($B6="","",$J6*$I6) -> -1680 | L6: =IF($A6="","",DATE(YEAR($A6),MONTH($A6),1)) -> 46296
A7: 46299 | B7: I004 | C7: =IF($B7="","",IFERROR(INDEX(INSUMOS!$B$6:$B$205,MATCH($B7,INSUMOS!$A$6:$A$205,0)),"¿Código?")) -> Crema dulce | D7: =IF($B7="","",IFERROR(INDEX(INSUMOS!$D$6:$D$205,MATCH($B7,INSUMOS!$A$6:$A$205,0)),"")) -> ml | E7: Vencimiento | F7: 500 | G7: Caja abierta vencida | H7: Encargado | I7: =IF($B7="","",IFERROR(INDEX(INSUMOS!$O$6:$O$205,MATCH($B7,INSUMOS!$A$6:$A$205,0)),0)) -> 2.55 | J7: =IF($B7="","",IF($E7="Ajuste (+) sobrante",1,-1)*N($F7)) -> -500 | K7: =IF($B7="","",$J7*$I7) -> -1275 | L7: =IF($A7="","",DATE(YEAR($A7),MONTH($A7),1)) -> 46296
C8: =IF($B8="","",IFERROR(INDEX(INSUMOS!$B$6:$B$205,MATCH($B8,INSUMOS!$A$6:$A$205,0)),"¿Código?")) | D8: =IF($B8="","",IFERROR(INDEX(INSUMOS!$D$6:$D$205,MATCH($B8,INSUMOS!$A$6:$A$205,0)),"")) | I8: =IF($B8="","",IFERROR(INDEX(INSUMOS!$O$6:$O$205,MATCH($B8,INSUMOS!$A$6:$A$205,0)),0)) | J8: =IF($B8="","",IF($E8="Ajuste (+) sobrante",1,-1)*N($F8)) | K8: =IF($B8="","",$J8*$I8) | L8: =IF($A8="","",DATE(YEAR($A8),MONTH($A8),1))
C9: =IF($B9="","",IFERROR(INDEX(INSUMOS!$B$6:$B$205,MATCH($B9,INSUMOS!$A$6:$A$205,0)),"¿Código?")) | D9: =IF($B9="","",IFERROR(INDEX(INSUMOS!$D$6:$D$205,MATCH($B9,INSUMOS!$A$6:$A$205,0)),"")) | I9: =IF($B9="","",IFERROR(INDEX(INSUMOS!$O$6:$O$205,MATCH($B9,INSUMOS!$A$6:$A$205,0)),0)) | J9: =IF($B9="","",IF($E9="Ajuste (+) sobrante",1,-1)*N($F9)) | K9: =IF($B9="","",$J9*$I9) | L9: =IF($A9="","",DATE(YEAR($A9),MONTH($A9),1))
C10: =IF($B10="","",IFERROR(INDEX(INSUMOS!$B$6:$B$205,MATCH($B10,INSUMOS!$A$6:$A$205,0)),"¿Código?")) | D10: =IF($B10="","",IFERROR(INDEX(INSUMOS!$D$6:$D$205,MATCH($B10,INSUMOS!$A$6:$A$205,0)),"")) | I10: =IF($B10="","",IFERROR(INDEX(INSUMOS!$O$6:$O$205,MATCH($B10,INSUMOS!$A$6:$A$205,0)),0)) | J10: =IF($B10="","",IF($E10="Ajuste (+) sobrante",1,-1)*N($F10)) | K10: =IF($B10="","",$J10*$I10) | L10: =IF($A10="","",DATE(YEAR($A10),MONTH($A10),1))
C11: =IF($B11="","",IFERROR(INDEX(INSUMOS!$B$6:$B$205,MATCH($B11,INSUMOS!$A$6:$A$205,0)),"¿Código?")) | D11: =IF($B11="","",IFERROR(INDEX(INSUMOS!$D$6:$D$205,MATCH($B11,INSUMOS!$A$6:$A$205,0)),"")) | I11: =IF($B11="","",IFERROR(INDEX(INSUMOS!$O$6:$O$205,MATCH($B11,INSUMOS!$A$6:$A$205,0)),0)) | J11: =IF($B11="","",IF($E11="Ajuste (+) sobrante",1,-1)*N($F11)) | K11: =IF($B11="","",$J11*$I11) | L11: =IF($A11="","",DATE(YEAR($A11),MONTH($A11),1))
C12: =IF($B12="","",IFERROR(INDEX(INSUMOS!$B$6:$B$205,MATCH($B12,INSUMOS!$A$6:$A$205,0)),"¿Código?")) | D12: =IF($B12="","",IFERROR(INDEX(INSUMOS!$D$6:$D$205,MATCH($B12,INSUMOS!$A$6:$A$205,0)),"")) | I12: =IF($B12="","",IFERROR(INDEX(INSUMOS!$O$6:$O$205,MATCH($B12,INSUMOS!$A$6:$A$205,0)),0)) | J12: =IF($B12="","",IF($E12="Ajuste (+) sobrante",1,-1)*N($F12)) | K12: =IF($B12="","",$J12*$I12) | L12: =IF($A12="","",DATE(YEAR($A12),MONTH($A12),1))
C13: =IF($B13="","",IFERROR(INDEX(INSUMOS!$B$6:$B$205,MATCH($B13,INSUMOS!$A$6:$A$205,0)),"¿Código?")) | D13: =IF($B13="","",IFERROR(INDEX(INSUMOS!$D$6:$D$205,MATCH($B13,INSUMOS!$A$6:$A$205,0)),"")) | I13: =IF($B13="","",IFERROR(INDEX(INSUMOS!$O$6:$O$205,MATCH($B13,INSUMOS!$A$6:$A$205,0)),0)) | J13: =IF($B13="","",IF($E13="Ajuste (+) sobrante",1,-1)*N($F13)) | K13: =IF($B13="","",$J13*$I13) | L13: =IF($A13="","",DATE(YEAR($A13),MONTH($A13),1))
C14: =IF($B14="","",IFERROR(INDEX(INSUMOS!$B$6:$B$205,MATCH($B14,INSUMOS!$A$6:$A$205,0)),"¿Código?")) | D14: =IF($B14="","",IFERROR(INDEX(INSUMOS!$D$6:$D$205,MATCH($B14,INSUMOS!$A$6:$A$205,0)),"")) | I14: =IF($B14="","",IFERROR(INDEX(INSUMOS!$O$6:$O$205,MATCH($B14,INSUMOS!$A$6:$A$205,0)),0)) | J14: =IF($B14="","",IF($E14="Ajuste (+) sobrante",1,-1)*N($F14)) | K14: =IF($B14="","",$J14*$I14) | L14: =IF($A14="","",DATE(YEAR($A14),MONTH($A14),1))
C15: =IF($B15="","",IFERROR(INDEX(INSUMOS!$B$6:$B$205,MATCH($B15,INSUMOS!$A$6:$A$205,0)),"¿Código?")) | D15: =IF($B15="","",IFERROR(INDEX(INSUMOS!$D$6:$D$205,MATCH($B15,INSUMOS!$A$6:$A$205,0)),"")) | I15: =IF($B15="","",IFERROR(INDEX(INSUMOS!$O$6:$O$205,MATCH($B15,INSUMOS!$A$6:$A$205,0)),0)) | J15: =IF($B15="","",IF($E15="Ajuste (+) sobrante",1,-1)*N($F15)) | K15: =IF($B15="","",$J15*$I15) | L15: =IF($A15="","",DATE(YEAR($A15),MONTH($A15),1))
C16: =IF($B16="","",IFERROR(INDEX(INSUMOS!$B$6:$B$205,MATCH($B16,INSUMOS!$A$6:$A$205,0)),"¿Código?")) | D16: =IF($B16="","",IFERROR(INDEX(INSUMOS!$D$6:$D$205,MATCH($B16,INSUMOS!$A$6:$A$205,0)),"")) | I16: =IF($B16="","",IFERROR(INDEX(INSUMOS!$O$6:$O$205,MATCH($B16,INSUMOS!$A$6:$A$205,0)),0)) | J16: =IF($B16="","",IF($E16="Ajuste (+) sobrante",1,-1)*N($F16)) | K16: =IF($B16="","",$J16*$I16) | L16: =IF($A16="","",DATE(YEAR($A16),MONTH($A16),1))
C17: =IF($B17="","",IFERROR(INDEX(INSUMOS!$B$6:$B$205,MATCH($B17,INSUMOS!$A$6:$A$205,0)),"¿Código?")) | D17: =IF($B17="","",IFERROR(INDEX(INSUMOS!$D$6:$D$205,MATCH($B17,INSUMOS!$A$6:$A$205,0)),"")) | I17: =IF($B17="","",IFERROR(INDEX(INSUMOS!$O$6:$O$205,MATCH($B17,INSUMOS!$A$6:$A$205,0)),0)) | J17: =IF($B17="","",IF($E17="Ajuste (+) sobrante",1,-1)*N($F17)) | K17: =IF($B17="","",$J17*$I17) | L17: =IF($A17="","",DATE(YEAR($A17),MONTH($A17),1))
C18: =IF($B18="","",IFERROR(INDEX(INSUMOS!$B$6:$B$205,MATCH($B18,INSUMOS!$A$6:$A$205,0)),"¿Código?")) | D18: =IF($B18="","",IFERROR(INDEX(INSUMOS!$D$6:$D$205,MATCH($B18,INSUMOS!$A$6:$A$205,0)),"")) | I18: =IF($B18="","",IFERROR(INDEX(INSUMOS!$O$6:$O$205,MATCH($B18,INSUMOS!$A$6:$A$205,0)),0)) | J18: =IF($B18="","",IF($E18="Ajuste (+) sobrante",1,-1)*N($F18)) | K18: =IF($B18="","",$J18*$I18) | L18: =IF($A18="","",DATE(YEAR($A18),MONTH($A18),1))
C19: =IF($B19="","",IFERROR(INDEX(INSUMOS!$B$6:$B$205,MATCH($B19,INSUMOS!$A$6:$A$205,0)),"¿Código?")) | D19: =IF($B19="","",IFERROR(INDEX(INSUMOS!$D$6:$D$205,MATCH($B19,INSUMOS!$A$6:$A$205,0)),"")) | I19: =IF($B19="","",IFERROR(INDEX(INSUMOS!$O$6:$O$205,MATCH($B19,INSUMOS!$A$6:$A$205,0)),0)) | J19: =IF($B19="","",IF($E19="Ajuste (+) sobrante",1,-1)*N($F19)) | K19: =IF($B19="","",$J19*$I19) | L19: =IF($A19="","",DATE(YEAR($A19),MONTH($A19),1))
... C505: =IF($B505="","",IFERROR(INDEX(INSUMOS!$B$6:$B$205,MATCH($B505,INSUMOS!$A$6:$A$205,0)),"¿Código?")) | D505: =IF($B505="","",IFERROR(INDEX(INSUMOS!$D$6:$D$205,MATCH($B505,INSUMOS!$A$6:$A$205,0)),"")) | I505: =IF($B505="","",IFERROR(INDEX(INSUMOS!$O$6:$O$205,MATCH($B505,INSUMOS!$A$6:$A$205,0)),0)) | J505: =IF($B505="","",IF($E505="Ajuste (+) sobrante",1,-1)*N($F505)) | K505: =IF($B505="","",$J505*$I505) | L505: =IF($A505="","",DATE(YEAR($A505),MONTH($A505),1))

Sheet PLANILLA
A1: PLANILLA MENSUAL Y CARGAS SOCIALES
A2: Una línea por colaborador por mes. Tasas en CONFIG (verifique las vigentes de CCSS e INS). Costo total empresa = bruto + CCSS patronal + INS + provisiones (aguinaldo, vacaciones, cesantía).
H4: Mes del DASHBOARD → | I4: =SUMIFS(I6:I505,S6:S505,MES_REPORTE) -> 1156000 | L4: =SUMIFS(L6:L505,S6:S505,MES_REPORTE) -> 1032654.8 | R4: =SUMIFS(R6:R505,S6:S505,MES_REPORTE) -> 1689725.2
A5: Mes (día 1) | B5: Colaborador | C5: Puesto | D5: Salario base mensual | E5: Horas extra (cantidad) | F5: Valor hora extra | G5: Monto horas extra | H5: Bonos / comisiones / otros | I5: SALARIO BRUTO | J5: CCSS obrera (rebajo) | K5: Otras deducciones (adelantos, renta, embargos) | L5: NETO A PAGAR | M5: CCSS patronal | N5: INS riesgos del trabajo | O5: Provisión aguinaldo | P5: Provisión vacaciones | Q5: Provisión cesantía | R5: COSTO TOTAL EMPRESA | S5: Mes (normalizado)
A6: 46296 | B6: Colaborador 1 | C6: Encargado(a) | D6: 520000 | E6: 8 | F6: =IF($B6="","",N($D6)/HORAS_MES*RECARGO_HE) -> 3250 | G6: =IF($B6="","",N($E6)*$F6) -> 26000 | H6: 0 | I6: =IF($B6="","",N($D6)+$G6+N($H6)) -> 546000 | J6: =IF($B6="","",$I6*CCSS_OBRERO) -> 58258.2 | L6: =IF($B6="","",$I6-$J6-N($K6)) -> 487741.8 | M6: =IF($B6="","",$I6*CCSS_PATRONAL) -> 144690 | N6: =IF($B6="","",$I6*INS_RT) -> 10101 | O6: =IF($B6="","",$I6*PROV_AGUINALDO) -> 45481.8 | P6: =IF($B6="","",$I6*PROV_VACACIONES) -> 22713.6 | Q6: =IF($B6="","",$I6*PROV_CESANTIA) -> 29101.8 | R6: =IF($B6="","",$I6+SUM($M6:$Q6)) -> 798088.2 | S6: =IF(OR($A6="",$B6=""),"",DATE(YEAR($A6),MONTH($A6),1)) -> 46296
A7: 46296 | B7: Colaborador 2 | C7: Dependiente | D7: 400000 | E7: 4 | F7: =IF($B7="","",N($D7)/HORAS_MES*RECARGO_HE) -> 2500 | G7: =IF($B7="","",N($E7)*$F7) -> 10000 | H7: 0 | I7: =IF($B7="","",N($D7)+$G7+N($H7)) -> 410000 | J7: =IF($B7="","",$I7*CCSS_OBRERO) -> 43747 | L7: =IF($B7="","",$I7-$J7-N($K7)) -> 366253 | M7: =IF($B7="","",$I7*CCSS_PATRONAL) -> 108650 | N7: =IF($B7="","",$I7*INS_RT) -> 7585 | O7: =IF($B7="","",$I7*PROV_AGUINALDO) -> 34153 | P7: =IF($B7="","",$I7*PROV_VACACIONES) -> 17056 | Q7: =IF($B7="","",$I7*PROV_CESANTIA) -> 21853 | R7: =IF($B7="","",$I7+SUM($M7:$Q7)) -> 599297 | S7: =IF(OR($A7="",$B7=""),"",DATE(YEAR($A7),MONTH($A7),1)) -> 46296
A8: 46296 | B8: Colaborador 3 | C8: Dependiente medio tiempo | D8: 200000 | E8: 0 | F8: =IF($B8="","",N($D8)/HORAS_MES*RECARGO_HE) -> 1250 | G8: =IF($B8="","",N($E8)*$F8) -> 0 | H8: 0 | I8: =IF($B8="","",N($D8)+$G8+N($H8)) -> 200000 | J8: =IF($B8="","",$I8*CCSS_OBRERO) -> 21340 | L8: =IF($B8="","",$I8-$J8-N($K8)) -> 178660 | M8: =IF($B8="","",$I8*CCSS_PATRONAL) -> 53000 | N8: =IF($B8="","",$I8*INS_RT) -> 3700 | O8: =IF($B8="","",$I8*PROV_AGUINALDO) -> 16660 | P8: =IF($B8="","",$I8*PROV_VACACIONES) -> 8320 | Q8: =IF($B8="","",$I8*PROV_CESANTIA) -> 10660 | R8: =IF($B8="","",$I8+SUM($M8:$Q8)) -> 292340 | S8: =IF(OR($A8="",$B8=""),"",DATE(YEAR($A8),MONTH($A8),1)) -> 46296
F9: =IF($B9="","",N($D9)/HORAS_MES*RECARGO_HE) | G9: =IF($B9="","",N($E9)*$F9) | I9: =IF($B9="","",N($D9)+$G9+N($H9)) | J9: =IF($B9="","",$I9*CCSS_OBRERO) | L9: =IF($B9="","",$I9-$J9-N($K9)) | M9: =IF($B9="","",$I9*CCSS_PATRONAL) | N9: =IF($B9="","",$I9*INS_RT) | O9: =IF($B9="","",$I9*PROV_AGUINALDO) | P9: =IF($B9="","",$I9*PROV_VACACIONES) | Q9: =IF($B9="","",$I9*PROV_CESANTIA) | R9: =IF($B9="","",$I9+SUM($M9:$Q9)) | S9: =IF(OR($A9="",$B9=""),"",DATE(YEAR($A9),MONTH($A9),1))
F10: =IF($B10="","",N($D10)/HORAS_MES*RECARGO_HE) | G10: =IF($B10="","",N($E10)*$F10) | I10: =IF($B10="","",N($D10)+$G10+N($H10)) | J10: =IF($B10="","",$I10*CCSS_OBRERO) | L10: =IF($B10="","",$I10-$J10-N($K10)) | M10: =IF($B10="","",$I10*CCSS_PATRONAL) | N10: =IF($B10="","",$I10*INS_RT) | O10: =IF($B10="","",$I10*PROV_AGUINALDO) | P10: =IF($B10="","",$I10*PROV_VACACIONES) | Q10: =IF($B10="","",$I10*PROV_CESANTIA) | R10: =IF($B10="","",$I10+SUM($M10:$Q10)) | S10: =IF(OR($A10="",$B10=""),"",DATE(YEAR($A10),MONTH($A10),1))
F11: =IF($B11="","",N($D11)/HORAS_MES*RECARGO_HE) | G11: =IF($B11="","",N($E11)*$F11) | I11: =IF($B11="","",N($D11)+$G11+N($H11)) | J11: =IF($B11="","",$I11*CCSS_OBRERO) | L11: =IF($B11="","",$I11-$J11-N($K11)) | M11: =IF($B11="","",$I11*CCSS_PATRONAL) | N11: =IF($B11="","",$I11*INS_RT) | O11: =IF($B11="","",$I11*PROV_AGUINALDO) | P11: =IF($B11="","",$I11*PROV_VACACIONES) | Q11: =IF($B11="","",$I11*PROV_CESANTIA) | R11: =IF($B11="","",$I11+SUM($M11:$Q11)) | S11: =IF(OR($A11="",$B11=""),"",DATE(YEAR($A11),MONTH($A11),1))
F12: =IF($B12="","",N($D12)/HORAS_MES*RECARGO_HE) | G12: =IF($B12="","",N($E12)*$F12) | I12: =IF($B12="","",N($D12)+$G12+N($H12)) | J12: =IF($B12="","",$I12*CCSS_OBRERO) | L12: =IF($B12="","",$I12-$J12-N($K12)) | M12: =IF($B12="","",$I12*CCSS_PATRONAL) | N12: =IF($B12="","",$I12*INS_RT) | O12: =IF($B12="","",$I12*PROV_AGUINALDO) | P12: =IF($B12="","",$I12*PROV_VACACIONES) | Q12: =IF($B12="","",$I12*PROV_CESANTIA) | R12: =IF($B12="","",$I12+SUM($M12:$Q12)) | S12: =IF(OR($A12="",$B12=""),"",DATE(YEAR($A12),MONTH($A12),1))
F13: =IF($B13="","",N($D13)/HORAS_MES*RECARGO_HE) | G13: =IF($B13="","",N($E13)*$F13) | I13: =IF($B13="","",N($D13)+$G13+N($H13)) | J13: =IF($B13="","",$I13*CCSS_OBRERO) | L13: =IF($B13="","",$I13-$J13-N($K13)) | M13: =IF($B13="","",$I13*CCSS_PATRONAL) | N13: =IF($B13="","",$I13*INS_RT) | O13: =IF($B13="","",$I13*PROV_AGUINALDO) | P13: =IF($B13="","",$I13*PROV_VACACIONES) | Q13: =IF($B13="","",$I13*PROV_CESANTIA) | R13: =IF($B13="","",$I13+SUM($M13:$Q13)) | S13: =IF(OR($A13="",$B13=""),"",DATE(YEAR($A13),MONTH($A13),1))
F14: =IF($B14="","",N($D14)/HORAS_MES*RECARGO_HE) | G14: =IF($B14="","",N($E14)*$F14) | I14: =IF($B14="","",N($D14)+$G14+N($H14)) | J14: =IF($B14="","",$I14*CCSS_OBRERO) | L14: =IF($B14="","",$I14-$J14-N($K14)) | M14: =IF($B14="","",$I14*CCSS_PATRONAL) | N14: =IF($B14="","",$I14*INS_RT) | O14: =IF($B14="","",$I14*PROV_AGUINALDO) | P14: =IF($B14="","",$I14*PROV_VACACIONES) | Q14: =IF($B14="","",$I14*PROV_CESANTIA) | R14: =IF($B14="","",$I14+SUM($M14:$Q14)) | S14: =IF(OR($A14="",$B14=""),"",DATE(YEAR($A14),MONTH($A14),1))
F15: =IF($B15="","",N($D15)/HORAS_MES*RECARGO_HE) | G15: =IF($B15="","",N($E15)*$F15) | I15: =IF($B15="","",N($D15)+$G15+N($H15)) | J15: =IF($B15="","",$I15*CCSS_OBRERO) | L15: =IF($B15="","",$I15-$J15-N($K15)) | M15: =IF($B15="","",$I15*CCSS_PATRONAL) | N15: =IF($B15="","",$I15*INS_RT) | O15: =IF($B15="","",$I15*PROV_AGUINALDO) | P15: =IF($B15="","",$I15*PROV_VACACIONES) | Q15: =IF($B15="","",$I15*PROV_CESANTIA) | R15: =IF($B15="","",$I15+SUM($M15:$Q15)) | S15: =IF(OR($A15="",$B15=""),"",DATE(YEAR($A15),MONTH($A15),1))
F16: =IF($B16="","",N($D16)/HORAS_MES*RECARGO_HE) | G16: =IF($B16="","",N($E16)*$F16) | I16: =IF($B16="","",N($D16)+$G16+N($H16)) | J16: =IF($B16="","",$I16*CCSS_OBRERO) | L16: =IF($B16="","",$I16-$J16-N($K16)) | M16: =IF($B16="","",$I16*CCSS_PATRONAL) | N16: =IF($B16="","",$I16*INS_RT) | O16: =IF($B16="","",$I16*PROV_AGUINALDO) | P16: =IF($B16="","",$I16*PROV_VACACIONES) | Q16: =IF($B16="","",$I16*PROV_CESANTIA) | R16: =IF($B16="","",$I16+SUM($M16:$Q16)) | S16: =IF(OR($A16="",$B16=""),"",DATE(YEAR($A16),MONTH($A16),1))
F17: =IF($B17="","",N($D17)/HORAS_MES*RECARGO_HE) | G17: =IF($B17="","",N($E17)*$F17) | I17: =IF($B17="","",N($D17)+$G17+N($H17)) | J17: =IF($B17="","",$I17*CCSS_OBRERO) | L17: =IF($B17="","",$I17-$J17-N($K17)) | M17: =IF($B17="","",$I17*CCSS_PATRONAL) | N17: =IF($B17="","",$I17*INS_RT) | O17: =IF($B17="","",$I17*PROV_AGUINALDO) | P17: =IF($B17="","",$I17*PROV_VACACIONES) | Q17: =IF($B17="","",$I17*PROV_CESANTIA) | R17: =IF($B17="","",$I17+SUM($M17:$Q17)) | S17: =IF(OR($A17="",$B17=""),"",DATE(YEAR($A17),MONTH($A17),1))
F18: =IF($B18="","",N($D18)/HORAS_MES*RECARGO_HE) | G18: =IF($B18="","",N($E18)*$F18) | I18: =IF($B18="","",N($D18)+$G18+N($H18)) | J18: =IF($B18="","",$I18*CCSS_OBRERO) | L18: =IF($B18="","",$I18-$J18-N($K18)) | M18: =IF($B18="","",$I18*CCSS_PATRONAL) | N18: =IF($B18="","",$I18*INS_RT) | O18: =IF($B18="","",$I18*PROV_AGUINALDO) | P18: =IF($B18="","",$I18*PROV_VACACIONES) | Q18: =IF($B18="","",$I18*PROV_CESANTIA) | R18: =IF($B18="","",$I18+SUM($M18:$Q18)) | S18: =IF(OR($A18="",$B18=""),"",DATE(YEAR($A18),MONTH($A18),1))
F19: =IF($B19="","",N($D19)/HORAS_MES*RECARGO_HE) | G19: =IF($B19="","",N($E19)*$F19) | I19: =IF($B19="","",N($D19)+$G19+N($H19)) | J19: =IF($B19="","",$I19*CCSS_OBRERO) | L19: =IF($B19="","",$I19-$J19-N($K19)) | M19: =IF($B19="","",$I19*CCSS_PATRONAL) | N19: =IF($B19="","",$I19*INS_RT) | O19: =IF($B19="","",$I19*PROV_AGUINALDO) | P19: =IF($B19="","",$I19*PROV_VACACIONES) | Q19: =IF($B19="","",$I19*PROV_CESANTIA) | R19: =IF($B19="","",$I19+SUM($M19:$Q19)) | S19: =IF(OR($A19="",$B19=""),"",DATE(YEAR($A19),MONTH($A19),1))
F20: =IF($B20="","",N($D20)/HORAS_MES*RECARGO_HE) | G20: =IF($B20="","",N($E20)*$F20) | I20: =IF($B20="","",N($D20)+$G20+N($H20)) | J20: =IF($B20="","",$I20*CCSS_OBRERO) | L20: =IF($B20="","",$I20-$J20-N($K20)) | M20: =IF($B20="","",$I20*CCSS_PATRONAL) | N20: =IF($B20="","",$I20*INS_RT) | O20: =IF($B20="","",$I20*PROV_AGUINALDO) | P20: =IF($B20="","",$I20*PROV_VACACIONES) | Q20: =IF($B20="","",$I20*PROV_CESANTIA) | R20: =IF($B20="","",$I20+SUM($M20:$Q20)) | S20: =IF(OR($A20="",$B20=""),"",DATE(YEAR($A20),MONTH($A20),1))
... F505: =IF($B505="","",N($D505)/HORAS_MES*RECARGO_HE) | G505: =IF($B505="","",N($E505)*$F505) | I505: =IF($B505="","",N($D505)+$G505+N($H505)) | J505: =IF($B505="","",$I505*CCSS_OBRERO) | L505: =IF($B505="","",$I505-$J505-N($K505)) | M505: =IF($B505="","",$I505*CCSS_PATRONAL) | N505: =IF($B505="","",$I505*INS_RT) | O505: =IF($B505="","",$I505*PROV_AGUINALDO) | P505: =IF($B505="","",$I505*PROV_VACACIONES) | Q505: =IF($B505="","",$I505*PROV_CESANTIA) | R505: =IF($B505="","",$I505+SUM($M505:$Q505)) | S505: =IF(OR($A505="",$B505=""),"",DATE(YEAR($A505),MONTH($A505),1))

Sheet GASTOS
A1: GASTOS OPERATIVOS
A2: Todo gasto que NO sea insumo de receta ni planilla: alquiler, servicios, publicidad, contador, mantenimiento, comisiones, etc.
A5: Fecha | B5: Categoría | C5: Descripción | D5: Proveedor | E5: Fijo / Variable | F5: Monto sin IVA | G5: % IVA | H5: IVA | I5: Total pagado | J5: Medio de pago | K5: Mes
A6: 46296 | B6: Alquiler | C6: Alquiler local octubre | D6: Arrendador | E6: Fijo | F6: 450000 | G6: 0.13 | H6: =IF($B6="","",N($F6)*N($G6)) -> 58500 | I6: =IF($B6="","",N($F6)+$H6) -> 508500 | J6: Transferencia | K6: =IF($A6="","",DATE(YEAR($A6),MONTH($A6),1)) -> 46296
A7: 46300 | B7: Electricidad | C7: Recibo eléctrico | D7: CNFL / ICE | E7: Fijo | F7: 85000 | G7: 0.13 | H7: =IF($B7="","",N($F7)*N($G7)) -> 11050 | I7: =IF($B7="","",N($F7)+$H7) -> 96050 | J7: Transferencia | K7: =IF($A7="","",DATE(YEAR($A7),MONTH($A7),1)) -> 46296
A8: 46300 | B8: Agua | C8: Recibo de agua | D8: AyA | E8: Fijo | F8: 20000 | G8: 0 | H8: =IF($B8="","",N($F8)*N($G8)) -> 0 | I8: =IF($B8="","",N($F8)+$H8) -> 20000 | J8: Transferencia | K8: =IF($A8="","",DATE(YEAR($A8),MONTH($A8),1)) -> 46296
A9: 46301 | B9: Internet y teléfono | C9: Internet + celular WhatsApp | D9: Operador | E9: Fijo | F9: 25000 | G9: 0.13 | H9: =IF($B9="","",N($F9)*N($G9)) -> 3250 | I9: =IF($B9="","",N($F9)+$H9) -> 28250 | J9: Transferencia | K9: =IF($A9="","",DATE(YEAR($A9),MONTH($A9),1)) -> 46296
A10: 46302 | B10: Publicidad y redes | C10: Pauta Instagram / TikTok | D10: Meta | E10: Variable | F10: 40000 | G10: 0.13 | H10: =IF($B10="","",N($F10)*N($G10)) -> 5200 | I10: =IF($B10="","",N($F10)+$H10) -> 45200 | J10: Tarjeta | K10: =IF($A10="","",DATE(YEAR($A10),MONTH($A10),1)) -> 46296
A11: 46305 | B11: Servicios profesionales | C11: Contador mensual | D11: Contador | E11: Fijo | F11: 60000 | G11: 0.13 | H11: =IF($B11="","",N($F11)*N($G11)) -> 7800 | I11: =IF($B11="","",N($F11)+$H11) -> 67800 | J11: Transferencia | K11: =IF($A11="","",DATE(YEAR($A11),MONTH($A11),1)) -> 46296
H12: =IF($B12="","",N($F12)*N($G12)) | I12: =IF($B12="","",N($F12)+$H12) | K12: =IF($A12="","",DATE(YEAR($A12),MONTH($A12),1))
H13: =IF($B13="","",N($F13)*N($G13)) | I13: =IF($B13="","",N($F13)+$H13) | K13: =IF($A13="","",DATE(YEAR($A13),MONTH($A13),1))
H14: =IF($B14="","",N($F14)*N($G14)) | I14: =IF($B14="","",N($F14)+$H14) | K14: =IF($A14="","",DATE(YEAR($A14),MONTH($A14),1))
H15: =IF($B15="","",N($F15)*N($G15)) | I15: =IF($B15="","",N($F15)+$H15) | K15: =IF($A15="","",DATE(YEAR($A15),MONTH($A15),1))
H16: =IF($B16="","",N($F16)*N($G16)) | I16: =IF($B16="","",N($F16)+$H16) | K16: =IF($A16="","",DATE(YEAR($A16),MONTH($A16),1))
H17: =IF($B17="","",N($F17)*N($G17)) | I17: =IF($B17="","",N($F17)+$H17) | K17: =IF($A17="","",DATE(YEAR($A17),MONTH($A17),1))
H18: =IF($B18="","",N($F18)*N($G18)) | I18: =IF($B18="","",N($F18)+$H18) | K18: =IF($A18="","",DATE(YEAR($A18),MONTH($A18),1))
H19: =IF($B19="","",N($F19)*N($G19)) | I19: =IF($B19="","",N($F19)+$H19) | K19: =IF($A19="","",DATE(YEAR($A19),MONTH($A19),1))
H20: =IF($B20="","",N($F20)*N($G20)) | I20: =IF($B20="","",N($F20)+$H20) | K20: =IF($A20="","",DATE(YEAR($A20),MONTH($A20),1))
H21: =IF($B21="","",N($F21)*N($G21)) | I21: =IF($B21="","",N($F21)+$H21) | K21: =IF($A21="","",DATE(YEAR($A21),MONTH($A21),1))
H22: =IF($B22="","",N($F22)*N($G22)) | I22: =IF($B22="","",N($F22)+$H22) | K22: =IF($A22="","",DATE(YEAR($A22),MONTH($A22),1))
H23: =IF($B23="","",N($F23)*N($G23)) | I23: =IF($B23="","",N($F23)+$H23) | K23: =IF($A23="","",DATE(YEAR($A23),MONTH($A23),1))
... H1005: =IF($B1005="","",N($F1005)*N($G1005)) | I1005: =IF($B1005="","",N($F1005)+$H1005) | K1005: =IF($A1005="","",DATE(YEAR($A1005),MONTH($A1005),1))

Sheet CAJA_DIARIA
A1: CIERRE DE CAJA DIARIO
A2: Ventas por medio de pago vienen de VENTAS (misma fecha). Efectivo esperado = fondo + ventas en efectivo − gastos pagados de caja − depósitos/retiros.
A5: Fecha | B5: Responsable | C5: Fondo inicial | D5: Ventas efectivo | E5: Ventas SINPE Móvil | F5: Ventas tarjeta | G5: Otros medios | H5: TOTAL VENTAS DÍA | I5: Gastos pagados de caja | J5: Depósitos / retiros | K5: Efectivo esperado | L5: Efectivo contado | M5: Diferencia | N5: Estado | O5: Observaciones
A6: 46298 | B6: Encargado | C6: 30000 | D6: =IF($A6="","",SUMIFS(VENTAS!$H$6:$H$2005,VENTAS!$A$6:$A$2005,$A6,VENTAS!$M$6:$M$2005,"Efectivo")) -> 50200 | E6: =IF($A6="","",SUMIFS(VENTAS!$H$6:$H$2005,VENTAS!$A$6:$A$2005,$A6,VENTAS!$M$6:$M$2005,"SINPE Móvil")) -> 75950 | F6: =IF($A6="","",SUMIFS(VENTAS!$H$6:$H$2005,VENTAS!$A$6:$A$2005,$A6,VENTAS!$M$6:$M$2005,"Tarjeta")) -> 44550 | G6: =IF($A6="","",SUMIFS(VENTAS!$H$6:$H$2005,VENTAS!$A$6:$A$2005,$A6)-$D6-$E6-$F6) -> 0 | H6: =IF($A6="","",SUM($D6:$G6)) -> 170700 | I6: 5000 | J6: 50000 | K6: =IF($A6="","",N($C6)+$D6-N($I6)-N($J6)) -> 25200 | L6: 24200 | M6: =IF(OR($A6="",$L6=""),"",$L6-$K6) -> -1000 | N6: =IF($A6="","",IF($L6="","PENDIENTE",IF(ABS($M6)<1,"OK",IF($M6<0,"FALTANTE","SOBRANTE")))) -> FALTANTE | O6: Faltan ₡1,000: revisar vuelto
A7: 46299 | B7: Encargado | C7: 30000 | D7: =IF($A7="","",SUMIFS(VENTAS!$H$6:$H$2005,VENTAS!$A$6:$A$2005,$A7,VENTAS!$M$6:$M$2005,"Efectivo")) -> 39450 | E7: =IF($A7="","",SUMIFS(VENTAS!$H$6:$H$2005,VENTAS!$A$6:$A$2005,$A7,VENTAS!$M$6:$M$2005,"SINPE Móvil")) -> 94300 | F7: =IF($A7="","",SUMIFS(VENTAS!$H$6:$H$2005,VENTAS!$A$6:$A$2005,$A7,VENTAS!$M$6:$M$2005,"Tarjeta")) -> 82250 | G7: =IF($A7="","",SUMIFS(VENTAS!$H$6:$H$2005,VENTAS!$A$6:$A$2005,$A7)-$D7-$E7-$F7) -> 0 | H7: =IF($A7="","",SUM($D7:$G7)) -> 216000 | I7: 0 | J7: 60000 | K7: =IF($A7="","",N($C7)+$D7-N($I7)-N($J7)) -> 9450 | M7: =IF(OR($A7="",$L7=""),"",$L7-$K7) | N7: =IF($A7="","",IF($L7="","PENDIENTE",IF(ABS($M7)<1,"OK",IF($M7<0,"FALTANTE","SOBRANTE")))) -> PENDIENTE
D8: =IF($A8="","",SUMIFS(VENTAS!$H$6:$H$2005,VENTAS!$A$6:$A$2005,$A8,VENTAS!$M$6:$M$2005,"Efectivo")) | E8: =IF($A8="","",SUMIFS(VENTAS!$H$6:$H$2005,VENTAS!$A$6:$A$2005,$A8,VENTAS!$M$6:$M$2005,"SINPE Móvil")) | F8: =IF($A8="","",SUMIFS(VENTAS!$H$6:$H$2005,VENTAS!$A$6:$A$2005,$A8,VENTAS!$M$6:$M$2005,"Tarjeta")) | G8: =IF($A8="","",SUMIFS(VENTAS!$H$6:$H$2005,VENTAS!$A$6:$A$2005,$A8)-$D8-$E8-$F8) | H8: =IF($A8="","",SUM($D8:$G8)) | K8: =IF($A8="","",N($C8)+$D8-N($I8)-N($J8)) | M8: =IF(OR($A8="",$L8=""),"",$L8-$K8) | N8: =IF($A8="","",IF($L8="","PENDIENTE",IF(ABS($M8)<1,"OK",IF($M8<0,"FALTANTE","SOBRANTE"))))
D9: =IF($A9="","",SUMIFS(VENTAS!$H$6:$H$2005,VENTAS!$A$6:$A$2005,$A9,VENTAS!$M$6:$M$2005,"Efectivo")) | E9: =IF($A9="","",SUMIFS(VENTAS!$H$6:$H$2005,VENTAS!$A$6:$A$2005,$A9,VENTAS!$M$6:$M$2005,"SINPE Móvil")) | F9: =IF($A9="","",SUMIFS(VENTAS!$H$6:$H$2005,VENTAS!$A$6:$A$2005,$A9,VENTAS!$M$6:$M$2005,"Tarjeta")) | G9: =IF($A9="","",SUMIFS(VENTAS!$H$6:$H$2005,VENTAS!$A$6:$A$2005,$A9)-$D9-$E9-$F9) | H9: =IF($A9="","",SUM($D9:$G9)) | K9: =IF($A9="","",N($C9)+$D9-N($I9)-N($J9)) | M9: =IF(OR($A9="",$L9=""),"",$L9-$K9) | N9: =IF($A9="","",IF($L9="","PENDIENTE",IF(ABS($M9)<1,"OK",IF($M9<0,"FALTANTE","SOBRANTE"))))
D10: =IF($A10="","",SUMIFS(VENTAS!$H$6:$H$2005,VENTAS!$A$6:$A$2005,$A10,VENTAS!$M$6:$M$2005,"Efectivo")) | E10: =IF($A10="","",SUMIFS(VENTAS!$H$6:$H$2005,VENTAS!$A$6:$A$2005,$A10,VENTAS!$M$6:$M$2005,"SINPE Móvil")) | F10: =IF($A10="","",SUMIFS(VENTAS!$H$6:$H$2005,VENTAS!$A$6:$A$2005,$A10,VENTAS!$M$6:$M$2005,"Tarjeta")) | G10: =IF($A10="","",SUMIFS(VENTAS!$H$6:$H$2005,VENTAS!$A$6:$A$2005,$A10)-$D10-$E10-$F10) | H10: =IF($A10="","",SUM($D10:$G10)) | K10: =IF($A10="","",N($C10)+$D10-N($I10)-N($J10)) | M10: =IF(OR($A10="",$L10=""),"",$L10-$K10) | N10: =IF($A10="","",IF($L10="","PENDIENTE",IF(ABS($M10)<1,"OK",IF($M10<0,"FALTANTE","SOBRANTE"))))
D11: =IF($A11="","",SUMIFS(VENTAS!$H$6:$H$2005,VENTAS!$A$6:$A$2005,$A11,VENTAS!$M$6:$M$2005,"Efectivo")) | E11: =IF($A11="","",SUMIFS(VENTAS!$H$6:$H$2005,VENTAS!$A$6:$A$2005,$A11,VENTAS!$M$6:$M$2005,"SINPE Móvil")) | F11: =IF($A11="","",SUMIFS(VENTAS!$H$6:$H$2005,VENTAS!$A$6:$A$2005,$A11,VENTAS!$M$6:$M$2005,"Tarjeta")) | G11: =IF($A11="","",SUMIFS(VENTAS!$H$6:$H$2005,VENTAS!$A$6:$A$2005,$A11)-$D11-$E11-$F11) | H11: =IF($A11="","",SUM($D11:$G11)) | K11: =IF($A11="","",N($C11)+$D11-N($I11)-N($J11)) | M11: =IF(OR($A11="",$L11=""),"",$L11-$K11) | N11: =IF($A11="","",IF($L11="","PENDIENTE",IF(ABS($M11)<1,"OK",IF($M11<0,"FALTANTE","SOBRANTE"))))
D12: =IF($A12="","",SUMIFS(VENTAS!$H$6:$H$2005,VENTAS!$A$6:$A$2005,$A12,VENTAS!$M$6:$M$2005,"Efectivo")) | E12: =IF($A12="","",SUMIFS(VENTAS!$H$6:$H$2005,VENTAS!$A$6:$A$2005,$A12,VENTAS!$M$6:$M$2005,"SINPE Móvil")) | F12: =IF($A12="","",SUMIFS(VENTAS!$H$6:$H$2005,VENTAS!$A$6:$A$2005,$A12,VENTAS!$M$6:$M$2005,"Tarjeta")) | G12: =IF($A12="","",SUMIFS(VENTAS!$H$6:$H$2005,VENTAS!$A$6:$A$2005,$A12)-$D12-$E12-$F12) | H12: =IF($A12="","",SUM($D12:$G12)) | K12: =IF($A12="","",N($C12)+$D12-N($I12)-N($J12)) | M12: =IF(OR($A12="",$L12=""),"",$L12-$K12) | N12: =IF($A12="","",IF($L12="","PENDIENTE",IF(ABS($M12)<1,"OK",IF($M12<0,"FALTANTE","SOBRANTE"))))
D13: =IF($A13="","",SUMIFS(VENTAS!$H$6:$H$2005,VENTAS!$A$6:$A$2005,$A13,VENTAS!$M$6:$M$2005,"Efectivo")) | E13: =IF($A13="","",SUMIFS(VENTAS!$H$6:$H$2005,VENTAS!$A$6:$A$2005,$A13,VENTAS!$M$6:$M$2005,"SINPE Móvil")) | F13: =IF($A13="","",SUMIFS(VENTAS!$H$6:$H$2005,VENTAS!$A$6:$A$2005,$A13,VENTAS!$M$6:$M$2005,"Tarjeta")) | G13: =IF($A13="","",SUMIFS(VENTAS!$H$6:$H$2005,VENTAS!$A$6:$A$2005,$A13)-$D13-$E13-$F13) | H13: =IF($A13="","",SUM($D13:$G13)) | K13: =IF($A13="","",N($C13)+$D13-N($I13)-N($J13)) | M13: =IF(OR($A13="",$L13=""),"",$L13-$K13) | N13: =IF($A13="","",IF($L13="","PENDIENTE",IF(ABS($M13)<1,"OK",IF($M13<0,"FALTANTE","SOBRANTE"))))
D14: =IF($A14="","",SUMIFS(VENTAS!$H$6:$H$2005,VENTAS!$A$6:$A$2005,$A14,VENTAS!$M$6:$M$2005,"Efectivo")) | E14: =IF($A14="","",SUMIFS(VENTAS!$H$6:$H$2005,VENTAS!$A$6:$A$2005,$A14,VENTAS!$M$6:$M$2005,"SINPE Móvil")) | F14: =IF($A14="","",SUMIFS(VENTAS!$H$6:$H$2005,VENTAS!$A$6:$A$2005,$A14,VENTAS!$M$6:$M$2005,"Tarjeta")) | G14: =IF($A14="","",SUMIFS(VENTAS!$H$6:$H$2005,VENTAS!$A$6:$A$2005,$A14)-$D14-$E14-$F14) | H14: =IF($A14="","",SUM($D14:$G14)) | K14: =IF($A14="","",N($C14)+$D14-N($I14)-N($J14)) | M14: =IF(OR($A14="",$L14=""),"",$L14-$K14) | N14: =IF($A14="","",IF($L14="","PENDIENTE",IF(ABS($M14)<1,"OK",IF($M14<0,"FALTANTE","SOBRANTE"))))
D15: =IF($A15="","",SUMIFS(VENTAS!$H$6:$H$2005,VENTAS!$A$6:$A$2005,$A15,VENTAS!$M$6:$M$2005,"Efectivo")) | E15: =IF($A15="","",SUMIFS(VENTAS!$H$6:$H$2005,VENTAS!$A$6:$A$2005,$A15,VENTAS!$M$6:$M$2005,"SINPE Móvil")) | F15: =IF($A15="","",SUMIFS(VENTAS!$H$6:$H$2005,VENTAS!$A$6:$A$2005,$A15,VENTAS!$M$6:$M$2005,"Tarjeta")) | G15: =IF($A15="","",SUMIFS(VENTAS!$H$6:$H$2005,VENTAS!$A$6:$A$2005,$A15)-$D15-$E15-$F15) | H15: =IF($A15="","",SUM($D15:$G15)) | K15: =IF($A15="","",N($C15)+$D15-N($I15)-N($J15)) | M15: =IF(OR($A15="",$L15=""),"",$L15-$K15) | N15: =IF($A15="","",IF($L15="","PENDIENTE",IF(ABS($M15)<1,"OK",IF($M15<0,"FALTANTE","SOBRANTE"))))
D16: =IF($A16="","",SUMIFS(VENTAS!$H$6:$H$2005,VENTAS!$A$6:$A$2005,$A16,VENTAS!$M$6:$M$2005,"Efectivo")) | E16: =IF($A16="","",SUMIFS(VENTAS!$H$6:$H$2005,VENTAS!$A$6:$A$2005,$A16,VENTAS!$M$6:$M$2005,"SINPE Móvil")) | F16: =IF($A16="","",SUMIFS(VENTAS!$H$6:$H$2005,VENTAS!$A$6:$A$2005,$A16,VENTAS!$M$6:$M$2005,"Tarjeta")) | G16: =IF($A16="","",SUMIFS(VENTAS!$H$6:$H$2005,VENTAS!$A$6:$A$2005,$A16)-$D16-$E16-$F16) | H16: =IF($A16="","",SUM($D16:$G16)) | K16: =IF($A16="","",N($C16)+$D16-N($I16)-N($J16)) | M16: =IF(OR($A16="",$L16=""),"",$L16-$K16) | N16: =IF($A16="","",IF($L16="","PENDIENTE",IF(ABS($M16)<1,"OK",IF($M16<0,"FALTANTE","SOBRANTE"))))
D17: =IF($A17="","",SUMIFS(VENTAS!$H$6:$H$2005,VENTAS!$A$6:$A$2005,$A17,VENTAS!$M$6:$M$2005,"Efectivo")) | E17: =IF($A17="","",SUMIFS(VENTAS!$H$6:$H$2005,VENTAS!$A$6:$A$2005,$A17,VENTAS!$M$6:$M$2005,"SINPE Móvil")) | F17: =IF($A17="","",SUMIFS(VENTAS!$H$6:$H$2005,VENTAS!$A$6:$A$2005,$A17,VENTAS!$M$6:$M$2005,"Tarjeta")) | G17: =IF($A17="","",SUMIFS(VENTAS!$H$6:$H$2005,VENTAS!$A$6:$A$2005,$A17)-$D17-$E17-$F17) | H17: =IF($A17="","",SUM($D17:$G17)) | K17: =IF($A17="","",N($C17)+$D17-N($I17)-N($J17)) | M17: =IF(OR($A17="",$L17=""),"",$L17-$K17) | N17: =IF($A17="","",IF($L17="","PENDIENTE",IF(ABS($M17)<1,"OK",IF($M17<0,"FALTANTE","SOBRANTE"))))
D18: =IF($A18="","",SUMIFS(VENTAS!$H$6:$H$2005,VENTAS!$A$6:$A$2005,$A18,VENTAS!$M$6:$M$2005,"Efectivo")) | E18: =IF($A18="","",SUMIFS(VENTAS!$H$6:$H$2005,VENTAS!$A$6:$A$2005,$A18,VENTAS!$M$6:$M$2005,"SINPE Móvil")) | F18: =IF($A18="","",SUMIFS(VENTAS!$H$6:$H$2005,VENTAS!$A$6:$A$2005,$A18,VENTAS!$M$6:$M$2005,"Tarjeta")) | G18: =IF($A18="","",SUMIFS(VENTAS!$H$6:$H$2005,VENTAS!$A$6:$A$2005,$A18)-$D18-$E18-$F18) | H18: =IF($A18="","",SUM($D18:$G18)) | K18: =IF($A18="","",N($C18)+$D18-N($I18)-N($J18)) | M18: =IF(OR($A18="",$L18=""),"",$L18-$K18) | N18: =IF($A18="","",IF($L18="","PENDIENTE",IF(ABS($M18)<1,"OK",IF($M18<0,"FALTANTE","SOBRANTE"))))
D19: =IF($A19="","",SUMIFS(VENTAS!$H$6:$H$2005,VENTAS!$A$6:$A$2005,$A19,VENTAS!$M$6:$M$2005,"Efectivo")) | E19: =IF($A19="","",SUMIFS(VENTAS!$H$6:$H$2005,VENTAS!$A$6:$A$2005,$A19,VENTAS!$M$6:$M$2005,"SINPE Móvil")) | F19: =IF($A19="","",SUMIFS(VENTAS!$H$6:$H$2005,VENTAS!$A$6:$A$2005,$A19,VENTAS!$M$6:$M$2005,"Tarjeta")) | G19: =IF($A19="","",SUMIFS(VENTAS!$H$6:$H$2005,VENTAS!$A$6:$A$2005,$A19)-$D19-$E19-$F19) | H19: =IF($A19="","",SUM($D19:$G19)) | K19: =IF($A19="","",N($C19)+$D19-N($I19)-N($J19)) | M19: =IF(OR($A19="",$L19=""),"",$L19-$K19) | N19: =IF($A19="","",IF($L19="","PENDIENTE",IF(ABS($M19)<1,"OK",IF($M19<0,"FALTANTE","SOBRANTE"))))
... D405: =IF($A405="","",SUMIFS(VENTAS!$H$6:$H$2005,VENTAS!$A$6:$A$2005,$A405,VENTAS!$M$6:$M$2005,"Efectivo")) | E405: =IF($A405="","",SUMIFS(VENTAS!$H$6:$H$2005,VENTAS!$A$6:$A$2005,$A405,VENTAS!$M$6:$M$2005,"SINPE Móvil")) | F405: =IF($A405="","",SUMIFS(VENTAS!$H$6:$H$2005,VENTAS!$A$6:$A$2005,$A405,VENTAS!$M$6:$M$2005,"Tarjeta")) | G405: =IF($A405="","",SUMIFS(VENTAS!$H$6:$H$2005,VENTAS!$A$6:$A$2005,$A405)-$D405-$E405-$F405) | H405: =IF($A405="","",SUM($D405:$G405)) | K405: =IF($A405="","",N($C405)+$D405-N($I405)-N($J405)) | M405: =IF(OR($A405="",$L405=""),"",$L405-$K405) | N405: =IF($A405="","",IF($L405="","PENDIENTE",IF(ABS($M405)<1,"OK",IF($M405<0,"FALTANTE","SOBRANTE"))))

Sheet ESTADO_RESULTADOS
A1: ESTADO DE RESULTADOS MENSUAL (REAL)
A2: Automático a partir de VENTAS, MERMAS, PLANILLA, GASTOS y COMPRAS. Costo de ventas = costo teórico de receta de lo vendido.
B4: ="Negocio: "&NEGOCIO&" · Año "&ANIO -> Negocio: La Cremería · Año 2026
B5: Concepto (₡) | C5: =DATE(ANIO,1,1) -> 46023 | D5: =DATE(ANIO,2,1) -> 46054 | E5: =DATE(ANIO,3,1) -> 46082 | F5: =DATE(ANIO,4,1) -> 46113 | G5: =DATE(ANIO,5,1) -> 46143 | H5: =DATE(ANIO,6,1) -> 46174 | I5: =DATE(ANIO,7,1) -> 46204 | J5: =DATE(ANIO,8,1) -> 46235 | K5: =DATE(ANIO,9,1) -> 46266 | L5: =DATE(ANIO,10,1) -> 46296 | M5: =DATE(ANIO,11,1) -> 46327 | N5: =DATE(ANIO,12,1) -> 46357 | O5: TOTAL AÑO
B6: INGRESOS
B7: Ventas brutas (con IVA) | C7: =SUMIFS(VENTAS!$H$6:$H$2005,VENTAS!$O$6:$O$2005,C$5) -> 0 | D7: =SUMIFS(VENTAS!$H$6:$H$2005,VENTAS!$O$6:$O$2005,D$5) -> 0 | E7: =SUMIFS(VENTAS!$H$6:$H$2005,VENTAS!$O$6:$O$2005,E$5) -> 0 | F7: =SUMIFS(VENTAS!$H$6:$H$2005,VENTAS!$O$6:$O$2005,F$5) -> 0 | G7: =SUMIFS(VENTAS!$H$6:$H$2005,VENTAS!$O$6:$O$2005,G$5) -> 0 | H7: =SUMIFS(VENTAS!$H$6:$H$2005,VENTAS!$O$6:$O$2005,H$5) -> 0 | I7: =SUMIFS(VENTAS!$H$6:$H$2005,VENTAS!$O$6:$O$2005,I$5) -> 0 | J7: =SUMIFS(VENTAS!$H$6:$H$2005,VENTAS!$O$6:$O$2005,J$5) -> 0 | ... N7: =SUMIFS(VENTAS!$H$6:$H$2005,VENTAS!$O$6:$O$2005,N$5) -> 0 | O7: =SUM(C7:N7) -> 386700
B8: (−) IVA cobrado | C8: =SUMIFS(VENTAS!$I$6:$I$2005,VENTAS!$O$6:$O$2005,C$5) -> 0 | D8: =SUMIFS(VENTAS!$I$6:$I$2005,VENTAS!$O$6:$O$2005,D$5) -> 0 | E8: =SUMIFS(VENTAS!$I$6:$I$2005,VENTAS!$O$6:$O$2005,E$5) -> 0 | F8: =SUMIFS(VENTAS!$I$6:$I$2005,VENTAS!$O$6:$O$2005,F$5) -> 0 | G8: =SUMIFS(VENTAS!$I$6:$I$2005,VENTAS!$O$6:$O$2005,G$5) -> 0 | H8: =SUMIFS(VENTAS!$I$6:$I$2005,VENTAS!$O$6:$O$2005,H$5) -> 0 | I8: =SUMIFS(VENTAS!$I$6:$I$2005,VENTAS!$O$6:$O$2005,I$5) -> 0 | J8: =SUMIFS(VENTAS!$I$6:$I$2005,VENTAS!$O$6:$O$2005,J$5) -> 0 | ... N8: =SUMIFS(VENTAS!$I$6:$I$2005,VENTAS!$O$6:$O$2005,N$5) -> 0 | O8: =SUM(C8:N8) -> 44487.611
B9: VENTAS NETAS | C9: =SUMIFS(VENTAS!$J$6:$J$2005,VENTAS!$O$6:$O$2005,C$5) -> 0 | D9: =SUMIFS(VENTAS!$J$6:$J$2005,VENTAS!$O$6:$O$2005,D$5) -> 0 | E9: =SUMIFS(VENTAS!$J$6:$J$2005,VENTAS!$O$6:$O$2005,E$5) -> 0 | F9: =SUMIFS(VENTAS!$J$6:$J$2005,VENTAS!$O$6:$O$2005,F$5) -> 0 | G9: =SUMIFS(VENTAS!$J$6:$J$2005,VENTAS!$O$6:$O$2005,G$5) -> 0 | H9: =SUMIFS(VENTAS!$J$6:$J$2005,VENTAS!$O$6:$O$2005,H$5) -> 0 | I9: =SUMIFS(VENTAS!$J$6:$J$2005,VENTAS!$O$6:$O$2005,I$5) -> 0 | J9: =SUMIFS(VENTAS!$J$6:$J$2005,VENTAS!$O$6:$O$2005,J$5) -> 0 | ... N9: =SUMIFS(VENTAS!$J$6:$J$2005,VENTAS!$O$6:$O$2005,N$5) -> 0 | O9: =SUM(C9:N9) -> 342212.39
B10: (−) Costo de ventas (recetas) | C10: =SUMIFS(VENTAS!$K$6:$K$2005,VENTAS!$O$6:$O$2005,C$5) -> 0 | D10: =SUMIFS(VENTAS!$K$6:$K$2005,VENTAS!$O$6:$O$2005,D$5) -> 0 | E10: =SUMIFS(VENTAS!$K$6:$K$2005,VENTAS!$O$6:$O$2005,E$5) -> 0 | F10: =SUMIFS(VENTAS!$K$6:$K$2005,VENTAS!$O$6:$O$2005,F$5) -> 0 | G10: =SUMIFS(VENTAS!$K$6:$K$2005,VENTAS!$O$6:$O$2005,G$5) -> 0 | H10: =SUMIFS(VENTAS!$K$6:$K$2005,VENTAS!$O$6:$O$2005,H$5) -> 0 | I10: =SUMIFS(VENTAS!$K$6:$K$2005,VENTAS!$O$6:$O$2005,I$5) -> 0 | J10: =SUMIFS(VENTAS!$K$6:$K$2005,VENTAS!$O$6:$O$2005,J$5) -> 0 | ... N10: =SUMIFS(VENTAS!$K$6:$K$2005,VENTAS!$O$6:$O$2005,N$5) -> 0 | O10: =SUM(C10:N10) -> 120605.7
B11: UTILIDAD BRUTA (contribución) | C11: =C9-C10 -> 0 | D11: =D9-D10 -> 0 | E11: =E9-E10 -> 0 | F11: =F9-F10 -> 0 | G11: =G9-G10 -> 0 | H11: =H9-H10 -> 0 | I11: =I9-I10 -> 0 | J11: =J9-J10 -> 0 | ... N11: =N9-N10 -> 0 | O11: =SUM(C11:N11) -> 221606.69
B12: Margen bruto % | C12: =IFERROR(C11/C9,0) -> 0 | D12: =IFERROR(D11/D9,0) -> 0 | E12: =IFERROR(E11/E9,0) -> 0 | F12: =IFERROR(F11/F9,0) -> 0 | G12: =IFERROR(G11/G9,0) -> 0 | H12: =IFERROR(H11/H9,0) -> 0 | I12: =IFERROR(I11/I9,0) -> 0 | J12: =IFERROR(J11/J9,0) -> 0 | ... O12: =IFERROR(O11/O9,0) -> 0.64757062
B13: GASTOS DE OPERACIÓN
B14: Mermas y ajustes de inventario | C14: =-SUMIFS(MERMAS!$K$6:$K$505,MERMAS!$L$6:$L$505,C$5) -> 0 | D14: =-SUMIFS(MERMAS!$K$6:$K$505,MERMAS!$L$6:$L$505,D$5) -> 0 | E14: =-SUMIFS(MERMAS!$K$6:$K$505,MERMAS!$L$6:$L$505,E$5) -> 0 | F14: =-SUMIFS(MERMAS!$K$6:$K$505,MERMAS!$L$6:$L$505,F$5) -> 0 | G14: =-SUMIFS(MERMAS!$K$6:$K$505,MERMAS!$L$6:$L$505,G$5) -> 0 | H14: =-SUMIFS(MERMAS!$K$6:$K$505,MERMAS!$L$6:$L$505,H$5) -> 0 | I14: =-SUMIFS(MERMAS!$K$6:$K$505,MERMAS!$L$6:$L$505,I$5) -> 0 | J14: =-SUMIFS(MERMAS!$K$6:$K$505,MERMAS!$L$6:$L$505,J$5) -> 0 | ... N14: =-SUMIFS(MERMAS!$K$6:$K$505,MERMAS!$L$6:$L$505,N$5) -> 0 | O14: =SUM(C14:N14) -> 2955
B15: Planilla (costo total empresa) | C15: =SUMIFS(PLANILLA!$R$6:$R$505,PLANILLA!$S$6:$S$505,C$5) -> 0 | D15: =SUMIFS(PLANILLA!$R$6:$R$505,PLANILLA!$S$6:$S$505,D$5) -> 0 | E15: =SUMIFS(PLANILLA!$R$6:$R$505,PLANILLA!$S$6:$S$505,E$5) -> 0 | F15: =SUMIFS(PLANILLA!$R$6:$R$505,PLANILLA!$S$6:$S$505,F$5) -> 0 | G15: =SUMIFS(PLANILLA!$R$6:$R$505,PLANILLA!$S$6:$S$505,G$5) -> 0 | H15: =SUMIFS(PLANILLA!$R$6:$R$505,PLANILLA!$S$6:$S$505,H$5) -> 0 | I15: =SUMIFS(PLANILLA!$R$6:$R$505,PLANILLA!$S$6:$S$505,I$5) -> 0 | J15: =SUMIFS(PLANILLA!$R$6:$R$505,PLANILLA!$S$6:$S$505,J$5) -> 0 | ... N15: =SUMIFS(PLANILLA!$R$6:$R$505,PLANILLA!$S$6:$S$505,N$5) -> 0 | O15: =SUM(C15:N15) -> 1689725.2
B16: =CONFIG!$H$6 -> Alquiler | C16: =IF(CONFIG!$H$6="",0,SUMIFS(GASTOS!$F$6:$F$1005,GASTOS!$K$6:$K$1005,C$5,GASTOS!$B$6:$B$1005,CONFIG!$H$6)) -> 0 | D16: =IF(CONFIG!$H$6="",0,SUMIFS(GASTOS!$F$6:$F$1005,GASTOS!$K$6:$K$1005,D$5,GASTOS!$B$6:$B$1005,CONFIG!$H$6)) -> 0 | E16: =IF(CONFIG!$H$6="",0,SUMIFS(GASTOS!$F$6:$F$1005,GASTOS!$K$6:$K$1005,E$5,GASTOS!$B$6:$B$1005,CONFIG!$H$6)) -> 0 | F16: =IF(CONFIG!$H$6="",0,SUMIFS(GASTOS!$F$6:$F$1005,GASTOS!$K$6:$K$1005,F$5,GASTOS!$B$6:$B$1005,CONFIG!$H$6)) -> 0 | G16: =IF(CONFIG!$H$6="",0,SUMIFS(GASTOS!$F$6:$F$1005,GASTOS!$K$6:$K$1005,G$5,GASTOS!$B$6:$B$1005,CONFIG!$H$6)) -> 0 | H16: =IF(CONFIG!$H$6="",0,SUMIFS(GASTOS!$F$6:$F$1005,GASTOS!$K$6:$K$1005,H$5,GASTOS!$B$6:$B$1005,CONFIG!$H$6)) -> 0 | I16: =IF(CONFIG!$H$6="",0,SUMIFS(GASTOS!$F$6:$F$1005,GASTOS!$K$6:$K$1005,I$5,GASTOS!$B$6:$B$1005,CONFIG!$H$6)) -> 0 | J16: =IF(CONFIG!$H$6="",0,SUMIFS(GASTOS!$F$6:$F$1005,GASTOS!$K$6:$K$1005,J$5,GASTOS!$B$6:$B$1005,CONFIG!$H$6)) -> 0 | ... N16: =IF(CONFIG!$H$6="",0,SUMIFS(GASTOS!$F$6:$F$1005,GASTOS!$K$6:$K$1005,N$5,GASTOS!$B$6:$B$1005,CONFIG!$H$6)) -> 0 | O16: =SUM(C16:N16) -> 450000
B17: =CONFIG!$H$7 -> Electricidad | C17: =IF(CONFIG!$H$7="",0,SUMIFS(GASTOS!$F$6:$F$1005,GASTOS!$K$6:$K$1005,C$5,GASTOS!$B$6:$B$1005,CONFIG!$H$7)) -> 0 | D17: =IF(CONFIG!$H$7="",0,SUMIFS(GASTOS!$F$6:$F$1005,GASTOS!$K$6:$K$1005,D$5,GASTOS!$B$6:$B$1005,CONFIG!$H$7)) -> 0 | E17: =IF(CONFIG!$H$7="",0,SUMIFS(GASTOS!$F$6:$F$1005,GASTOS!$K$6:$K$1005,E$5,GASTOS!$B$6:$B$1005,CONFIG!$H$7)) -> 0 | F17: =IF(CONFIG!$H$7="",0,SUMIFS(GASTOS!$F$6:$F$1005,GASTOS!$K$6:$K$1005,F$5,GASTOS!$B$6:$B$1005,CONFIG!$H$7)) -> 0 | G17: =IF(CONFIG!$H$7="",0,SUMIFS(GASTOS!$F$6:$F$1005,GASTOS!$K$6:$K$1005,G$5,GASTOS!$B$6:$B$1005,CONFIG!$H$7)) -> 0 | H17: =IF(CONFIG!$H$7="",0,SUMIFS(GASTOS!$F$6:$F$1005,GASTOS!$K$6:$K$1005,H$5,GASTOS!$B$6:$B$1005,CONFIG!$H$7)) -> 0 | I17: =IF(CONFIG!$H$7="",0,SUMIFS(GASTOS!$F$6:$F$1005,GASTOS!$K$6:$K$1005,I$5,GASTOS!$B$6:$B$1005,CONFIG!$H$7)) -> 0 | J17: =IF(CONFIG!$H$7="",0,SUMIFS(GASTOS!$F$6:$F$1005,GASTOS!$K$6:$K$1005,J$5,GASTOS!$B$6:$B$1005,CONFIG!$H$7)) -> 0 | ... N17: =IF(CONFIG!$H$7="",0,SUMIFS(GASTOS!$F$6:$F$1005,GASTOS!$K$6:$K$1005,N$5,GASTOS!$B$6:$B$1005,CONFIG!$H$7)) -> 0 | O17: =SUM(C17:N17) -> 85000
B18: =CONFIG!$H$8 -> Agua | C18: =IF(CONFIG!$H$8="",0,SUMIFS(GASTOS!$F$6:$F$1005,GASTOS!$K$6:$K$1005,C$5,GASTOS!$B$6:$B$1005,CONFIG!$H$8)) -> 0 | D18: =IF(CONFIG!$H$8="",0,SUMIFS(GASTOS!$F$6:$F$1005,GASTOS!$K$6:$K$1005,D$5,GASTOS!$B$6:$B$1005,CONFIG!$H$8)) -> 0 | E18: =IF(CONFIG!$H$8="",0,SUMIFS(GASTOS!$F$6:$F$1005,GASTOS!$K$6:$K$1005,E$5,GASTOS!$B$6:$B$1005,CONFIG!$H$8)) -> 0 | F18: =IF(CONFIG!$H$8="",0,SUMIFS(GASTOS!$F$6:$F$1005,GASTOS!$K$6:$K$1005,F$5,GASTOS!$B$6:$B$1005,CONFIG!$H$8)) -> 0 | G18: =IF(CONFIG!$H$8="",0,SUMIFS(GASTOS!$F$6:$F$1005,GASTOS!$K$6:$K$1005,G$5,GASTOS!$B$6:$B$1005,CONFIG!$H$8)) -> 0 | H18: =IF(CONFIG!$H$8="",0,SUMIFS(GASTOS!$F$6:$F$1005,GASTOS!$K$6:$K$1005,H$5,GASTOS!$B$6:$B$1005,CONFIG!$H$8)) -> 0 | I18: =IF(CONFIG!$H$8="",0,SUMIFS(GASTOS!$F$6:$F$1005,GASTOS!$K$6:$K$1005,I$5,GASTOS!$B$6:$B$1005,CONFIG!$H$8)) -> 0 | J18: =IF(CONFIG!$H$8="",0,SUMIFS(GASTOS!$F$6:$F$1005,GASTOS!$K$6:$K$1005,J$5,GASTOS!$B$6:$B$1005,CONFIG!$H$8)) -> 0 | ... N18: =IF(CONFIG!$H$8="",0,SUMIFS(GASTOS!$F$6:$F$1005,GASTOS!$K$6:$K$1005,N$5,GASTOS!$B$6:$B$1005,CONFIG!$H$8)) -> 0 | O18: =SUM(C18:N18) -> 20000
B19: =CONFIG!$H$9 -> Internet y teléfono | C19: =IF(CONFIG!$H$9="",0,SUMIFS(GASTOS!$F$6:$F$1005,GASTOS!$K$6:$K$1005,C$5,GASTOS!$B$6:$B$1005,CONFIG!$H$9)) -> 0 | D19: =IF(CONFIG!$H$9="",0,SUMIFS(GASTOS!$F$6:$F$1005,GASTOS!$K$6:$K$1005,D$5,GASTOS!$B$6:$B$1005,CONFIG!$H$9)) -> 0 | E19: =IF(CONFIG!$H$9="",0,SUMIFS(GASTOS!$F$6:$F$1005,GASTOS!$K$6:$K$1005,E$5,GASTOS!$B$6:$B$1005,CONFIG!$H$9)) -> 0 | F19: =IF(CONFIG!$H$9="",0,SUMIFS(GASTOS!$F$6:$F$1005,GASTOS!$K$6:$K$1005,F$5,GASTOS!$B$6:$B$1005,CONFIG!$H$9)) -> 0 | G19: =IF(CONFIG!$H$9="",0,SUMIFS(GASTOS!$F$6:$F$1005,GASTOS!$K$6:$K$1005,G$5,GASTOS!$B$6:$B$1005,CONFIG!$H$9)) -> 0 | H19: =IF(CONFIG!$H$9="",0,SUMIFS(GASTOS!$F$6:$F$1005,GASTOS!$K$6:$K$1005,H$5,GASTOS!$B$6:$B$1005,CONFIG!$H$9)) -> 0 | I19: =IF(CONFIG!$H$9="",0,SUMIFS(GASTOS!$F$6:$F$1005,GASTOS!$K$6:$K$1005,I$5,GASTOS!$B$6:$B$1005,CONFIG!$H$9)) -> 0 | J19: =IF(CONFIG!$H$9="",0,SUMIFS(GASTOS!$F$6:$F$1005,GASTOS!$K$6:$K$1005,J$5,GASTOS!$B$6:$B$1005,CONFIG!$H$9)) -> 0 | ... N19: =IF(CONFIG!$H$9="",0,SUMIFS(GASTOS!$F$6:$F$1005,GASTOS!$K$6:$K$1005,N$5,GASTOS!$B$6:$B$1005,CONFIG!$H$9)) -> 0 | O19: =SUM(C19:N19) -> 25000
B20: =CONFIG!$H$10 -> Gas | C20: =IF(CONFIG!$H$10="",0,SUMIFS(GASTOS!$F$6:$F$1005,GASTOS!$K$6:$K$1005,C$5,GASTOS!$B$6:$B$1005,CONFIG!$H$10)) -> 0 | D20: =IF(CONFIG!$H$10="",0,SUMIFS(GASTOS!$F$6:$F$1005,GASTOS!$K$6:$K$1005,D$5,GASTOS!$B$6:$B$1005,CONFIG!$H$10)) -> 0 | E20: =IF(CONFIG!$H$10="",0,SUMIFS(GASTOS!$F$6:$F$1005,GASTOS!$K$6:$K$1005,E$5,GASTOS!$B$6:$B$1005,CONFIG!$H$10)) -> 0 | F20: =IF(CONFIG!$H$10="",0,SUMIFS(GASTOS!$F$6:$F$1005,GASTOS!$K$6:$K$1005,F$5,GASTOS!$B$6:$B$1005,CONFIG!$H$10)) -> 0 | G20: =IF(CONFIG!$H$10="",0,SUMIFS(GASTOS!$F$6:$F$1005,GASTOS!$K$6:$K$1005,G$5,GASTOS!$B$6:$B$1005,CONFIG!$H$10)) -> 0 | H20: =IF(CONFIG!$H$10="",0,SUMIFS(GASTOS!$F$6:$F$1005,GASTOS!$K$6:$K$1005,H$5,GASTOS!$B$6:$B$1005,CONFIG!$H$10)) -> 0 | I20: =IF(CONFIG!$H$10="",0,SUMIFS(GASTOS!$F$6:$F$1005,GASTOS!$K$6:$K$1005,I$5,GASTOS!$B$6:$B$1005,CONFIG!$H$10)) -> 0 | J20: =IF(CONFIG!$H$10="",0,SUMIFS(GASTOS!$F$6:$F$1005,GASTOS!$K$6:$K$1005,J$5,GASTOS!$B$6:$B$1005,CONFIG!$H$10)) -> 0 | ... N20: =IF(CONFIG!$H$10="",0,SUMIFS(GASTOS!$F$6:$F$1005,GASTOS!$K$6:$K$1005,N$5,GASTOS!$B$6:$B$1005,CONFIG!$H$10)) -> 0 | O20: =SUM(C20:N20) -> 0
B21: =CONFIG!$H$11 -> Publicidad y redes | C21: =IF(CONFIG!$H$11="",0,SUMIFS(GASTOS!$F$6:$F$1005,GASTOS!$K$6:$K$1005,C$5,GASTOS!$B$6:$B$1005,CONFIG!$H$11)) -> 0 | D21: =IF(CONFIG!$H$11="",0,SUMIFS(GASTOS!$F$6:$F$1005,GASTOS!$K$6:$K$1005,D$5,GASTOS!$B$6:$B$1005,CONFIG!$H$11)) -> 0 | E21: =IF(CONFIG!$H$11="",0,SUMIFS(GASTOS!$F$6:$F$1005,GASTOS!$K$6:$K$1005,E$5,GASTOS!$B$6:$B$1005,CONFIG!$H$11)) -> 0 | F21: =IF(CONFIG!$H$11="",0,SUMIFS(GASTOS!$F$6:$F$1005,GASTOS!$K$6:$K$1005,F$5,GASTOS!$B$6:$B$1005,CONFIG!$H$11)) -> 0 | G21: =IF(CONFIG!$H$11="",0,SUMIFS(GASTOS!$F$6:$F$1005,GASTOS!$K$6:$K$1005,G$5,GASTOS!$B$6:$B$1005,CONFIG!$H$11)) -> 0 | H21: =IF(CONFIG!$H$11="",0,SUMIFS(GASTOS!$F$6:$F$1005,GASTOS!$K$6:$K$1005,H$5,GASTOS!$B$6:$B$1005,CONFIG!$H$11)) -> 0 | I21: =IF(CONFIG!$H$11="",0,SUMIFS(GASTOS!$F$6:$F$1005,GASTOS!$K$6:$K$1005,I$5,GASTOS!$B$6:$B$1005,CONFIG!$H$11)) -> 0 | J21: =IF(CONFIG!$H$11="",0,SUMIFS(GASTOS!$F$6:$F$1005,GASTOS!$K$6:$K$1005,J$5,GASTOS!$B$6:$B$1005,CONFIG!$H$11)) -> 0 | ... N21: =IF(CONFIG!$H$11="",0,SUMIFS(GASTOS!$F$6:$F$1005,GASTOS!$K$6:$K$1005,N$5,GASTOS!$B$6:$B$1005,CONFIG!$H$11)) -> 0 | O21: =SUM(C21:N21) -> 40000
B22: =CONFIG!$H$12 -> Servicios profesionales | C22: =IF(CONFIG!$H$12="",0,SUMIFS(GASTOS!$F$6:$F$1005,GASTOS!$K$6:$K$1005,C$5,GASTOS!$B$6:$B$1005,CONFIG!$H$12)) -> 0 | D22: =IF(CONFIG!$H$12="",0,SUMIFS(GASTOS!$F$6:$F$1005,GASTOS!$K$6:$K$1005,D$5,GASTOS!$B$6:$B$1005,CONFIG!$H$12)) -> 0 | E22: =IF(CONFIG!$H$12="",0,SUMIFS(GASTOS!$F$6:$F$1005,GASTOS!$K$6:$K$1005,E$5,GASTOS!$B$6:$B$1005,CONFIG!$H$12)) -> 0 | F22: =IF(CONFIG!$H$12="",0,SUMIFS(GASTOS!$F$6:$F$1005,GASTOS!$K$6:$K$1005,F$5,GASTOS!$B$6:$B$1005,CONFIG!$H$12)) -> 0 | G22: =IF(CONFIG!$H$12="",0,SUMIFS(GASTOS!$F$6:$F$1005,GASTOS!$K$6:$K$1005,G$5,GASTOS!$B$6:$B$1005,CONFIG!$H$12)) -> 0 | H22: =IF(CONFIG!$H$12="",0,SUMIFS(GASTOS!$F$6:$F$1005,GASTOS!$K$6:$K$1005,H$5,GASTOS!$B$6:$B$1005,CONFIG!$H$12)) -> 0 | I22: =IF(CONFIG!$H$12="",0,SUMIFS(GASTOS!$F$6:$F$1005,GASTOS!$K$6:$K$1005,I$5,GASTOS!$B$6:$B$1005,CONFIG!$H$12)) -> 0 | J22: =IF(CONFIG!$H$12="",0,SUMIFS(GASTOS!$F$6:$F$1005,GASTOS!$K$6:$K$1005,J$5,GASTOS!$B$6:$B$1005,CONFIG!$H$12)) -> 0 | ... N22: =IF(CONFIG!$H$12="",0,SUMIFS(GASTOS!$F$6:$F$1005,GASTOS!$K$6:$K$1005,N$5,GASTOS!$B$6:$B$1005,CONFIG!$H$12)) -> 0 | O22: =SUM(C22:N22) -> 60000
B23: =CONFIG!$H$13 -> Mantenimiento y reparaciones | C23: =IF(CONFIG!$H$13="",0,SUMIFS(GASTOS!$F$6:$F$1005,GASTOS!$K$6:$K$1005,C$5,GASTOS!$B$6:$B$1005,CONFIG!$H$13)) -> 0 | D23: =IF(CONFIG!$H$13="",0,SUMIFS(GASTOS!$F$6:$F$1005,GASTOS!$K$6:$K$1005,D$5,GASTOS!$B$6:$B$1005,CONFIG!$H$13)) -> 0 | E23: =IF(CONFIG!$H$13="",0,SUMIFS(GASTOS!$F$6:$F$1005,GASTOS!$K$6:$K$1005,E$5,GASTOS!$B$6:$B$1005,CONFIG!$H$13)) -> 0 | F23: =IF(CONFIG!$H$13="",0,SUMIFS(GASTOS!$F$6:$F$1005,GASTOS!$K$6:$K$1005,F$5,GASTOS!$B$6:$B$1005,CONFIG!$H$13)) -> 0 | G23: =IF(CONFIG!$H$13="",0,SUMIFS(GASTOS!$F$6:$F$1005,GASTOS!$K$6:$K$1005,G$5,GASTOS!$B$6:$B$1005,CONFIG!$H$13)) -> 0 | H23: =IF(CONFIG!$H$13="",0,SUMIFS(GASTOS!$F$6:$F$1005,GASTOS!$K$6:$K$1005,H$5,GASTOS!$B$6:$B$1005,CONFIG!$H$13)) -> 0 | I23: =IF(CONFIG!$H$13="",0,SUMIFS(GASTOS!$F$6:$F$1005,GASTOS!$K$6:$K$1005,I$5,GASTOS!$B$6:$B$1005,CONFIG!$H$13)) -> 0 | J23: =IF(CONFIG!$H$13="",0,SUMIFS(GASTOS!$F$6:$F$1005,GASTOS!$K$6:$K$1005,J$5,GASTOS!$B$6:$B$1005,CONFIG!$H$13)) -> 0 | ... N23: =IF(CONFIG!$H$13="",0,SUMIFS(GASTOS!$F$6:$F$1005,GASTOS!$K$6:$K$1005,N$5,GASTOS!$B$6:$B$1005,CONFIG!$H$13)) -> 0 | O23: =SUM(C23:N23) -> 0
B24: =CONFIG!$H$14 -> Limpieza | C24: =IF(CONFIG!$H$14="",0,SUMIFS(GASTOS!$F$6:$F$1005,GASTOS!$K$6:$K$1005,C$5,GASTOS!$B$6:$B$1005,CONFIG!$H$14)) -> 0 | D24: =IF(CONFIG!$H$14="",0,SUMIFS(GASTOS!$F$6:$F$1005,GASTOS!$K$6:$K$1005,D$5,GASTOS!$B$6:$B$1005,CONFIG!$H$14)) -> 0 | E24: =IF(CONFIG!$H$14="",0,SUMIFS(GASTOS!$F$6:$F$1005,GASTOS!$K$6:$K$1005,E$5,GASTOS!$B$6:$B$1005,CONFIG!$H$14)) -> 0 | F24: =IF(CONFIG!$H$14="",0,SUMIFS(GASTOS!$F$6:$F$1005,GASTOS!$K$6:$K$1005,F$5,GASTOS!$B$6:$B$1005,CONFIG!$H$14)) -> 0 | G24: =IF(CONFIG!$H$14="",0,SUMIFS(GASTOS!$F$6:$F$1005,GASTOS!$K$6:$K$1005,G$5,GASTOS!$B$6:$B$1005,CONFIG!$H$14)) -> 0 | H24: =IF(CONFIG!$H$14="",0,SUMIFS(GASTOS!$F$6:$F$1005,GASTOS!$K$6:$K$1005,H$5,GASTOS!$B$6:$B$1005,CONFIG!$H$14)) -> 0 | I24: =IF(CONFIG!$H$14="",0,SUMIFS(GASTOS!$F$6:$F$1005,GASTOS!$K$6:$K$1005,I$5,GASTOS!$B$6:$B$1005,CONFIG!$H$14)) -> 0 | J24: =IF(CONFIG!$H$14="",0,SUMIFS(GASTOS!$F$6:$F$1005,GASTOS!$K$6:$K$1005,J$5,GASTOS!$B$6:$B$1005,CONFIG!$H$14)) -> 0 | ... N24: =IF(CONFIG!$H$14="",0,SUMIFS(GASTOS!$F$6:$F$1005,GASTOS!$K$6:$K$1005,N$5,GASTOS!$B$6:$B$1005,CONFIG!$H$14)) -> 0 | O24: =SUM(C24:N24) -> 0
B25: =CONFIG!$H$15 -> Patentes, permisos y seguros | C25: =IF(CONFIG!$H$15="",0,SUMIFS(GASTOS!$F$6:$F$1005,GASTOS!$K$6:$K$1005,C$5,GASTOS!$B$6:$B$1005,CONFIG!$H$15)) -> 0 | D25: =IF(CONFIG!$H$15="",0,SUMIFS(GASTOS!$F$6:$F$1005,GASTOS!$K$6:$K$1005,D$5,GASTOS!$B$6:$B$1005,CONFIG!$H$15)) -> 0 | E25: =IF(CONFIG!$H$15="",0,SUMIFS(GASTOS!$F$6:$F$1005,GASTOS!$K$6:$K$1005,E$5,GASTOS!$B$6:$B$1005,CONFIG!$H$15)) -> 0 | F25: =IF(CONFIG!$H$15="",0,SUMIFS(GASTOS!$F$6:$F$1005,GASTOS!$K$6:$K$1005,F$5,GASTOS!$B$6:$B$1005,CONFIG!$H$15)) -> 0 | G25: =IF(CONFIG!$H$15="",0,SUMIFS(GASTOS!$F$6:$F$1005,GASTOS!$K$6:$K$1005,G$5,GASTOS!$B$6:$B$1005,CONFIG!$H$15)) -> 0 | H25: =IF(CONFIG!$H$15="",0,SUMIFS(GASTOS!$F$6:$F$1005,GASTOS!$K$6:$K$1005,H$5,GASTOS!$B$6:$B$1005,CONFIG!$H$15)) -> 0 | I25: =IF(CONFIG!$H$15="",0,SUMIFS(GASTOS!$F$6:$F$1005,GASTOS!$K$6:$K$1005,I$5,GASTOS!$B$6:$B$1005,CONFIG!$H$15)) -> 0 | J25: =IF(CONFIG!$H$15="",0,SUMIFS(GASTOS!$F$6:$F$1005,GASTOS!$K$6:$K$1005,J$5,GASTOS!$B$6:$B$1005,CONFIG!$H$15)) -> 0 | ... N25: =IF(CONFIG!$H$15="",0,SUMIFS(GASTOS!$F$6:$F$1005,GASTOS!$K$6:$K$1005,N$5,GASTOS!$B$6:$B$1005,CONFIG!$H$15)) -> 0 | O25: =SUM(C25:N25) -> 0
B26: =CONFIG!$H$16 -> Comisiones tarjetas/plataformas | C26: =IF(CONFIG!$H$16="",0,SUMIFS(GASTOS!$F$6:$F$1005,GASTOS!$K$6:$K$1005,C$5,GASTOS!$B$6:$B$1005,CONFIG!$H$16)) -> 0 | D26: =IF(CONFIG!$H$16="",0,SUMIFS(GASTOS!$F$6:$F$1005,GASTOS!$K$6:$K$1005,D$5,GASTOS!$B$6:$B$1005,CONFIG!$H$16)) -> 0 | E26: =IF(CONFIG!$H$16="",0,SUMIFS(GASTOS!$F$6:$F$1005,GASTOS!$K$6:$K$1005,E$5,GASTOS!$B$6:$B$1005,CONFIG!$H$16)) -> 0 | F26: =IF(CONFIG!$H$16="",0,SUMIFS(GASTOS!$F$6:$F$1005,GASTOS!$K$6:$K$1005,F$5,GASTOS!$B$6:$B$1005,CONFIG!$H$16)) -> 0 | G26: =IF(CONFIG!$H$16="",0,SUMIFS(GASTOS!$F$6:$F$1005,GASTOS!$K$6:$K$1005,G$5,GASTOS!$B$6:$B$1005,CONFIG!$H$16)) -> 0 | H26: =IF(CONFIG!$H$16="",0,SUMIFS(GASTOS!$F$6:$F$1005,GASTOS!$K$6:$K$1005,H$5,GASTOS!$B$6:$B$1005,CONFIG!$H$16)) -> 0 | I26: =IF(CONFIG!$H$16="",0,SUMIFS(GASTOS!$F$6:$F$1005,GASTOS!$K$6:$K$1005,I$5,GASTOS!$B$6:$B$1005,CONFIG!$H$16)) -> 0 | J26: =IF(CONFIG!$H$16="",0,SUMIFS(GASTOS!$F$6:$F$1005,GASTOS!$K$6:$K$1005,J$5,GASTOS!$B$6:$B$1005,CONFIG!$H$16)) -> 0 | ... N26: =IF(CONFIG!$H$16="",0,SUMIFS(GASTOS!$F$6:$F$1005,GASTOS!$K$6:$K$1005,N$5,GASTOS!$B$6:$B$1005,CONFIG!$H$16)) -> 0 | O26: =SUM(C26:N26) -> 0
B27: =CONFIG!$H$17 -> Transporte y combustible | C27: =IF(CONFIG!$H$17="",0,SUMIFS(GASTOS!$F$6:$F$1005,GASTOS!$K$6:$K$1005,C$5,GASTOS!$B$6:$B$1005,CONFIG!$H$17)) -> 0 | D27: =IF(CONFIG!$H$17="",0,SUMIFS(GASTOS!$F$6:$F$1005,GASTOS!$K$6:$K$1005,D$5,GASTOS!$B$6:$B$1005,CONFIG!$H$17)) -> 0 | E27: =IF(CONFIG!$H$17="",0,SUMIFS(GASTOS!$F$6:$F$1005,GASTOS!$K$6:$K$1005,E$5,GASTOS!$B$6:$B$1005,CONFIG!$H$17)) -> 0 | F27: =IF(CONFIG!$H$17="",0,SUMIFS(GASTOS!$F$6:$F$1005,GASTOS!$K$6:$K$1005,F$5,GASTOS!$B$6:$B$1005,CONFIG!$H$17)) -> 0 | G27: =IF(CONFIG!$H$17="",0,SUMIFS(GASTOS!$F$6:$F$1005,GASTOS!$K$6:$K$1005,G$5,GASTOS!$B$6:$B$1005,CONFIG!$H$17)) -> 0 | H27: =IF(CONFIG!$H$17="",0,SUMIFS(GASTOS!$F$6:$F$1005,GASTOS!$K$6:$K$1005,H$5,GASTOS!$B$6:$B$1005,CONFIG!$H$17)) -> 0 | I27: =IF(CONFIG!$H$17="",0,SUMIFS(GASTOS!$F$6:$F$1005,GASTOS!$K$6:$K$1005,I$5,GASTOS!$B$6:$B$1005,CONFIG!$H$17)) -> 0 | J27: =IF(CONFIG!$H$17="",0,SUMIFS(GASTOS!$F$6:$F$1005,GASTOS!$K$6:$K$1005,J$5,GASTOS!$B$6:$B$1005,CONFIG!$H$17)) -> 0 | ... N27: =IF(CONFIG!$H$17="",0,SUMIFS(GASTOS!$F$6:$F$1005,GASTOS!$K$6:$K$1005,N$5,GASTOS!$B$6:$B$1005,CONFIG!$H$17)) -> 0 | O27: =SUM(C27:N27) -> 0
B28: =CONFIG!$H$18 -> Otros gastos | C28: =IF(CONFIG!$H$18="",0,SUMIFS(GASTOS!$F$6:$F$1005,GASTOS!$K$6:$K$1005,C$5,GASTOS!$B$6:$B$1005,CONFIG!$H$18)) -> 0 | D28: =IF(CONFIG!$H$18="",0,SUMIFS(GASTOS!$F$6:$F$1005,GASTOS!$K$6:$K$1005,D$5,GASTOS!$B$6:$B$1005,CONFIG!$H$18)) -> 0 | E28: =IF(CONFIG!$H$18="",0,SUMIFS(GASTOS!$F$6:$F$1005,GASTOS!$K$6:$K$1005,E$5,GASTOS!$B$6:$B$1005,CONFIG!$H$18)) -> 0 | F28: =IF(CONFIG!$H$18="",0,SUMIFS(GASTOS!$F$6:$F$1005,GASTOS!$K$6:$K$1005,F$5,GASTOS!$B$6:$B$1005,CONFIG!$H$18)) -> 0 | G28: =IF(CONFIG!$H$18="",0,SUMIFS(GASTOS!$F$6:$F$1005,GASTOS!$K$6:$K$1005,G$5,GASTOS!$B$6:$B$1005,CONFIG!$H$18)) -> 0 | H28: =IF(CONFIG!$H$18="",0,SUMIFS(GASTOS!$F$6:$F$1005,GASTOS!$K$6:$K$1005,H$5,GASTOS!$B$6:$B$1005,CONFIG!$H$18)) -> 0 | I28: =IF(CONFIG!$H$18="",0,SUMIFS(GASTOS!$F$6:$F$1005,GASTOS!$K$6:$K$1005,I$5,GASTOS!$B$6:$B$1005,CONFIG!$H$18)) -> 0 | J28: =IF(CONFIG!$H$18="",0,SUMIFS(GASTOS!$F$6:$F$1005,GASTOS!$K$6:$K$1005,J$5,GASTOS!$B$6:$B$1005,CONFIG!$H$18)) -> 0 | ... N28: =IF(CONFIG!$H$18="",0,SUMIFS(GASTOS!$F$6:$F$1005,GASTOS!$K$6:$K$1005,N$5,GASTOS!$B$6:$B$1005,CONFIG!$H$18)) -> 0 | O28: =SUM(C28:N28) -> 0
B29: =CONFIG!$H$19 -> 0 | C29: =IF(CONFIG!$H$19="",0,SUMIFS(GASTOS!$F$6:$F$1005,GASTOS!$K$6:$K$1005,C$5,GASTOS!$B$6:$B$1005,CONFIG!$H$19)) -> 0 | D29: =IF(CONFIG!$H$19="",0,SUMIFS(GASTOS!$F$6:$F$1005,GASTOS!$K$6:$K$1005,D$5,GASTOS!$B$6:$B$1005,CONFIG!$H$19)) -> 0 | E29: =IF(CONFIG!$H$19="",0,SUMIFS(GASTOS!$F$6:$F$1005,GASTOS!$K$6:$K$1005,E$5,GASTOS!$B$6:$B$1005,CONFIG!$H$19)) -> 0 | F29: =IF(CONFIG!$H$19="",0,SUMIFS(GASTOS!$F$6:$F$1005,GASTOS!$K$6:$K$1005,F$5,GASTOS!$B$6:$B$1005,CONFIG!$H$19)) -> 0 | G29: =IF(CONFIG!$H$19="",0,SUMIFS(GASTOS!$F$6:$F$1005,GASTOS!$K$6:$K$1005,G$5,GASTOS!$B$6:$B$1005,CONFIG!$H$19)) -> 0 | H29: =IF(CONFIG!$H$19="",0,SUMIFS(GASTOS!$F$6:$F$1005,GASTOS!$K$6:$K$1005,H$5,GASTOS!$B$6:$B$1005,CONFIG!$H$19)) -> 0 | I29: =IF(CONFIG!$H$19="",0,SUMIFS(GASTOS!$F$6:$F$1005,GASTOS!$K$6:$K$1005,I$5,GASTOS!$B$6:$B$1005,CONFIG!$H$19)) -> 0 | J29: =IF(CONFIG!$H$19="",0,SUMIFS(GASTOS!$F$6:$F$1005,GASTOS!$K$6:$K$1005,J$5,GASTOS!$B$6:$B$1005,CONFIG!$H$19)) -> 0 | ... N29: =IF(CONFIG!$H$19="",0,SUMIFS(GASTOS!$F$6:$F$1005,GASTOS!$K$6:$K$1005,N$5,GASTOS!$B$6:$B$1005,CONFIG!$H$19)) -> 0 | O29: =SUM(C29:N29) -> 0
B30: =CONFIG!$H$20 -> 0 | C30: =IF(CONFIG!$H$20="",0,SUMIFS(GASTOS!$F$6:$F$1005,GASTOS!$K$6:$K$1005,C$5,GASTOS!$B$6:$B$1005,CONFIG!$H$20)) -> 0 | D30: =IF(CONFIG!$H$20="",0,SUMIFS(GASTOS!$F$6:$F$1005,GASTOS!$K$6:$K$1005,D$5,GASTOS!$B$6:$B$1005,CONFIG!$H$20)) -> 0 | E30: =IF(CONFIG!$H$20="",0,SUMIFS(GASTOS!$F$6:$F$1005,GASTOS!$K$6:$K$1005,E$5,GASTOS!$B$6:$B$1005,CONFIG!$H$20)) -> 0 | F30: =IF(CONFIG!$H$20="",0,SUMIFS(GASTOS!$F$6:$F$1005,GASTOS!$K$6:$K$1005,F$5,GASTOS!$B$6:$B$1005,CONFIG!$H$20)) -> 0 | G30: =IF(CONFIG!$H$20="",0,SUMIFS(GASTOS!$F$6:$F$1005,GASTOS!$K$6:$K$1005,G$5,GASTOS!$B$6:$B$1005,CONFIG!$H$20)) -> 0 | H30: =IF(CONFIG!$H$20="",0,SUMIFS(GASTOS!$F$6:$F$1005,GASTOS!$K$6:$K$1005,H$5,GASTOS!$B$6:$B$1005,CONFIG!$H$20)) -> 0 | I30: =IF(CONFIG!$H$20="",0,SUMIFS(GASTOS!$F$6:$F$1005,GASTOS!$K$6:$K$1005,I$5,GASTOS!$B$6:$B$1005,CONFIG!$H$20)) -> 0 | J30: =IF(CONFIG!$H$20="",0,SUMIFS(GASTOS!$F$6:$F$1005,GASTOS!$K$6:$K$1005,J$5,GASTOS!$B$6:$B$1005,CONFIG!$H$20)) -> 0 | ... N30: =IF(CONFIG!$H$20="",0,SUMIFS(GASTOS!$F$6:$F$1005,GASTOS!$K$6:$K$1005,N$5,GASTOS!$B$6:$B$1005,CONFIG!$H$20)) -> 0 | O30: =SUM(C30:N30) -> 0
B31: TOTAL GASTOS DE OPERACIÓN | C31: =SUM(C14:C30) -> 0 | D31: =SUM(D14:D30) -> 0 | E31: =SUM(E14:E30) -> 0 | F31: =SUM(F14:F30) -> 0 | G31: =SUM(G14:G30) -> 0 | H31: =SUM(H14:H30) -> 0 | I31: =SUM(I14:I30) -> 0 | J31: =SUM(J14:J30) -> 0 | ... N31: =SUM(N14:N30) -> 0 | O31: =SUM(C31:N31) -> 2372680.2
B32: UTILIDAD OPERATIVA (antes de impuestos) | C32: =C11-C31 -> 0 | D32: =D11-D31 -> 0 | E32: =E11-E31 -> 0 | F32: =F11-F31 -> 0 | G32: =G11-G31 -> 0 | H32: =H11-H31 -> 0 | I32: =I11-I31 -> 0 | J32: =J11-J31 -> 0 | ... N32: =N11-N31 -> 0 | O32: =SUM(C32:N32) -> -2151073.5
B33: Margen operativo % | C33: =IFERROR(C32/C9,0) -> 0 | D33: =IFERROR(D32/D9,0) -> 0 | E33: =IFERROR(E32/E9,0) -> 0 | F33: =IFERROR(F32/F9,0) -> 0 | G33: =IFERROR(G32/G9,0) -> 0 | H33: =IFERROR(H32/H9,0) -> 0 | I33: =IFERROR(I32/I9,0) -> 0 | J33: =IFERROR(J32/J9,0) -> 0 | ... O33: =IFERROR(O32/O9,0) -> -6.285785
B34: (−) Impuesto sobre la renta estimado | C34: =IF(C32>0,C32*RENTA,0) -> 0 | D34: =IF(D32>0,D32*RENTA,0) -> 0 | E34: =IF(E32>0,E32*RENTA,0) -> 0 | F34: =IF(F32>0,F32*RENTA,0) -> 0 | G34: =IF(G32>0,G32*RENTA,0) -> 0 | H34: =IF(H32>0,H32*RENTA,0) -> 0 | I34: =IF(I32>0,I32*RENTA,0) -> 0 | J34: =IF(J32>0,J32*RENTA,0) -> 0 | ... N34: =IF(N32>0,N32*RENTA,0) -> 0 | O34: =SUM(C34:N34) -> 0
B35: UTILIDAD NETA | C35: =C32-C34 -> 0 | D35: =D32-D34 -> 0 | E35: =E32-E34 -> 0 | F35: =F32-F34 -> 0 | G35: =G32-G34 -> 0 | H35: =H32-H34 -> 0 | I35: =I32-I34 -> 0 | J35: =J32-J34 -> 0 | ... N35: =N32-N34 -> 0 | O35: =SUM(C35:N35) -> -2151073.5
B36: INDICADORES
B37: Food cost % (costo ventas ÷ ventas netas) | C37: =IFERROR(C10/C9,0) -> 0 | D37: =IFERROR(D10/D9,0) -> 0 | E37: =IFERROR(E10/E9,0) -> 0 | F37: =IFERROR(F10/F9,0) -> 0 | G37: =IFERROR(G10/G9,0) -> 0 | H37: =IFERROR(H10/H9,0) -> 0 | I37: =IFERROR(I10/I9,0) -> 0 | J37: =IFERROR(J10/J9,0) -> 0 | ... O37: =IFERROR(O10/O9,0) -> 0.35242938
B38: Labor cost % (planilla ÷ ventas netas) | C38: =IFERROR(C15/C9,0) -> 0 | D38: =IFERROR(D15/D9,0) -> 0 | E38: =IFERROR(E15/E9,0) -> 0 | F38: =IFERROR(F15/F9,0) -> 0 | G38: =IFERROR(G15/G9,0) -> 0 | H38: =IFERROR(H15/H9,0) -> 0 | I38: =IFERROR(I15/I9,0) -> 0 | J38: =IFERROR(J15/J9,0) -> 0 | ... O38: =IFERROR(O15/O9,0) -> 4.9376506
B39: Prime cost % (costo ventas + planilla) | C39: =IFERROR((C10+C15)/C9,0) -> 0 | D39: =IFERROR((D10+D15)/D9,0) -> 0 | E39: =IFERROR((E10+E15)/E9,0) -> 0 | F39: =IFERROR((F10+F15)/F9,0) -> 0 | G39: =IFERROR((G10+G15)/G9,0) -> 0 | H39: =IFERROR((H10+H15)/H9,0) -> 0 | I39: =IFERROR((I10+I15)/I9,0) -> 0 | J39: =IFERROR((J10+J15)/J9,0) -> 0 | ... O39: =IFERROR((O10+O15)/O9,0) -> 5.2900799
B40: IVA DEL MES (referencia para la declaración)
